Workbook

Sheet Input Data
A1: KODE | B1: TANGGAL | C1: NAMA | D1: WHATSAPP | E1: SOURCE | F1: AGEN | G1: STATUS | H1: PAKET / DESTINASI | I1: TANGGAL TRIP | J1: PAX | K1: ESTIMASI NILAI ORDER | L1: KETERANGAN | M1: TAHAPAN (STATUS) | N1: ANALISA AI
A2: 2601A001 | B2: 46023 | C2: Cynthia | D2: 081249880600 | E2: Website | F2: Alvin | G2: Closing | H2: Menjangan Tabuhan | I2: 46025 | J2: 10+1 | K2: 7905000 | L2: tambah foto video | M2: {=IF( G2:G5505="", "", IFERROR( IFS( G2:G5505="Leads Baru",1, G2:G5505="Qualified",2, G2:G5505="Prospek",3, G2:G5505="Follow Up",4, G2:G5505="Warm Leads",5, G2:G5505="Hot Leads",6, G2:G5505="Closing",7, G2:G5505="Gagal",8 ), 99 ) )} -> 7
A3: 2601A002 | B3: 46023 | C3: Dewitri | D3: 085776495791 | E3: Website | F3: Alvin | G3: Gagal | H3: Kawah ijen | I3: 46023 | J3: 3 | M3: 8
A4: 2601A003 | B4: 46024 | C4: Ulil albab | D4: 08561542812 | E4: Website | F4: Alvin | G4: Gagal | H4: Trip MT | I4: 46024 | J4: 4 | L4: Over budget | M4: 8
A5: 2601A004 | B5: 46024 | C5: Anto | D5: 0818950503 | E5: Website | F5: Alvin | G5: Gagal | L5: jadinya ke malang | M5: 8
A6: 2601A005 | B6: 46026 | C6: Tjen bie | D6: 081330627337 | E6: Website | F6: Alvin | G6: Gagal | H6: 3H2M Z | I6: 46027 | J6: 2 | L6: Jadi ke lovina | M6: 8
A7: 2601A006 | B7: 46027 | C7: Anindita purnamasari | D7: 082233330301 | E7: Website | F7: Alvin | G7: Gagal | H7: 2H1M | J7: 2 | L7: dikabari jika jadi ambil paketnya | M7: 8
A8: 2601A007 | B8: 46027 | C8: Riska | D8: 08994700800 | E8: Website | F8: Alvin | G8: Gagal | H8: 3H2M A | J8: 10 | L8: tanya tanya, masih blm jawab follow up | M8: 8
A9: 2601A008 | B9: 46029 | C9: Helmi | D9: 083826179860‬ | E9: Website | F9: Alvin | G9: Gagal | H9: 1D IB | I9: 46030 | J9: 3 | K9: 2076000 | L9: order | M9: 8
A10: 2601A009 | B10: 46030 | C10: Ruly | D10: 08170934898 | E10: Website | F10: Alvin | G10: Gagal | H10: 3H2M A | J10: 2 | L10: Tidak jawab | M10: 8
A11: 2601A010 | B11: 46030 | C11: Stephan | D11: 085105912829 | E11: Website | F11: Alvin | G11: Gagal | H11: 4H3M | I11: akhir januari | J11: 2 | L11: lagi pikir-pikir, FU pertengahan januari | M11: 8
A12: 2601A011 | B12: 46031 | C12: carone | D12: 0877933043674 | E12: Lainnya | F12: Alvin | G12: Gagal | H12: 3H2M | L12: Masih tanya tanya | M12: 8
A13: 2601D001 | B13: 46023 | C13: H | D13: 082114698226 | E13: Instagram | F13: Dela | G13: Gagal | H13: 2H1M | I13: 16-18 januari | L13: Nanti dikabari | M13: 8
A14: 2601A012 | B14: 46031 | C14: Giet | D14: 085377504433 | E14: Website | F14: Alvin | G14: Gagal | H14: 3H2M | L14: masih tanya tanya | M14: 8
A15: 2601D002 | B15: 46023 | C15: Ari.Januari.2026 | D15: 0881036053274 | E15: Website | F15: Dela | G15: Gagal | H15: CT | L15: ingin paket campervan | M15: 8
A16: 2601A013 | B16: 46032 | C16: Deni Sultan | D16: 081912435459‬ | E16: Website | F16: Alvin | G16: Closing | H16: MT | I16: 46046 | J16: 2 | K16: 590000 | L16: order | M16: 7
A17: 2601D003 | B17: 46023 | C17: Muliono | D17: 085851219044 | E17: Website | F17: Dela | G17: Gagal | H17: Trip baluran | J17: 7 | L17: Tidak jawab | M17: 8
A18: 2601D004 | B18: 46023 | C18: Berliana | D18: 085806069951 | E18: Instagram | F18: Dela | G18: Gagal | H18: one day trip | L18: Tidak jawab | M18: 8
A19: 2601D005 | B19: 46023 | C19: Muhammad Amrullah a.k | D19: 081393712742 | E19: Instagram | F19: Dela | G19: Gagal | H19: custom 3H2M | I19: Maret Akhir atau April | J19: 7 | K19: =1603393*7 -> 11223751 | L19: tidak ada jawaban | M19: 8
A20: 2601D006 | B20: 46023 | C20: Prima Gita | D20: 081284286428 | E20: Instagram | F20: Dela | G20: Gagal | H20: 2H1M opsi a | I20: menentukan waktu | L20: Tidak jawab | M20: 8
A21: 2601D007 | B21: 46023 | C21: Mia Bella | D21: 08133977533 | E21: Instagram | F21: Dela | G21: Gagal | H21: Ijen Baluran one day trip | I21: 46026 | J21: 2 | L21: 1 wni 1 wna, tdk jawab | M21: 8
A22: 2601D008 | B22: 46023 | C22: Kai | D22: 081399930501 | E22: Instagram | F22: Dela | G22: Gagal | H22: ot 3h2m | I22: 9-11 Januari 26 | L22: lewat tanggal | M22: 8
A23: 2601D009 | B23: 46024 | C23: Iin Noor Chozin | D23: 081233197590 | E23: Website | F23: Dela | G23: Closing | H23: Trip Menjangan Tabuhan | I23: 46025 | J23: 6 | K23: =410000*6 -> 2460000 | L23: menjangan tabuhan | M23: 7
A24: 2601D010 | B24: 46024 | C24: Dia Pur's | D24: 082360390604 | E24: Instagram | F24: Dela | G24: Gagal | H24: custom 2h1m | I24: 3 4 februari | J24: 4 | L24: tanggal lewat | M24: 8
A25: 2601D011 | B25: 46024 | C25: Inggrid | D25: 085156507128 | E25: Instagram | F25: Dela | G25: Gagal | H25: OT Januari | I25: Januari | L25: tidak jawab | M25: 8
A26: 2601D012 | B26: 46024 | C26: Kartika | D26: 082143617625 | E26: Website | F26: Dela | G26: Closing | H26: OT Menjangan Tabuhan | I26: 46033 | J26: 4 | K26: =295000*4 -> 1180000 | M26: 7
A27: 2601D013 | B27: 46024 | C27: Diyatrana | D27: 085729990708 | E27: Instagram | F27: Dela | G27: Gagal | H27: 3H2M opsi A | L27: tidak jawab | M27: 8
A28: 2601D014 | B28: 46024 | C28: Peni | D28: 081553992808 | E28: Instagram | F28: Dela | G28: Gagal | H28: Trip Pulau Bedil | I28: 46104 | J28: 4 | K28: =640000+192000*4 -> 1408000 | L28: pindah haluan liburan | M28: 8
A29: 2601D015 | B29: 46024 | C29: Kirana | D29: 085777785090 | E29: Website | F29: Dela | G29: Review | H29: custom 2h1m | I29: 6 -7 Februari | J29: 40 | K29: =2051220*20 -> 41024400 | L29: MINTA PAKET, fu akhir januari | M29: 99
A30: 2601D016 | B30: 46024 | C30: Ika W/ Ibu ms Nasir | D30: 0882007680200 | E30: Website | F30: Dela | G30: Gagal | H30: 2H1M opsi C | I30: 46170 | J30: 17 | L30: ganti ke bromo | M30: 8
A31: 2601D017 | B31: 46024 | C31: Karen | D31: 087772484641 | E31: Instagram | F31: Dela | G31: Gagal | H31: 2 paket open trip | I31: 4 dan 5 Maret 226 | J31: 2 | K31: =525000*2 -> 1050000 | L31: follow up tanggal 15 februari | M31: 8
A32: 2601D018 | B32: 46024 | C32: Tiyas | D32: 082136195477 | E32: Lainnya | F32: Dela | G32: Gagal | H32: Custom 2h1m | I32: 16 17 Januari 2026 | J32: 2 | L32: Minta Paket, fu tgl 10 | M32: 8
A33: 2601D019 | B33: 46025 | C33: Beta Amrina | D33: 082327577538 | E33: Instagram | F33: Dela | G33: Gagal | H33: OT | I33: Mei 14-16 2026 | J33: 3 | K33: =1600000*3 -> 4800000 | L33: tidak jawab | M33: 8
A34: 2601D020 | B34: 46025 | C34: Wa | D34: 085641568779 | E34: Lainnya | F34: Dela | G34: Gagal | H34: ot djawatan baluran | L34: tidak jawab | M34: 8
A35: 2601D021 | B35: 46025 | C35: Buds | D35: 085720585703 | E35: Website | F35: Dela | G35: Gagal | H35: Baluran private | L35: tidak jawab | M35: 8
A36: 2601D022 | B36: 46025 | C36: Seysa | D36: 085886980015 | E36: Instagram | F36: Dela | G36: Gagal | H36: trip kawah wurung | I36: 46028 | J36: 3 | L36: masih pikir2 dulu, sudah lewat tgl | M36: 8
A37: 2601D023 | B37: 46025 | C37: Nothing | D37: 085820515179 | E37: Website | F37: Dela | G37: Gagal | H37: Trip Kawah Ijen | L37: mepo sby atau gresik | M37: 8
A38: 2601D024 | B38: 46025 | C38: Dhevy Hariady | D38: 082282391601 | E38: Instagram | F38: Dela | G38: Gagal | H38: trip djawatan baluran | I38: Bulan Juni | J38: 4 | K38: =499000*4 -> 1996000 | L38: tidak jadi liburan ke BWI | M38: 8 | N38: https://docs.google.com/document/d/1wA6Vstebr_OPv-YiZuHCtRJ0dphAaw92AabZKFpW9i0/edit?tab=t.0
A39: 2601D025 | B39: 46025 | C39: Ratu (Bunda FazZZam) | D39: 081806567775 | E39: Instagram | F39: Dela | G39: Gagal | H39: OT 3H2M | L39: masih ngomong ke atasan | M39: 8
A40: 2601D026 | B40: 46025 | C40: Gilang | D40: 081221614470 | E40: Website | F40: Dela | G40: Closing | H40: Private Trip Kawah Wurung | I40: 46026 | J40: 1 | K40: 2318100 | M40: 7
A41: 2601D027 | B41: 46025 | C41: Farus nabil | D41: 081293944286 | E41: Instagram | F41: Dela | G41: Closing | H41: Private Trip Menjangan Tabuhan | I41: 46032 | J41: 5 | K41: 2300000 | M41: 7
A42: 2601D028 | B42: 46025 | C42: Rehan | D42: 08963381584 | E42: Instagram | F42: Dela | G42: Gagal | H42: 2H1M | I42: 24 dan 25 Maret | J42: 5 | K42: =1845000*5 -> 9225000 | L42: tidak ada jawaban | M42: 8
A43: 2601D029 | B43: 46025 | C43: Nella Holiday | D43: 089672570321 | E43: Website | F43: Dela | G43: Gagal | H43: trip ijen | I43: 46039 | J43: 14 | L43: SDH FOLLOW UP | M43: 8
A44: 2601D030 | B44: 46026 | C44: Cika | D44: 085782656823 | E44: Instagram | F44: Dela | G44: Gagal | H44: Trip 3H2M | I44: Bulan April | L44: tidak ada jawaban | M44: 8
A45: 2601D031 | B45: 46026 | C45: Sulistio W.N | D45: 082137405814 | E45: Website | F45: Dela | G45: Gagal | H45: 3H2M opsi B | L45: tanya yacht boom, fu tgl 15 | M45: 8
A46: 2601D032 | B46: 46026 | C46: Thata Anggitha | D46: 082137405814 | E46: Instagram | F46: Dela | G46: Gagal | J46: 2 | L46: sudah follow up | M46: 8
A47: 2601D033 | B47: 46026 | C47: Aris Guntoro | D47: 081355209321 | E47: Website | F47: Dela | G47: Closing | H47: Trip Kawah Ijen | I47: 46038 | J47: 4 | K47: =314000*5 -> 1570000 | L47: sudah closing | M47: 7
A48: 2601D034 | B48: 46026 | C48: Rizal Pratama | D48: 082216912039 | E48: Instagram | F48: Dela | G48: Gagal | H48: 3H2M opsi A | I48: Februari | J48: 30 | L48: sudah sm rekan lain | M48: 8
A49: 2601D035 | B49: 46026 | C49: Surya | D49: 081803536960 | E49: Website | F49: Dela | G49: Gagal | H49: Trip Menjangan Tabuhan | J49: 25 | L49: tidak cocok harga | M49: 8
A50: 2601D036 | B50: 46026 | C50: Yaya | D50: 089612554076 | E50: Instagram | F50: Dela | G50: Gagal | H50: OT 3H2M | L50: tidak jawab | M50: 8
A51: 2601D037 | B51: 46026 | C51: Hums GPS Malang | D51: 085888433436 | E51: Instagram | F51: Dela | G51: Gagal | H51: 2H1M | L51: minta jpt sby | M51: 8
A52: 2601D038 | B52: 46026 | C52: Sary Maheswari | D52: 085729077777 | E52: Instagram | F52: Dela | G52: Gagal | H52: 2H1M | I52: 9-10 Januari 26 | J52: 6 | L52: tanya paket, lewat tanggal | M52: 8
A53: 2601D039 | B53: 46027 | C53: Tanamalintan | D53: 083877965575 | E53: Website | F53: Dela | G53: Gagal | H53: 2H1M | I53: lebaran/libur sekolah | J53: 60 | L53: tunda lebaran tahun depan | M53: 8
A54: 2601D040 | B54: 46027 | C54: Gian Septim Rohmaduri | D54: 081328834222 | E54: Instagram | F54: Dela | G54: Gagal | J54: 10 | L54: ga ada jawaban | M54: 8
A55: 2601D041 | B55: 46027 | C55: Bidadari Surga | D55: 082136616696 | E55: Instagram | F55: Dela | G55: Gagal | H55: 3H2M | I55: APRIL | J55: 27 | L55: FU MARET | M55: 8
A56: 2601D042 | B56: 46027 | C56: Rosa Tan | D56: 08562877979 | E56: Lainnya | F56: Dela | G56: Gagal | H56: 3H2M OR 2H1M | I56: bulan juni | J56: 50 | K56: =900000*50 -> 45000000 | L56: DESTINASI SENIOR FRIENDLY, follow up mei | M56: 8
A57: 2601D043 | B57: 46027 | C57: Dwi K | D57: 0811822328 | E57: Website | F57: Dela | G57: Gagal | H57: OT 3h2m | I57: 14-16 feeb | L57: tidak jawab | M57: 8
A58: 2601D044 | B58: 46027 | C58: Dian Indra | D58: 08123589756 | E58: Instagram | F58: Dela | G58: Closing | H58: 2H1M opsi c | J58: 4 | K58: 4090000 | L58: sudah closing | M58: 7
A59: 2601D045 | B59: 46027 | C59: D. Luhki | D59: 0818575855 | E59: Lainnya | F59: Dela | G59: Gagal | H59: 2D1N | J59: 60 | L59: sdh fu tanggal 17 | M59: 8
A60: 2601D046 | B60: 46027 | C60: Erlangga | D60: 0895340047293 | E60: Website | F60: Dela | G60: Gagal | H60: 3H2M | I60: Februari | J60: 100 | K60: 134600000 | L60: tidak ada jawaban | M60: 8
A61: 2601D047 | B61: 46027 | C61: KAI WNA | D61: 4915736805277 | E61: Website | F61: Dela | G61: Gagal | H61: TN ALAS PURWO | J61: 2 | L61: tdk ada kelanjutan | M61: 8
A62: 2601D048 | B62: 46027 | C62: Nww | D62: 082232269773 | E62: Website | F62: Dela | G62: Gagal | M62: 8
A63: 2601D049 | B63: 46027 | C63: Fjr | D63: 081937743496 | E63: Instagram | F63: Dela | G63: Gagal | H63: trip bedil | I63: AKHIR JANUARI | L63: tidak jawab | M63: 8
A64: 2601D050 | B64: 46027 | C64: Agus Trisunu | D64: 082198600529 | E64: Website | F64: Dela | G64: Gagal | H64: 3H2M | I64: 46042 | J64: 2 | L64: batal | M64: 8
A65: 2601D051 | B65: 46027 | C65: SriH fai hai | D65: 081317770228 | E65: Instagram | F65: Dela | G65: Closing | H65: 3H2M | K65: 6400000 | M65: 7
A66: 2601D052 | B66: 46027 | C66: Athaya | D66: 087786696160 | E66: Lainnya | F66: Dela | G66: Gagal | H66: OT 1 day | I66: 46042 | J66: 1 | L66: tidak ada barengan | M66: 8
A67: 2601D053 | B67: 46028 | C67: Beni Kosnadi | D67: 082297981197 | E67: Instagram | F67: Dela | G67: Gagal | H67: OT 1 day Menjangan | I67: 46039 | J67: 1 | L67: sdh dapat trip | M67: 8
A68: 2601D054 | B68: 46028 | C68: Nsyw | D68: 085156302725 | E68: Instagram | F68: Dela | G68: Gagal | H68: OT 3H2M | L68: masih liat katalog | M68: 8
A69: 2601D055 | B69: 46028 | C69: Hari setiyawati | D69: 085921091374 | E69: Website | F69: Dela | G69: Gagal | H69: custom 3H2M | J69: 18 | L69: tidak jadi budged tidak cukup | M69: 8
A70: 2601D056 | B70: 46028 | C70: Robby rinaldy | D70: 082122227424 | E70: Instagram | F70: Dela | G70: Gagal | I70: 46038 | J70: 1 | L70: CARI TEMEN TRIP, lwt tanggal | M70: 8
A71: 2601D057 | B71: 46028 | C71: Farrel Raynaldi | D71: 087762831355 | E71: Website | F71: Dela | G71: Gagal | H71: 3H2M | J71: 30 | L71: tidak jawab | M71: 8
A72: 2601D058 | B72: 46028 | C72: Hajar adiwiyana | D72: 085755999900 | E72: Instagram | F72: Dela | G72: Gagal | H72: 2H1M | J72: 2 | L72: pending ke bwi | M72: 8
A73: 2601D059 | B73: 46028 | C73: Weny | D73: 08125262656 | E73: Website | F73: Dela | G73: Gagal | H73: 2H1M | L73: start sby | M73: 8
A74: 2601D060 | B74: 46028 | C74: Yande BaliBagus | D74: 081225318054 | E74: Website | F74: Dela | G74: Gagal | H74: 2H1M (trekking ijen) | I74: 14 - 16 maret | J74: 4 | K74: =3300000*2 -> 6600000 | L74: follow up akhir februari | M74: 8
A75: 2601D061 | B75: 46028 | C75: Sinta julianti | D75: 085865365502 | E75: Instagram | F75: Dela | G75: Gagal | L75: tidak jawab | M75: 8
A76: 2601D062 | B76: 46029 | C76: Rachel | D76: 085775220152 | E76: Instagram | F76: Dela | G76: Gagal | I76: 46038 | L76: tidak jawab | M76: 8
A77: 2601D063 | B77: 46029 | C77: Sobar | D77: 081353674012 | E77: Lainnya | F77: Dela | G77: Gagal | H77: OT D TI | I77: 46030 | J77: 1 | L77: tidak ada barengan | M77: 8
A78: 2601D064 | B78: 46030 | C78: Nanik A | D78: 082225737622 | E78: Instagram | F78: Dela | G78: Gagal | H78: Trip djawatan baluran | I78: sekitar tgl 3-4 feb | J78: 3 | L78: nunggu jadwal cuti | M78: 8
A79: 2601D065 | B79: 46030 | C79: Ganang Age | D79: 0895363160977 | E79: Lainnya | F79: Dela | G79: Gagal | L79: tidak jawab | M79: 8
A80: 2601D066 | B80: 46030 | C80: Adhelia | D80: 082335290562 | E80: Lainnya | F80: Dela | G80: Gagal | H80: Trip baluran | J80: 4 | L80: ga jawab | M80: 8
A81: 2601D067 | B81: 46030 | C81: Khoirunnisa' linaas | D81: 081230352078 | E81: Instagram | F81: Dela | G81: Gagal | H81: tim building KW | I81: februari atau lebaran | J81: 100 | K81: =350000*50 -> 17500000 | L81: tidak ada jawaban | M81: 8
A82: 2601D068 | B82: 46030 | C82: No name WNA WNI | D82: 085784629188 | E82: Lainnya | F82: Dela | G82: Gagal | H82: custom desinasi | I82: bulan feb | J82: 2 | L82: buat penawaran, FU pertengahan jan | M82: 8
A83: 2601D069 | B83: 46030 | C83: No name Maret | D83: 081236371881 | E83: Instagram | F83: Dela | G83: Gagal | H83: OT 3H2M | I83: 23 - 25 maret | J83: 4 | K83: =1600000*4 -> 6400000 | L83: tidak ada jawaban, sudah fu 5 kali | M83: 8
A84: 2601D070 | B84: 46030 | C84: Alfian | D84: 085729019851 | E84: Lainnya | F84: Dela | G84: Gagal | H84: private trip | J84: 5 | L84: tanya tanya, sudah FU tgl 9 | M84: 8
A85: 2601D071 | B85: 46030 | C85: Terry sukma ezaria | D85: 081910004277 | E85: Instagram | F85: Dela | G85: Prospek | H85: paket custom | I85: 15 - 17 agustus | J85: 80 | K85: =1800000*80 -> 144000000 | L85: buat penawaran, FU 2 Juni | M85: 3 | N85: https://docs.google.com/document/d/1fMFdvXachGDtyak_UDLjTqjsPv8dJU-8h8riaob89KM/edit?tab=t.0
A86: 2601D072 | B86: 46030 | C86: Novia dian | D86: 087748304348 | E86: Instagram | F86: Dela | G86: Gagal | H86: OT 3H2M | I86: 12 19 bulan feb | J86: 1 | L86: tidak ada jawaban dan barengan, lewat tanggal | M86: 8
A87: 2601D073 | B87: 46031 | C87: Nusroh Linnas | D87: 08973257454 | E87: Instagram | F87: Dela | G87: Gagal | L87: tanya terkait dokumentasi | M87: 8
A88: 2601D074 | B88: 46031 | C88: Khalisa | D88: 082159266648 | E88: Instagram | F88: Dela | G88: Gagal | H88: Open trip MT | I88: bulan juni | J88: 4 | K88: =295000*5 -> 1475000 | L88: gajadi liburan tahun inii | M88: 8 | N88: https://docs.google.com/document/d/1vdzggSvQW_6p_JDwwPzKp9o4Qo3PymCg6LpFHcmIR1M/edit?tab=t.0
A89: 2601D075 | B89: 46031 | C89: Arifah | D89: 085174307926 | E89: Instagram | F89: Dela | G89: Review | H89: Trip 4H3M | I89: sekitar hari raya | J89: 4 | K89: =2115000*4 -> 8460000 | L89: sdh closing | M89: 99
A90: 2601D076 | B90: 46031 | C90: Livia | D90: 085786328047 | E90: Instagram | F90: Dela | G90: Gagal | I90: maret april | L90: di FU tidak balas | M90: 8 | N90: https://docs.google.com/document/d/1GT9NMnoa3lcZIxGW9QCfVEc-3eBA1sFnuwQzkzq4o4M/edit?tab=t.0
A91: 2601D077 | B91: 46031 | C91: Helsa | D91: 085721780257 | E91: Instagram | F91: Dela | G91: Gagal | J91: 2 | L91: tanya tanya, FU tgl 11 | M91: 8
A92: 2601D078 | B92: 46031 | C92: Muawanah | D92: 08111626220 | E92: Lainnya | F92: Dela | G92: Gagal | H92: OT 3H2M | L92: nunggu info tanggal, FU tgl 11 | M92: 8
A93: 2601D079 | B93: 46031 | C93: Anis dadik | D93: 081238722671 | E93: Instagram | F93: Dela | G93: Gagal | H93: Trip 3H2M | J93: 2 | L93: menunggu kabar selanjutnya, FU tgl 11 | M93: 8
A94: 2601D080 | B94: 46031 | C94: Tya mardin F.A | D94: 081297769438 | E94: Lainnya | F94: Dela | G94: Gagal | L94: tanya mepo | M94: 8
A95: 2601D081 | B95: 46032 | C95: Evi yemima | D95: 08973106657 | E95: Instagram | F95: Dela | G95: Gagal | H95: 2H1M opsi C | L95: tanya tanya | M95: 8
A96: 2601D082 | B96: 46032 | C96: Yuninda cahyani | D96: 08562899073 | E96: Lainnya | F96: Dela | G96: Gagal | H96: opsi 3H2M | L96: cuaca tidak bersahabat | M96: 8
A97: 2601D083 | B97: 46032 | C97: Pel | D97: 081211252959 | E97: Instagram | F97: Dela | G97: Review | H97: custom 2H1M | I97: 15 feb - 16 feb | J97: 4 | K97: 6800000 | L97: FU AKHIR JANUARI | M97: 99
A98: 2601D084 | B98: 46032 | C98: Wiwit supranata | D98: 085640533187 | E98: Lainnya | F98: Dela | G98: Review | H98: Tim building PT SBI | I98: 46066 | J98: 38 | K98: 36753000 | L98: penawaran | M98: 99
A99: 2601D085 | B99: 46032 | C99: Cindy alicia | D99: 085782665535 | E99: Instagram | F99: Dela | G99: Closing | H99: OT one day D, B | I99: 46037 | J99: 3 | K99: =550000*3 -> 1650000 | M99: 7
A100: 2601D086 | B100: 46032 | C100: Adhiww | D100: 08921872710 | E100: Website | F100: Dela | G100: Gagal | H100: OP kawah ijen | I100: 46038 | J100: 2 | L100: tanya tanya, lewat tanggal | M100: 8
...

Sheet Tahapan Leads
B3: Nomer | C3: Tahapan | D3: Keterangan | E3: Next Action | F3: Yes | G3: No
B4: 1 | C4: Leads Baru | D4: Menyapa dan tanya informasi | E4: Mengulik kebutuhan | F4: Masuk tahap 2 | G4: Follow up ringan (H+1), jika tidak respon → arsip sementara, lebih dari seminggu jadi gagal
B5: 2 | C5: Qualified | D5: Menyampaikan kebutuhan | E5: Kirim penawaran | F5: Masuk tahap 3 | G5: Edukasi ulang / klarifikasi kebutuhan (jangan kirim promo)
B6: 3 | C6: Prospek | D6: Sudah tertarik tapi belum komitmen | E6: Edukasi, beri kepercayaan, kirim voice note, tawari telfon | F6: Masuk tahap 4 | G6: Jadwalkan follow up (H+2 / H+3)
B7: 4 | C7: Follow Up | D7: Sudah dikasih edukasi tapi belum komitmen | E7: Menanyakan atau membuat janji waktu follow up | F7: Masuk tahap 5 | G7: Pindahkan ke Warm Leads (cooling)
B8: 5 | C8: Warm Leads | D8: Sudah difollowup tapi belum komitmen juga | E8: Kasih urgency slot atau bonus atau promo | F8: Masuk tahap 6 | G8: Pending / Dormant (tunggu momen, jangan kejar terus)
B9: 6 | C9: Hot Leads | D9: Terima form reservasi / terima invoice | E9: Menanyakan DP | F9: Masuk tahap 7 | G9: Follow up deadline DP (H+1), jika gagal → balik ke Warm
B10: 7 | C10: Closing | D10: Sudah reservasi | E10: Input data reservasi, kirim form reservasi ke grup, kirim itinerary & RAB ke Business Operation
B11: 8 | C11: Review | D11: Meminta review ke tamu setelah trip selesai | E11: Laporan ke Business Operation
B14: 1 | C14: Meminta itinerary dan RAB ke sales
B15: 2 | C15: Koordinasi dengan sales vendor mana aja yang sudah dipesan dan belum dipesan
B16: 3 | C16: Membuat list vendor yang belum dipesan sama sales
B17: 4 | C17: Memesan vendor yang belum dipesan sama sales
B18: 5 | C18: Update data reservasi ketika sudah ready
B19: 6 | C19: Memastikan ulang semua ready di H-3 trip
B20: 7 | C20: Monitoring saat trip berjalan
B21: 8 | C21: Follow up ke crew untuk meminta sumber leads tamu dan kirim link review
B22: 9 | C22: Ketika trip selesai, menanyakan laporan trip ke crew yang bertugas
B23: 10 | C23: Kirim nomer PIC ke crew yang bertugas untuk laporan operasional trip
B24: 11 | C24: Meminta review ke tamu jika tamu belum review di google business H+3

Sheet Leads_Dela
A1: =IFERROR(__xludf.DUMMYFUNCTION("QUERY( 'Input Data'!A1:N5505, ""select B, A, C, D, E, G, H, I, J, K, L, N where F = 'Dela'"", 1 ) "),"TANGGAL") -> TANGGAL | B1: =IFERROR(__xludf.DUMMYFUNCTION("""COMPUTED_VALUE"""),"KODE") -> KODE | C1: =IFERROR(__xludf.DUMMYFUNCTION("""COMPUTED_VALUE"""),"NAMA") -> NAMA | D1: =IFERROR(__xludf.DUMMYFUNCTION("""COMPUTED_VALUE"""),"WHATSAPP") -> WHATSAPP | E1: =IFERROR(__xludf.DUMMYFUNCTION("""COMPUTED_VALUE"""),"SOURCE") -> SOURCE | F1: =IFERROR(__xludf.DUMMYFUNCTION("""COMPUTED_VALUE"""),"STATUS") -> STATUS | G1: =IFERROR(__xludf.DUMMYFUNCTION("""COMPUTED_VALUE"""),"PAKET / DESTINASI") -> PAKET / DESTINASI | H1: =IFERROR(__xludf.DUMMYFUNCTION("""COMPUTED_VALUE"""),"TANGGAL TRIP") -> TANGGAL TRIP | I1: =IFERROR(__xludf.DUMMYFUNCTION("""COMPUTED_VALUE"""),"PAX") -> PAX | J1: =IFERROR(__xludf.DUMMYFUNCTION("""COMPUTED_VALUE"""),"ESTIMASI NILAI ORDER") -> ESTIMASI NILAI ORDER | K1: =IFERROR(__xludf.DUMMYFUNCTION("""COMPUTED_VALUE"""),"KETERANGAN") -> KETERANGAN | L1: =IFERROR(__xludf.DUMMYFUNCTION("""COMPUTED_VALUE"""),"ANALISA AI") -> ANALISA AI
A2: =IFERROR(__xludf.DUMMYFUNCTION("""COMPUTED_VALUE"""),46023.0) -> 46023 | B2: =IFERROR(__xludf.DUMMYFUNCTION("""COMPUTED_VALUE"""),"2601D001") -> 2601D001 | C2: =IFERROR(__xludf.DUMMYFUNCTION("""COMPUTED_VALUE"""),"H ") -> H | D2: =IFERROR(__xludf.DUMMYFUNCTION("""COMPUTED_VALUE"""),"082114698226") -> 082114698226 | E2: =IFERROR(__xludf.DUMMYFUNCTION("""COMPUTED_VALUE"""),"Instagram") -> Instagram | F2: =IFERROR(__xludf.DUMMYFUNCTION("""COMPUTED_VALUE"""),"Gagal") -> Gagal | G2: =IFERROR(__xludf.DUMMYFUNCTION("""COMPUTED_VALUE"""),"2H1M") -> 2H1M | K2: =IFERROR(__xludf.DUMMYFUNCTION("""COMPUTED_VALUE"""),"Nanti dikabari") -> Nanti dikabari
A3: =IFERROR(__xludf.DUMMYFUNCTION("""COMPUTED_VALUE"""),46023.0) -> 46023 | B3: =IFERROR(__xludf.DUMMYFUNCTION("""COMPUTED_VALUE"""),"2601D002") -> 2601D002 | C3: =IFERROR(__xludf.DUMMYFUNCTION("""COMPUTED_VALUE"""),"Ari.Januari.2026") -> Ari.Januari.2026 | D3: =IFERROR(__xludf.DUMMYFUNCTION("""COMPUTED_VALUE"""),"0881036053274") -> 0881036053274 | E3: =IFERROR(__xludf.DUMMYFUNCTION("""COMPUTED_VALUE"""),"Website") -> Website | F3: =IFERROR(__xludf.DUMMYFUNCTION("""COMPUTED_VALUE"""),"Gagal") -> Gagal | G3: =IFERROR(__xludf.DUMMYFUNCTION("""COMPUTED_VALUE"""),"CT") -> CT | K3: =IFERROR(__xludf.DUMMYFUNCTION("""COMPUTED_VALUE"""),"ingin paket campervan") -> ingin paket campervan
A4: =IFERROR(__xludf.DUMMYFUNCTION("""COMPUTED_VALUE"""),46023.0) -> 46023 | B4: =IFERROR(__xludf.DUMMYFUNCTION("""COMPUTED_VALUE"""),"2601D003") -> 2601D003 | C4: =IFERROR(__xludf.DUMMYFUNCTION("""COMPUTED_VALUE"""),"Muliono") -> Muliono | D4: =IFERROR(__xludf.DUMMYFUNCTION("""COMPUTED_VALUE"""),"085851219044") -> 085851219044 | E4: =IFERROR(__xludf.DUMMYFUNCTION("""COMPUTED_VALUE"""),"Website") -> Website | F4: =IFERROR(__xludf.DUMMYFUNCTION("""COMPUTED_VALUE"""),"Gagal") -> Gagal | G4: =IFERROR(__xludf.DUMMYFUNCTION("""COMPUTED_VALUE"""),"Trip baluran ") -> Trip baluran | I4: =IFERROR(__xludf.DUMMYFUNCTION("""COMPUTED_VALUE"""),7.0) -> 7 | K4: =IFERROR(__xludf.DUMMYFUNCTION("""COMPUTED_VALUE"""),"Tidak jawab") -> Tidak jawab
A5: =IFERROR(__xludf.DUMMYFUNCTION("""COMPUTED_VALUE"""),46023.0) -> 46023 | B5: =IFERROR(__xludf.DUMMYFUNCTION("""COMPUTED_VALUE"""),"2601D004") -> 2601D004 | C5: =IFERROR(__xludf.DUMMYFUNCTION("""COMPUTED_VALUE"""),"Berliana") -> Berliana | D5: =IFERROR(__xludf.DUMMYFUNCTION("""COMPUTED_VALUE"""),"085806069951") -> 085806069951 | E5: =IFERROR(__xludf.DUMMYFUNCTION("""COMPUTED_VALUE"""),"Instagram") -> Instagram | F5: =IFERROR(__xludf.DUMMYFUNCTION("""COMPUTED_VALUE"""),"Gagal") -> Gagal | G5: =IFERROR(__xludf.DUMMYFUNCTION("""COMPUTED_VALUE"""),"one day trip") -> one day trip | K5: =IFERROR(__xludf.DUMMYFUNCTION("""COMPUTED_VALUE"""),"Tidak jawab") -> Tidak jawab
A6: =IFERROR(__xludf.DUMMYFUNCTION("""COMPUTED_VALUE"""),46023.0) -> 46023 | B6: =IFERROR(__xludf.DUMMYFUNCTION("""COMPUTED_VALUE"""),"2601D005") -> 2601D005 | C6: =IFERROR(__xludf.DUMMYFUNCTION("""COMPUTED_VALUE"""),"Muhammad Amrullah a.k") -> Muhammad Amrullah a.k | D6: =IFERROR(__xludf.DUMMYFUNCTION("""COMPUTED_VALUE"""),"081393712742") -> 081393712742 | E6: =IFERROR(__xludf.DUMMYFUNCTION("""COMPUTED_VALUE"""),"Instagram") -> Instagram | F6: =IFERROR(__xludf.DUMMYFUNCTION("""COMPUTED_VALUE"""),"Gagal") -> Gagal | G6: =IFERROR(__xludf.DUMMYFUNCTION("""COMPUTED_VALUE"""),"custom 3H2M") -> custom 3H2M | I6: =IFERROR(__xludf.DUMMYFUNCTION("""COMPUTED_VALUE"""),7.0) -> 7 | J6: =IFERROR(__xludf.DUMMYFUNCTION("""COMPUTED_VALUE"""),1.1223751E7) -> 11223751 | K6: =IFERROR(__xludf.DUMMYFUNCTION("""COMPUTED_VALUE"""),"tidak ada jawaban") -> tidak ada jawaban
A7: =IFERROR(__xludf.DUMMYFUNCTION("""COMPUTED_VALUE"""),46023.0) -> 46023 | B7: =IFERROR(__xludf.DUMMYFUNCTION("""COMPUTED_VALUE"""),"2601D006") -> 2601D006 | C7: =IFERROR(__xludf.DUMMYFUNCTION("""COMPUTED_VALUE"""),"Prima Gita") -> Prima Gita | D7: =IFERROR(__xludf.DUMMYFUNCTION("""COMPUTED_VALUE"""),"081284286428") -> 081284286428 | E7: =IFERROR(__xludf.DUMMYFUNCTION("""COMPUTED_VALUE"""),"Instagram") -> Instagram | F7: =IFERROR(__xludf.DUMMYFUNCTION("""COMPUTED_VALUE"""),"Gagal") -> Gagal | G7: =IFERROR(__xludf.DUMMYFUNCTION("""COMPUTED_VALUE"""),"2H1M opsi a") -> 2H1M opsi a | K7: =IFERROR(__xludf.DUMMYFUNCTION("""COMPUTED_VALUE"""),"Tidak jawab") -> Tidak jawab
A8: =IFERROR(__xludf.DUMMYFUNCTION("""COMPUTED_VALUE"""),46023.0) -> 46023 | B8: =IFERROR(__xludf.DUMMYFUNCTION("""COMPUTED_VALUE"""),"2601D007") -> 2601D007 | C8: =IFERROR(__xludf.DUMMYFUNCTION("""COMPUTED_VALUE"""),"Mia Bella") -> Mia Bella | D8: =IFERROR(__xludf.DUMMYFUNCTION("""COMPUTED_VALUE"""),"08133977533") -> 08133977533 | E8: =IFERROR(__xludf.DUMMYFUNCTION("""COMPUTED_VALUE"""),"Instagram") -> Instagram | F8: =IFERROR(__xludf.DUMMYFUNCTION("""COMPUTED_VALUE"""),"Gagal") -> Gagal | G8: =IFERROR(__xludf.DUMMYFUNCTION("""COMPUTED_VALUE"""),"Ijen Baluran one day trip") -> Ijen Baluran one day trip | H8: =IFERROR(__xludf.DUMMYFUNCTION("""COMPUTED_VALUE"""),46026.0) -> 46026 | I8: =IFERROR(__xludf.DUMMYFUNCTION("""COMPUTED_VALUE"""),2.0) -> 2 | K8: =IFERROR(__xludf.DUMMYFUNCTION("""COMPUTED_VALUE"""),"1 wni 1 wna, tdk jawab") -> 1 wni 1 wna, tdk jawab
A9: =IFERROR(__xludf.DUMMYFUNCTION("""COMPUTED_VALUE"""),46023.0) -> 46023 | B9: =IFERROR(__xludf.DUMMYFUNCTION("""COMPUTED_VALUE"""),"2601D008") -> 2601D008 | C9: =IFERROR(__xludf.DUMMYFUNCTION("""COMPUTED_VALUE"""),"Kai") -> Kai | D9: =IFERROR(__xludf.DUMMYFUNCTION("""COMPUTED_VALUE"""),"081399930501") -> 081399930501 | E9: =IFERROR(__xludf.DUMMYFUNCTION("""COMPUTED_VALUE"""),"Instagram") -> Instagram | F9: =IFERROR(__xludf.DUMMYFUNCTION("""COMPUTED_VALUE"""),"Gagal") -> Gagal | G9: =IFERROR(__xludf.DUMMYFUNCTION("""COMPUTED_VALUE"""),"ot 3h2m") -> ot 3h2m | K9: =IFERROR(__xludf.DUMMYFUNCTION("""COMPUTED_VALUE"""),"lewat tanggal") -> lewat tanggal
A10: =IFERROR(__xludf.DUMMYFUNCTION("""COMPUTED_VALUE"""),46024.0) -> 46024 | B10: =IFERROR(__xludf.DUMMYFUNCTION("""COMPUTED_VALUE"""),"2601D009") -> 2601D009 | C10: =IFERROR(__xludf.DUMMYFUNCTION("""COMPUTED_VALUE"""),"Iin Noor Chozin") -> Iin Noor Chozin | D10: =IFERROR(__xludf.DUMMYFUNCTION("""COMPUTED_VALUE"""),"081233197590") -> 081233197590 | E10: =IFERROR(__xludf.DUMMYFUNCTION("""COMPUTED_VALUE"""),"Website") -> Website | F10: =IFERROR(__xludf.DUMMYFUNCTION("""COMPUTED_VALUE"""),"Closing") -> Closing | G10: =IFERROR(__xludf.DUMMYFUNCTION("""COMPUTED_VALUE"""),"Trip Menjangan Tabuhan") -> Trip Menjangan Tabuhan | H10: =IFERROR(__xludf.DUMMYFUNCTION("""COMPUTED_VALUE"""),46025.0) -> 46025 | I10: =IFERROR(__xludf.DUMMYFUNCTION("""COMPUTED_VALUE"""),6.0) -> 6 | J10: =IFERROR(__xludf.DUMMYFUNCTION("""COMPUTED_VALUE"""),2460000.0) -> 2460000 | K10: =IFERROR(__xludf.DUMMYFUNCTION("""COMPUTED_VALUE"""),"menjangan tabuhan") -> menjangan tabuhan
A11: =IFERROR(__xludf.DUMMYFUNCTION("""COMPUTED_VALUE"""),46024.0) -> 46024 | B11: =IFERROR(__xludf.DUMMYFUNCTION("""COMPUTED_VALUE"""),"2601D010") -> 2601D010 | C11: =IFERROR(__xludf.DUMMYFUNCTION("""COMPUTED_VALUE"""),"Dia Pur's") -> Dia Pur's | D11: =IFERROR(__xludf.DUMMYFUNCTION("""COMPUTED_VALUE"""),"082360390604") -> 082360390604 | E11: =IFERROR(__xludf.DUMMYFUNCTION("""COMPUTED_VALUE"""),"Instagram") -> Instagram | F11: =IFERROR(__xludf.DUMMYFUNCTION("""COMPUTED_VALUE"""),"Gagal") -> Gagal | G11: =IFERROR(__xludf.DUMMYFUNCTION("""COMPUTED_VALUE"""),"custom 2h1m") -> custom 2h1m | I11: =IFERROR(__xludf.DUMMYFUNCTION("""COMPUTED_VALUE"""),4.0) -> 4 | K11: =IFERROR(__xludf.DUMMYFUNCTION("""COMPUTED_VALUE"""),"tanggal lewat") -> tanggal lewat
A12: =IFERROR(__xludf.DUMMYFUNCTION("""COMPUTED_VALUE"""),46024.0) -> 46024 | B12: =IFERROR(__xludf.DUMMYFUNCTION("""COMPUTED_VALUE"""),"2601D011") -> 2601D011 | C12: =IFERROR(__xludf.DUMMYFUNCTION("""COMPUTED_VALUE"""),"Inggrid") -> Inggrid | D12: =IFERROR(__xludf.DUMMYFUNCTION("""COMPUTED_VALUE"""),"085156507128") -> 085156507128 | E12: =IFERROR(__xludf.DUMMYFUNCTION("""COMPUTED_VALUE"""),"Instagram") -> Instagram | F12: =IFERROR(__xludf.DUMMYFUNCTION("""COMPUTED_VALUE"""),"Gagal") -> Gagal | G12: =IFERROR(__xludf.DUMMYFUNCTION("""COMPUTED_VALUE"""),"OT Januari") -> OT Januari | K12: =IFERROR(__xludf.DUMMYFUNCTION("""COMPUTED_VALUE"""),"tidak jawab") -> tidak jawab
A13: =IFERROR(__xludf.DUMMYFUNCTION("""COMPUTED_VALUE"""),46024.0) -> 46024 | B13: =IFERROR(__xludf.DUMMYFUNCTION("""COMPUTED_VALUE"""),"2601D012") -> 2601D012 | C13: =IFERROR(__xludf.DUMMYFUNCTION("""COMPUTED_VALUE"""),"Kartika") -> Kartika | D13: =IFERROR(__xludf.DUMMYFUNCTION("""COMPUTED_VALUE"""),"082143617625") -> 082143617625 | E13: =IFERROR(__xludf.DUMMYFUNCTION("""COMPUTED_VALUE"""),"Website") -> Website | F13: =IFERROR(__xludf.DUMMYFUNCTION("""COMPUTED_VALUE"""),"Closing") -> Closing | G13: =IFERROR(__xludf.DUMMYFUNCTION("""COMPUTED_VALUE"""),"OT Menjangan Tabuhan") -> OT Menjangan Tabuhan | H13: =IFERROR(__xludf.DUMMYFUNCTION("""COMPUTED_VALUE"""),46033.0) -> 46033 | I13: =IFERROR(__xludf.DUMMYFUNCTION("""COMPUTED_VALUE"""),4.0) -> 4 | J13: =IFERROR(__xludf.DUMMYFUNCTION("""COMPUTED_VALUE"""),1180000.0) -> 1180000
A14: =IFERROR(__xludf.DUMMYFUNCTION("""COMPUTED_VALUE"""),46024.0) -> 46024 | B14: =IFERROR(__xludf.DUMMYFUNCTION("""COMPUTED_VALUE"""),"2601D013") -> 2601D013 | C14: =IFERROR(__xludf.DUMMYFUNCTION("""COMPUTED_VALUE"""),"Diyatrana") -> Diyatrana | D14: =IFERROR(__xludf.DUMMYFUNCTION("""COMPUTED_VALUE"""),"085729990708") -> 085729990708 | E14: =IFERROR(__xludf.DUMMYFUNCTION("""COMPUTED_VALUE"""),"Instagram") -> Instagram | F14: =IFERROR(__xludf.DUMMYFUNCTION("""COMPUTED_VALUE"""),"Gagal") -> Gagal | G14: =IFERROR(__xludf.DUMMYFUNCTION("""COMPUTED_VALUE"""),"3H2M opsi A") -> 3H2M opsi A | K14: =IFERROR(__xludf.DUMMYFUNCTION("""COMPUTED_VALUE"""),"tidak jawab") -> tidak jawab
A15: =IFERROR(__xludf.DUMMYFUNCTION("""COMPUTED_VALUE"""),46024.0) -> 46024 | B15: =IFERROR(__xludf.DUMMYFUNCTION("""COMPUTED_VALUE"""),"2601D014") -> 2601D014 | C15: =IFERROR(__xludf.DUMMYFUNCTION("""COMPUTED_VALUE"""),"Peni") -> Peni | D15: =IFERROR(__xludf.DUMMYFUNCTION("""COMPUTED_VALUE"""),"081553992808") -> 081553992808 | E15: =IFERROR(__xludf.DUMMYFUNCTION("""COMPUTED_VALUE"""),"Instagram") -> Instagram | F15: =IFERROR(__xludf.DUMMYFUNCTION("""COMPUTED_VALUE"""),"Gagal") -> Gagal | G15: =IFERROR(__xludf.DUMMYFUNCTION("""COMPUTED_VALUE"""),"Trip Pulau Bedil") -> Trip Pulau Bedil | H15: =IFERROR(__xludf.DUMMYFUNCTION("""COMPUTED_VALUE"""),46104.0) -> 46104 | I15: =IFERROR(__xludf.DUMMYFUNCTION("""COMPUTED_VALUE"""),4.0) -> 4 | J15: =IFERROR(__xludf.DUMMYFUNCTION("""COMPUTED_VALUE"""),1408000.0) -> 1408000 | K15: =IFERROR(__xludf.DUMMYFUNCTION("""COMPUTED_VALUE"""),"pindah haluan liburan") -> pindah haluan liburan
A16: =IFERROR(__xludf.DUMMYFUNCTION("""COMPUTED_VALUE"""),46024.0) -> 46024 | B16: =IFERROR(__xludf.DUMMYFUNCTION("""COMPUTED_VALUE"""),"2601D015") -> 2601D015 | C16: =IFERROR(__xludf.DUMMYFUNCTION("""COMPUTED_VALUE"""),"Kirana") -> Kirana | D16: =IFERROR(__xludf.DUMMYFUNCTION("""COMPUTED_VALUE"""),"085777785090") -> 085777785090 | E16: =IFERROR(__xludf.DUMMYFUNCTION("""COMPUTED_VALUE"""),"Website") -> Website | F16: =IFERROR(__xludf.DUMMYFUNCTION("""COMPUTED_VALUE"""),"Review") -> Review | G16: =IFERROR(__xludf.DUMMYFUNCTION("""COMPUTED_VALUE"""),"custom 2h1m") -> custom 2h1m | I16: =IFERROR(__xludf.DUMMYFUNCTION("""COMPUTED_VALUE"""),40.0) -> 40 | J16: =IFERROR(__xludf.DUMMYFUNCTION("""COMPUTED_VALUE"""),4.10244E7) -> 41024400 | K16: =IFERROR(__xludf.DUMMYFUNCTION("""COMPUTED_VALUE"""),"MINTA PAKET, fu akhir januari") -> MINTA PAKET, fu akhir januari
A17: =IFERROR(__xludf.DUMMYFUNCTION("""COMPUTED_VALUE"""),46024.0) -> 46024 | B17: =IFERROR(__xludf.DUMMYFUNCTION("""COMPUTED_VALUE"""),"2601D016") -> 2601D016 | C17: =IFERROR(__xludf.DUMMYFUNCTION("""COMPUTED_VALUE"""),"Ika W/ Ibu ms Nasir") -> Ika W/ Ibu ms Nasir | D17: =IFERROR(__xludf.DUMMYFUNCTION("""COMPUTED_VALUE"""),"0882007680200") -> 0882007680200 | E17: =IFERROR(__xludf.DUMMYFUNCTION("""COMPUTED_VALUE"""),"Website") -> Website | F17: =IFERROR(__xludf.DUMMYFUNCTION("""COMPUTED_VALUE"""),"Gagal") -> Gagal | G17: =IFERROR(__xludf.DUMMYFUNCTION("""COMPUTED_VALUE"""),"2H1M opsi C") -> 2H1M opsi C | H17: =IFERROR(__xludf.DUMMYFUNCTION("""COMPUTED_VALUE"""),46170.0) -> 46170 | I17: =IFERROR(__xludf.DUMMYFUNCTION("""COMPUTED_VALUE"""),17.0) -> 17 | K17: =IFERROR(__xludf.DUMMYFUNCTION("""COMPUTED_VALUE"""),"ganti ke bromo") -> ganti ke bromo
A18: =IFERROR(__xludf.DUMMYFUNCTION("""COMPUTED_VALUE"""),46024.0) -> 46024 | B18: =IFERROR(__xludf.DUMMYFUNCTION("""COMPUTED_VALUE"""),"2601D017") -> 2601D017 | C18: =IFERROR(__xludf.DUMMYFUNCTION("""COMPUTED_VALUE"""),"Karen") -> Karen | D18: =IFERROR(__xludf.DUMMYFUNCTION("""COMPUTED_VALUE"""),"087772484641") -> 087772484641 | E18: =IFERROR(__xludf.DUMMYFUNCTION("""COMPUTED_VALUE"""),"Instagram") -> Instagram | F18: =IFERROR(__xludf.DUMMYFUNCTION("""COMPUTED_VALUE"""),"Gagal") -> Gagal | G18: =IFERROR(__xludf.DUMMYFUNCTION("""COMPUTED_VALUE"""),"2 paket open trip") -> 2 paket open trip | I18: =IFERROR(__xludf.DUMMYFUNCTION("""COMPUTED_VALUE"""),2.0) -> 2 | J18: =IFERROR(__xludf.DUMMYFUNCTION("""COMPUTED_VALUE"""),1050000.0) -> 1050000 | K18: =IFERROR(__xludf.DUMMYFUNCTION("""COMPUTED_VALUE"""),"follow up tanggal 15 februari") -> follow up tanggal 15 februari
A19: =IFERROR(__xludf.DUMMYFUNCTION("""COMPUTED_VALUE"""),46024.0) -> 46024 | B19: =IFERROR(__xludf.DUMMYFUNCTION("""COMPUTED_VALUE"""),"2601D018") -> 2601D018 | C19: =IFERROR(__xludf.DUMMYFUNCTION("""COMPUTED_VALUE"""),"Tiyas") -> Tiyas | D19: =IFERROR(__xludf.DUMMYFUNCTION("""COMPUTED_VALUE"""),"082136195477") -> 082136195477 | E19: =IFERROR(__xludf.DUMMYFUNCTION("""COMPUTED_VALUE"""),"Lainnya") -> Lainnya | F19: =IFERROR(__xludf.DUMMYFUNCTION("""COMPUTED_VALUE"""),"Gagal") -> Gagal | G19: =IFERROR(__xludf.DUMMYFUNCTION("""COMPUTED_VALUE"""),"Custom 2h1m") -> Custom 2h1m | I19: =IFERROR(__xludf.DUMMYFUNCTION("""COMPUTED_VALUE"""),2.0) -> 2 | K19: =IFERROR(__xludf.DUMMYFUNCTION("""COMPUTED_VALUE"""),"Minta Paket, fu tgl 10") -> Minta Paket, fu tgl 10
A20: =IFERROR(__xludf.DUMMYFUNCTION("""COMPUTED_VALUE"""),46025.0) -> 46025 | B20: =IFERROR(__xludf.DUMMYFUNCTION("""COMPUTED_VALUE"""),"2601D019") -> 2601D019 | C20: =IFERROR(__xludf.DUMMYFUNCTION("""COMPUTED_VALUE"""),"Beta Amrina") -> Beta Amrina | D20: =IFERROR(__xludf.DUMMYFUNCTION("""COMPUTED_VALUE"""),"082327577538") -> 082327577538 | E20: =IFERROR(__xludf.DUMMYFUNCTION("""COMPUTED_VALUE"""),"Instagram") -> Instagram | F20: =IFERROR(__xludf.DUMMYFUNCTION("""COMPUTED_VALUE"""),"Gagal") -> Gagal | G20: =IFERROR(__xludf.DUMMYFUNCTION("""COMPUTED_VALUE"""),"OT") -> OT | I20: =IFERROR(__xludf.DUMMYFUNCTION("""COMPUTED_VALUE"""),3.0) -> 3 | J20: =IFERROR(__xludf.DUMMYFUNCTION("""COMPUTED_VALUE"""),4800000.0) -> 4800000 | K20: =IFERROR(__xludf.DUMMYFUNCTION("""COMPUTED_VALUE"""),"tidak jawab") -> tidak jawab
A21: =IFERROR(__xludf.DUMMYFUNCTION("""COMPUTED_VALUE"""),46025.0) -> 46025 | B21: =IFERROR(__xludf.DUMMYFUNCTION("""COMPUTED_VALUE"""),"2601D020") -> 2601D020 | C21: =IFERROR(__xludf.DUMMYFUNCTION("""COMPUTED_VALUE"""),"Wa ") -> Wa | D21: =IFERROR(__xludf.DUMMYFUNCTION("""COMPUTED_VALUE"""),"085641568779") -> 085641568779 | E21: =IFERROR(__xludf.DUMMYFUNCTION("""COMPUTED_VALUE"""),"Lainnya") -> Lainnya | F21: =IFERROR(__xludf.DUMMYFUNCTION("""COMPUTED_VALUE"""),"Gagal") -> Gagal | G21: =IFERROR(__xludf.DUMMYFUNCTION("""COMPUTED_VALUE"""),"ot djawatan baluran") -> ot djawatan baluran | K21: =IFERROR(__xludf.DUMMYFUNCTION("""COMPUTED_VALUE"""),"tidak jawab") -> tidak jawab
A22: =IFERROR(__xludf.DUMMYFUNCTION("""COMPUTED_VALUE"""),46025.0) -> 46025 | B22: =IFERROR(__xludf.DUMMYFUNCTION("""COMPUTED_VALUE"""),"2601D021") -> 2601D021 | C22: =IFERROR(__xludf.DUMMYFUNCTION("""COMPUTED_VALUE"""),"Buds") -> Buds | D22: =IFERROR(__xludf.DUMMYFUNCTION("""COMPUTED_VALUE"""),"085720585703") -> 085720585703 | E22: =IFERROR(__xludf.DUMMYFUNCTION("""COMPUTED_VALUE"""),"Website") -> Website | F22: =IFERROR(__xludf.DUMMYFUNCTION("""COMPUTED_VALUE"""),"Gagal") -> Gagal | G22: =IFERROR(__xludf.DUMMYFUNCTION("""COMPUTED_VALUE"""),"Baluran private ") -> Baluran private | K22: =IFERROR(__xludf.DUMMYFUNCTION("""COMPUTED_VALUE"""),"tidak jawab") -> tidak jawab
A23: =IFERROR(__xludf.DUMMYFUNCTION("""COMPUTED_VALUE"""),46025.0) -> 46025 | B23: =IFERROR(__xludf.DUMMYFUNCTION("""COMPUTED_VALUE"""),"2601D022") -> 2601D022 | C23: =IFERROR(__xludf.DUMMYFUNCTION("""COMPUTED_VALUE"""),"Seysa") -> Seysa | D23: =IFERROR(__xludf.DUMMYFUNCTION("""COMPUTED_VALUE"""),"085886980015") -> 085886980015 | E23: =IFERROR(__xludf.DUMMYFUNCTION("""COMPUTED_VALUE"""),"Instagram") -> Instagram | F23: =IFERROR(__xludf.DUMMYFUNCTION("""COMPUTED_VALUE"""),"Gagal") -> Gagal | G23: =IFERROR(__xludf.DUMMYFUNCTION("""COMPUTED_VALUE"""),"trip kawah wurung") -> trip kawah wurung | H23: =IFERROR(__xludf.DUMMYFUNCTION("""COMPUTED_VALUE"""),46028.0) -> 46028 | I23: =IFERROR(__xludf.DUMMYFUNCTION("""COMPUTED_VALUE"""),3.0) -> 3 | K23: =IFERROR(__xludf.DUMMYFUNCTION("""COMPUTED_VALUE"""),"masih pikir2 dulu, sudah lewat tgl") -> masih pikir2 dulu, sudah lewat tgl
A24: =IFERROR(__xludf.DUMMYFUNCTION("""COMPUTED_VALUE"""),46025.0) -> 46025 | B24: =IFERROR(__xludf.DUMMYFUNCTION("""COMPUTED_VALUE"""),"2601D023") -> 2601D023 | C24: =IFERROR(__xludf.DUMMYFUNCTION("""COMPUTED_VALUE"""),"Nothing") -> Nothing | D24: =IFERROR(__xludf.DUMMYFUNCTION("""COMPUTED_VALUE"""),"085820515179") -> 085820515179 | E24: =IFERROR(__xludf.DUMMYFUNCTION("""COMPUTED_VALUE"""),"Website") -> Website | F24: =IFERROR(__xludf.DUMMYFUNCTION("""COMPUTED_VALUE"""),"Gagal") -> Gagal | G24: =IFERROR(__xludf.DUMMYFUNCTION("""COMPUTED_VALUE"""),"Trip Kawah Ijen") -> Trip Kawah Ijen | K24: =IFERROR(__xludf.DUMMYFUNCTION("""COMPUTED_VALUE"""),"mepo sby atau gresik") -> mepo sby atau gresik
A25: =IFERROR(__xludf.DUMMYFUNCTION("""COMPUTED_VALUE"""),46025.0) -> 46025 | B25: =IFERROR(__xludf.DUMMYFUNCTION("""COMPUTED_VALUE"""),"2601D024") -> 2601D024 | C25: =IFERROR(__xludf.DUMMYFUNCTION("""COMPUTED_VALUE"""),"Dhevy Hariady") -> Dhevy Hariady | D25: =IFERROR(__xludf.DUMMYFUNCTION("""COMPUTED_VALUE"""),"082282391601") -> 082282391601 | E25: =IFERROR(__xludf.DUMMYFUNCTION("""COMPUTED_VALUE"""),"Instagram") -> Instagram | F25: =IFERROR(__xludf.DUMMYFUNCTION("""COMPUTED_VALUE"""),"Gagal") -> Gagal | G25: =IFERROR(__xludf.DUMMYFUNCTION("""COMPUTED_VALUE"""),"trip djawatan baluran") -> trip djawatan baluran | I25: =IFERROR(__xludf.DUMMYFUNCTION("""COMPUTED_VALUE"""),4.0) -> 4 | J25: =IFERROR(__xludf.DUMMYFUNCTION("""COMPUTED_VALUE"""),1996000.0) -> 1996000 | K25: =IFERROR(__xludf.DUMMYFUNCTION("""COMPUTED_VALUE"""),"tidak jadi liburan ke BWI") -> tidak jadi liburan ke BWI | L25: =IFERROR(__xludf.DUMMYFUNCTION("""COMPUTED_VALUE"""),"https://docs.google.com/document/d/1wA6Vstebr_OPv-YiZuHCtRJ0dphAaw92AabZKFpW9i0/edit?tab=t.0") -> https://docs.google.com/document/d/1wA6Vstebr_OPv-YiZuHCtRJ0dphAaw92AabZKFpW9i0/edit?tab=t.0
A26: =IFERROR(__xludf.DUMMYFUNCTION("""COMPUTED_VALUE"""),46025.0) -> 46025 | B26: =IFERROR(__xludf.DUMMYFUNCTION("""COMPUTED_VALUE"""),"2601D025") -> 2601D025 | C26: =IFERROR(__xludf.DUMMYFUNCTION("""COMPUTED_VALUE"""),"Ratu (Bunda FazZZam)") -> Ratu (Bunda FazZZam) | D26: =IFERROR(__xludf.DUMMYFUNCTION("""COMPUTED_VALUE"""),"081806567775") -> 081806567775 | E26: =IFERROR(__xludf.DUMMYFUNCTION("""COMPUTED_VALUE"""),"Instagram") -> Instagram | F26: =IFERROR(__xludf.DUMMYFUNCTION("""COMPUTED_VALUE"""),"Gagal") -> Gagal | G26: =IFERROR(__xludf.DUMMYFUNCTION("""COMPUTED_VALUE"""),"OT 3H2M") -> OT 3H2M | K26: =IFERROR(__xludf.DUMMYFUNCTION("""COMPUTED_VALUE"""),"masih ngomong ke atasan") -> masih ngomong ke atasan
A27: =IFERROR(__xludf.DUMMYFUNCTION("""COMPUTED_VALUE"""),46025.0) -> 46025 | B27: =IFERROR(__xludf.DUMMYFUNCTION("""COMPUTED_VALUE"""),"2601D026") -> 2601D026 | C27: =IFERROR(__xludf.DUMMYFUNCTION("""COMPUTED_VALUE"""),"Gilang") -> Gilang | D27: =IFERROR(__xludf.DUMMYFUNCTION("""COMPUTED_VALUE"""),"081221614470") -> 081221614470 | E27: =IFERROR(__xludf.DUMMYFUNCTION("""COMPUTED_VALUE"""),"Website") -> Website | F27: =IFERROR(__xludf.DUMMYFUNCTION("""COMPUTED_VALUE"""),"Closing") -> Closing | G27: =IFERROR(__xludf.DUMMYFUNCTION("""COMPUTED_VALUE"""),"Private Trip Kawah Wurung") -> Private Trip Kawah Wurung | H27: =IFERROR(__xludf.DUMMYFUNCTION("""COMPUTED_VALUE"""),46026.0) -> 46026 | I27: =IFERROR(__xludf.DUMMYFUNCTION("""COMPUTED_VALUE"""),1.0) -> 1 | J27: =IFERROR(__xludf.DUMMYFUNCTION("""COMPUTED_VALUE"""),2318100.0) -> 2318100
A28: =IFERROR(__xludf.DUMMYFUNCTION("""COMPUTED_VALUE"""),46025.0) -> 46025 | B28: =IFERROR(__xludf.DUMMYFUNCTION("""COMPUTED_VALUE"""),"2601D027") -> 2601D027 | C28: =IFERROR(__xludf.DUMMYFUNCTION("""COMPUTED_VALUE"""),"Farus nabil") -> Farus nabil | D28: =IFERROR(__xludf.DUMMYFUNCTION("""COMPUTED_VALUE"""),"081293944286") -> 081293944286 | E28: =IFERROR(__xludf.DUMMYFUNCTION("""COMPUTED_VALUE"""),"Instagram") -> Instagram | F28: =IFERROR(__xludf.DUMMYFUNCTION("""COMPUTED_VALUE"""),"Closing") -> Closing | G28: =IFERROR(__xludf.DUMMYFUNCTION("""COMPUTED_VALUE"""),"Private Trip Menjangan Tabuhan") -> Private Trip Menjangan Tabuhan | H28: =IFERROR(__xludf.DUMMYFUNCTION("""COMPUTED_VALUE"""),46032.0) -> 46032 | I28: =IFERROR(__xludf.DUMMYFUNCTION("""COMPUTED_VALUE"""),5.0) -> 5 | J28: =IFERROR(__xludf.DUMMYFUNCTION("""COMPUTED_VALUE"""),2300000.0) -> 2300000
A29: =IFERROR(__xludf.DUMMYFUNCTION("""COMPUTED_VALUE"""),46025.0) -> 46025 | B29: =IFERROR(__xludf.DUMMYFUNCTION("""COMPUTED_VALUE"""),"2601D028") -> 2601D028 | C29: =IFERROR(__xludf.DUMMYFUNCTION("""COMPUTED_VALUE"""),"Rehan") -> Rehan | D29: =IFERROR(__xludf.DUMMYFUNCTION("""COMPUTED_VALUE"""),"08963381584") -> 08963381584 | E29: =IFERROR(__xludf.DUMMYFUNCTION("""COMPUTED_VALUE"""),"Instagram") -> Instagram | F29: =IFERROR(__xludf.DUMMYFUNCTION("""COMPUTED_VALUE"""),"Gagal") -> Gagal | G29: =IFERROR(__xludf.DUMMYFUNCTION("""COMPUTED_VALUE"""),"2H1M") -> 2H1M | I29: =IFERROR(__xludf.DUMMYFUNCTION("""COMPUTED_VALUE"""),5.0) -> 5 | J29: =IFERROR(__xludf.DUMMYFUNCTION("""COMPUTED_VALUE"""),9225000.0) -> 9225000 | K29: =IFERROR(__xludf.DUMMYFUNCTION("""COMPUTED_VALUE"""),"tidak ada jawaban") -> tidak ada jawaban
A30: =IFERROR(__xludf.DUMMYFUNCTION("""COMPUTED_VALUE"""),46025.0) -> 46025 | B30: =IFERROR(__xludf.DUMMYFUNCTION("""COMPUTED_VALUE"""),"2601D029") -> 2601D029 | C30: =IFERROR(__xludf.DUMMYFUNCTION("""COMPUTED_VALUE"""),"Nella Holiday") -> Nella Holiday | D30: =IFERROR(__xludf.DUMMYFUNCTION("""COMPUTED_VALUE"""),"089672570321") -> 089672570321 | E30: =IFERROR(__xludf.DUMMYFUNCTION("""COMPUTED_VALUE"""),"Website") -> Website | F30: =IFERROR(__xludf.DUMMYFUNCTION("""COMPUTED_VALUE"""),"Gagal") -> Gagal | G30: =IFERROR(__xludf.DUMMYFUNCTION("""COMPUTED_VALUE"""),"trip ijen") -> trip ijen | H30: =IFERROR(__xludf.DUMMYFUNCTION("""COMPUTED_VALUE"""),46039.0) -> 46039 | I30: =IFERROR(__xludf.DUMMYFUNCTION("""COMPUTED_VALUE"""),14.0) -> 14 | K30: =IFERROR(__xludf.DUMMYFUNCTION("""COMPUTED_VALUE"""),"SDH FOLLOW UP") -> SDH FOLLOW UP
A31: =IFERROR(__xludf.DUMMYFUNCTION("""COMPUTED_VALUE"""),46026.0) -> 46026 | B31: =IFERROR(__xludf.DUMMYFUNCTION("""COMPUTED_VALUE"""),"2601D030") -> 2601D030 | C31: =IFERROR(__xludf.DUMMYFUNCTION("""COMPUTED_VALUE"""),"Cika") -> Cika | D31: =IFERROR(__xludf.DUMMYFUNCTION("""COMPUTED_VALUE"""),"085782656823") -> 085782656823 | E31: =IFERROR(__xludf.DUMMYFUNCTION("""COMPUTED_VALUE"""),"Instagram") -> Instagram | F31: =IFERROR(__xludf.DUMMYFUNCTION("""COMPUTED_VALUE"""),"Gagal") -> Gagal | G31: =IFERROR(__xludf.DUMMYFUNCTION("""COMPUTED_VALUE"""),"Trip 3H2M") -> Trip 3H2M | K31: =IFERROR(__xludf.DUMMYFUNCTION("""COMPUTED_VALUE"""),"tidak ada jawaban") -> tidak ada jawaban
A32: =IFERROR(__xludf.DUMMYFUNCTION("""COMPUTED_VALUE"""),46026.0) -> 46026 | B32: =IFERROR(__xludf.DUMMYFUNCTION("""COMPUTED_VALUE"""),"2601D031") -> 2601D031 | C32: =IFERROR(__xludf.DUMMYFUNCTION("""COMPUTED_VALUE"""),"Sulistio W.N") -> Sulistio W.N | D32: =IFERROR(__xludf.DUMMYFUNCTION("""COMPUTED_VALUE"""),"082137405814") -> 082137405814 | E32: =IFERROR(__xludf.DUMMYFUNCTION("""COMPUTED_VALUE"""),"Website") -> Website | F32: =IFERROR(__xludf.DUMMYFUNCTION("""COMPUTED_VALUE"""),"Gagal") -> Gagal | G32: =IFERROR(__xludf.DUMMYFUNCTION("""COMPUTED_VALUE"""),"3H2M opsi B") -> 3H2M opsi B | K32: =IFERROR(__xludf.DUMMYFUNCTION("""COMPUTED_VALUE"""),"tanya yacht boom, fu tgl 15") -> tanya yacht boom, fu tgl 15
A33: =IFERROR(__xludf.DUMMYFUNCTION("""COMPUTED_VALUE"""),46026.0) -> 46026 | B33: =IFERROR(__xludf.DUMMYFUNCTION("""COMPUTED_VALUE"""),"2601D032") -> 2601D032 | C33: =IFERROR(__xludf.DUMMYFUNCTION("""COMPUTED_VALUE"""),"Thata Anggitha") -> Thata Anggitha | D33: =IFERROR(__xludf.DUMMYFUNCTION("""COMPUTED_VALUE"""),"082137405814") -> 082137405814 | E33: =IFERROR(__xludf.DUMMYFUNCTION("""COMPUTED_VALUE"""),"Instagram") -> Instagram | F33: =IFERROR(__xludf.DUMMYFUNCTION("""COMPUTED_VALUE"""),"Gagal") -> Gagal | I33: =IFERROR(__xludf.DUMMYFUNCTION("""COMPUTED_VALUE"""),2.0) -> 2 | K33: =IFERROR(__xludf.DUMMYFUNCTION("""COMPUTED_VALUE"""),"sudah follow up") -> sudah follow up
A34: =IFERROR(__xludf.DUMMYFUNCTION("""COMPUTED_VALUE"""),46026.0) -> 46026 | B34: =IFERROR(__xludf.DUMMYFUNCTION("""COMPUTED_VALUE"""),"2601D033") -> 2601D033 | C34: =IFERROR(__xludf.DUMMYFUNCTION("""COMPUTED_VALUE"""),"Aris Guntoro") -> Aris Guntoro | D34: =IFERROR(__xludf.DUMMYFUNCTION("""COMPUTED_VALUE"""),"081355209321") -> 081355209321 | E34: =IFERROR(__xludf.DUMMYFUNCTION("""COMPUTED_VALUE"""),"Website") -> Website | F34: =IFERROR(__xludf.DUMMYFUNCTION("""COMPUTED_VALUE"""),"Closing") -> Closing | G34: =IFERROR(__xludf.DUMMYFUNCTION("""COMPUTED_VALUE"""),"Trip Kawah Ijen") -> Trip Kawah Ijen | H34: =IFERROR(__xludf.DUMMYFUNCTION("""COMPUTED_VALUE"""),46038.0) -> 46038 | I34: =IFERROR(__xludf.DUMMYFUNCTION("""COMPUTED_VALUE"""),4.0) -> 4 | J34: =IFERROR(__xludf.DUMMYFUNCTION("""COMPUTED_VALUE"""),1570000.0) -> 1570000 | K34: =IFERROR(__xludf.DUMMYFUNCTION("""COMPUTED_VALUE"""),"sudah closing") -> sudah closing
A35: =IFERROR(__xludf.DUMMYFUNCTION("""COMPUTED_VALUE"""),46026.0) -> 46026 | B35: =IFERROR(__xludf.DUMMYFUNCTION("""COMPUTED_VALUE"""),"2601D034") -> 2601D034 | C35: =IFERROR(__xludf.DUMMYFUNCTION("""COMPUTED_VALUE"""),"Rizal Pratama") -> Rizal Pratama | D35: =IFERROR(__xludf.DUMMYFUNCTION("""COMPUTED_VALUE"""),"082216912039") -> 082216912039 | E35: =IFERROR(__xludf.DUMMYFUNCTION("""COMPUTED_VALUE"""),"Instagram") -> Instagram | F35: =IFERROR(__xludf.DUMMYFUNCTION("""COMPUTED_VALUE"""),"Gagal") -> Gagal | G35: =IFERROR(__xludf.DUMMYFUNCTION("""COMPUTED_VALUE"""),"3H2M opsi A") -> 3H2M opsi A | I35: =IFERROR(__xludf.DUMMYFUNCTION("""COMPUTED_VALUE"""),30.0) -> 30 | K35: =IFERROR(__xludf.DUMMYFUNCTION("""COMPUTED_VALUE"""),"sudah sm rekan lain") -> sudah sm rekan lain
A36: =IFERROR(__xludf.DUMMYFUNCTION("""COMPUTED_VALUE"""),46026.0) -> 46026 | B36: =IFERROR(__xludf.DUMMYFUNCTION("""COMPUTED_VALUE"""),"2601D035") -> 2601D035 | C36: =IFERROR(__xludf.DUMMYFUNCTION("""COMPUTED_VALUE"""),"Surya") -> Surya | D36: =IFERROR(__xludf.DUMMYFUNCTION("""COMPUTED_VALUE"""),"081803536960") -> 081803536960 | E36: =IFERROR(__xludf.DUMMYFUNCTION("""COMPUTED_VALUE"""),"Website") -> Website | F36: =IFERROR(__xludf.DUMMYFUNCTION("""COMPUTED_VALUE"""),"Gagal") -> Gagal | G36: =IFERROR(__xludf.DUMMYFUNCTION("""COMPUTED_VALUE"""),"Trip Menjangan Tabuhan ") -> Trip Menjangan Tabuhan | I36: =IFERROR(__xludf.DUMMYFUNCTION("""COMPUTED_VALUE"""),25.0) -> 25 | K36: =IFERROR(__xludf.DUMMYFUNCTION("""COMPUTED_VALUE"""),"tidak cocok harga") -> tidak cocok harga
A37: =IFERROR(__xludf.DUMMYFUNCTION("""COMPUTED_VALUE"""),46026.0) -> 46026 | B37: =IFERROR(__xludf.DUMMYFUNCTION("""COMPUTED_VALUE"""),"2601D036") -> 2601D036 | C37: =IFERROR(__xludf.DUMMYFUNCTION("""COMPUTED_VALUE"""),"Yaya") -> Yaya | D37: =IFERROR(__xludf.DUMMYFUNCTION("""COMPUTED_VALUE"""),"089612554076") -> 089612554076 | E37: =IFERROR(__xludf.DUMMYFUNCTION("""COMPUTED_VALUE"""),"Instagram") -> Instagram | F37: =IFERROR(__xludf.DUMMYFUNCTION("""COMPUTED_VALUE"""),"Gagal") -> Gagal | G37: =IFERROR(__xludf.DUMMYFUNCTION("""COMPUTED_VALUE"""),"OT 3H2M") -> OT 3H2M | K37: =IFERROR(__xludf.DUMMYFUNCTION("""COMPUTED_VALUE"""),"tidak jawab") -> tidak jawab
A38: =IFERROR(__xludf.DUMMYFUNCTION("""COMPUTED_VALUE"""),46026.0) -> 46026 | B38: =IFERROR(__xludf.DUMMYFUNCTION("""COMPUTED_VALUE"""),"2601D037") -> 2601D037 | C38: =IFERROR(__xludf.DUMMYFUNCTION("""COMPUTED_VALUE"""),"Hums GPS Malang") -> Hums GPS Malang | D38: =IFERROR(__xludf.DUMMYFUNCTION("""COMPUTED_VALUE"""),"085888433436") -> 085888433436 | E38: =IFERROR(__xludf.DUMMYFUNCTION("""COMPUTED_VALUE"""),"Instagram") -> Instagram | F38: =IFERROR(__xludf.DUMMYFUNCTION("""COMPUTED_VALUE"""),"Gagal") -> Gagal | G38: =IFERROR(__xludf.DUMMYFUNCTION("""COMPUTED_VALUE"""),"2H1M") -> 2H1M | K38: =IFERROR(__xludf.DUMMYFUNCTION("""COMPUTED_VALUE"""),"minta jpt sby") -> minta jpt sby
A39: =IFERROR(__xludf.DUMMYFUNCTION("""COMPUTED_VALUE"""),46026.0) -> 46026 | B39: =IFERROR(__xludf.DUMMYFUNCTION("""COMPUTED_VALUE"""),"2601D038") -> 2601D038 | C39: =IFERROR(__xludf.DUMMYFUNCTION("""COMPUTED_VALUE"""),"Sary Maheswari") -> Sary Maheswari | D39: =IFERROR(__xludf.DUMMYFUNCTION("""COMPUTED_VALUE"""),"085729077777") -> 085729077777 | E39: =IFERROR(__xludf.DUMMYFUNCTION("""COMPUTED_VALUE"""),"Instagram") -> Instagram | F39: =IFERROR(__xludf.DUMMYFUNCTION("""COMPUTED_VALUE"""),"Gagal") -> Gagal | G39: =IFERROR(__xludf.DUMMYFUNCTION("""COMPUTED_VALUE"""),"2H1M") -> 2H1M | I39: =IFERROR(__xludf.DUMMYFUNCTION("""COMPUTED_VALUE"""),6.0) -> 6 | K39: =IFERROR(__xludf.DUMMYFUNCTION("""COMPUTED_VALUE"""),"tanya paket, lewat tanggal") -> tanya paket, lewat tanggal
A40: =IFERROR(__xludf.DUMMYFUNCTION("""COMPUTED_VALUE"""),46027.0) -> 46027 | B40: =IFERROR(__xludf.DUMMYFUNCTION("""COMPUTED_VALUE"""),"2601D039") -> 2601D039 | C40: =IFERROR(__xludf.DUMMYFUNCTION("""COMPUTED_VALUE"""),"Tanamalintan ") -> Tanamalintan | D40: =IFERROR(__xludf.DUMMYFUNCTION("""COMPUTED_VALUE"""),"083877965575") -> 083877965575 | E40: =IFERROR(__xludf.DUMMYFUNCTION("""COMPUTED_VALUE"""),"Website") -> Website | F40: =IFERROR(__xludf.DUMMYFUNCTION("""COMPUTED_VALUE"""),"Gagal") -> Gagal | G40: =IFERROR(__xludf.DUMMYFUNCTION("""COMPUTED_VALUE"""),"2H1M") -> 2H1M | I40: =IFERROR(__xludf.DUMMYFUNCTION("""COMPUTED_VALUE"""),60.0) -> 60 | K40: =IFERROR(__xludf.DUMMYFUNCTION("""COMPUTED_VALUE"""),"tunda lebaran tahun depan") -> tunda lebaran tahun depan
A41: =IFERROR(__xludf.DUMMYFUNCTION("""COMPUTED_VALUE"""),46027.0) -> 46027 | B41: =IFERROR(__xludf.DUMMYFUNCTION("""COMPUTED_VALUE"""),"2601D040") -> 2601D040 | C41: =IFERROR(__xludf.DUMMYFUNCTION("""COMPUTED_VALUE"""),"Gian Septim Rohmaduri") -> Gian Septim Rohmaduri | D41: =IFERROR(__xludf.DUMMYFUNCTION("""COMPUTED_VALUE"""),"081328834222") -> 081328834222 | E41: =IFERROR(__xludf.DUMMYFUNCTION("""COMPUTED_VALUE"""),"Instagram") -> Instagram | F41: =IFERROR(__xludf.DUMMYFUNCTION("""COMPUTED_VALUE"""),"Gagal") -> Gagal | I41: =IFERROR(__xludf.DUMMYFUNCTION("""COMPUTED_VALUE"""),10.0) -> 10 | K41: =IFERROR(__xludf.DUMMYFUNCTION("""COMPUTED_VALUE"""),"ga ada jawaban") -> ga ada jawaban
A42: =IFERROR(__xludf.DUMMYFUNCTION("""COMPUTED_VALUE"""),46027.0) -> 46027 | B42: =IFERROR(__xludf.DUMMYFUNCTION("""COMPUTED_VALUE"""),"2601D041") -> 2601D041 | C42: =IFERROR(__xludf.DUMMYFUNCTION("""COMPUTED_VALUE"""),"Bidadari Surga") -> Bidadari Surga | D42: =IFERROR(__xludf.DUMMYFUNCTION("""COMPUTED_VALUE"""),"082136616696") -> 082136616696 | E42: =IFERROR(__xludf.DUMMYFUNCTION("""COMPUTED_VALUE"""),"Instagram") -> Instagram | F42: =IFERROR(__xludf.DUMMYFUNCTION("""COMPUTED_VALUE"""),"Gagal") -> Gagal | G42: =IFERROR(__xludf.DUMMYFUNCTION("""COMPUTED_VALUE"""),"3H2M") -> 3H2M | I42: =IFERROR(__xludf.DUMMYFUNCTION("""COMPUTED_VALUE"""),27.0) -> 27 | K42: =IFERROR(__xludf.DUMMYFUNCTION("""COMPUTED_VALUE"""),"FU MARET") -> FU MARET
A43: =IFERROR(__xludf.DUMMYFUNCTION("""COMPUTED_VALUE"""),46027.0) -> 46027 | B43: =IFERROR(__xludf.DUMMYFUNCTION("""COMPUTED_VALUE"""),"2601D042") -> 2601D042 | C43: =IFERROR(__xludf.DUMMYFUNCTION("""COMPUTED_VALUE"""),"Rosa Tan") -> Rosa Tan | D43: =IFERROR(__xludf.DUMMYFUNCTION("""COMPUTED_VALUE"""),"08562877979") -> 08562877979 | E43: =IFERROR(__xludf.DUMMYFUNCTION("""COMPUTED_VALUE"""),"Lainnya") -> Lainnya | F43: =IFERROR(__xludf.DUMMYFUNCTION("""COMPUTED_VALUE"""),"Gagal") -> Gagal | G43: =IFERROR(__xludf.DUMMYFUNCTION("""COMPUTED_VALUE"""),"3H2M OR 2H1M") -> 3H2M OR 2H1M | I43: =IFERROR(__xludf.DUMMYFUNCTION("""COMPUTED_VALUE"""),50.0) -> 50 | J43: =IFERROR(__xludf.DUMMYFUNCTION("""COMPUTED_VALUE"""),4.5E7) -> 45000000 | K43: =IFERROR(__xludf.DUMMYFUNCTION("""COMPUTED_VALUE"""),"DESTINASI SENIOR FRIENDLY, follow up mei") -> DESTINASI SENIOR FRIENDLY, follow up mei
A44: =IFERROR(__xludf.DUMMYFUNCTION("""COMPUTED_VALUE"""),46027.0) -> 46027 | B44: =IFERROR(__xludf.DUMMYFUNCTION("""COMPUTED_VALUE"""),"2601D043") -> 2601D043 | C44: =IFERROR(__xludf.DUMMYFUNCTION("""COMPUTED_VALUE"""),"Dwi K") -> Dwi K | D44: =IFERROR(__xludf.DUMMYFUNCTION("""COMPUTED_VALUE"""),"0811822328") -> 0811822328 | E44: =IFERROR(__xludf.DUMMYFUNCTION("""COMPUTED_VALUE"""),"Website") -> Website | F44: =IFERROR(__xludf.DUMMYFUNCTION("""COMPUTED_VALUE"""),"Gagal") -> Gagal | G44: =IFERROR(__xludf.DUMMYFUNCTION("""COMPUTED_VALUE"""),"OT 3h2m") -> OT 3h2m | K44: =IFERROR(__xludf.DUMMYFUNCTION("""COMPUTED_VALUE"""),"tidak jawab") -> tidak jawab
A45: =IFERROR(__xludf.DUMMYFUNCTION("""COMPUTED_VALUE"""),46027.0) -> 46027 | B45: =IFERROR(__xludf.DUMMYFUNCTION("""COMPUTED_VALUE"""),"2601D044") -> 2601D044 | C45: =IFERROR(__xludf.DUMMYFUNCTION("""COMPUTED_VALUE"""),"Dian Indra") -> Dian Indra | D45: =IFERROR(__xludf.DUMMYFUNCTION("""COMPUTED_VALUE"""),"08123589756") -> 08123589756 | E45: =IFERROR(__xludf.DUMMYFUNCTION("""COMPUTED_VALUE"""),"Instagram") -> Instagram | F45: =IFERROR(__xludf.DUMMYFUNCTION("""COMPUTED_VALUE"""),"Closing") -> Closing | G45: =IFERROR(__xludf.DUMMYFUNCTION("""COMPUTED_VALUE"""),"2H1M opsi c") -> 2H1M opsi c | I45: =IFERROR(__xludf.DUMMYFUNCTION("""COMPUTED_VALUE"""),4.0) -> 4 | J45: =IFERROR(__xludf.DUMMYFUNCTION("""COMPUTED_VALUE"""),4090000.0) -> 4090000 | K45: =IFERROR(__xludf.DUMMYFUNCTION("""COMPUTED_VALUE"""),"sudah closing") -> sudah closing
A46: =IFERROR(__xludf.DUMMYFUNCTION("""COMPUTED_VALUE"""),46027.0) -> 46027 | B46: =IFERROR(__xludf.DUMMYFUNCTION("""COMPUTED_VALUE"""),"2601D045") -> 2601D045 | C46: =IFERROR(__xludf.DUMMYFUNCTION("""COMPUTED_VALUE"""),"D. Luhki") -> D. Luhki | D46: =IFERROR(__xludf.DUMMYFUNCTION("""COMPUTED_VALUE"""),"0818575855") -> 0818575855 | E46: =IFERROR(__xludf.DUMMYFUNCTION("""COMPUTED_VALUE"""),"Lainnya") -> Lainnya | F46: =IFERROR(__xludf.DUMMYFUNCTION("""COMPUTED_VALUE"""),"Gagal") -> Gagal | G46: =IFERROR(__xludf.DUMMYFUNCTION("""COMPUTED_VALUE"""),"2D1N") -> 2D1N | I46: =IFERROR(__xludf.DUMMYFUNCTION("""COMPUTED_VALUE"""),60.0) -> 60 | K46: =IFERROR(__xludf.DUMMYFUNCTION("""COMPUTED_VALUE"""),"sdh fu tanggal 17") -> sdh fu tanggal 17
A47: =IFERROR(__xludf.DUMMYFUNCTION("""COMPUTED_VALUE"""),46027.0) -> 46027 | B47: =IFERROR(__xludf.DUMMYFUNCTION("""COMPUTED_VALUE"""),"2601D046") -> 2601D046 | C47: =IFERROR(__xludf.DUMMYFUNCTION("""COMPUTED_VALUE"""),"Erlangga") -> Erlangga | D47: =IFERROR(__xludf.DUMMYFUNCTION("""COMPUTED_VALUE"""),"0895340047293") -> 0895340047293 | E47: =IFERROR(__xludf.DUMMYFUNCTION("""COMPUTED_VALUE"""),"Website") -> Website | F47: =IFERROR(__xludf.DUMMYFUNCTION("""COMPUTED_VALUE"""),"Gagal") -> Gagal | G47: =IFERROR(__xludf.DUMMYFUNCTION("""COMPUTED_VALUE"""),"3H2M") -> 3H2M | I47: =IFERROR(__xludf.DUMMYFUNCTION("""COMPUTED_VALUE"""),100.0) -> 100 | J47: =IFERROR(__xludf.DUMMYFUNCTION("""COMPUTED_VALUE"""),1.346E8) -> 134600000 | K47: =IFERROR(__xludf.DUMMYFUNCTION("""COMPUTED_VALUE"""),"tidak ada jawaban") -> tidak ada jawaban
A48: =IFERROR(__xludf.DUMMYFUNCTION("""COMPUTED_VALUE"""),46027.0) -> 46027 | B48: =IFERROR(__xludf.DUMMYFUNCTION("""COMPUTED_VALUE"""),"2601D047") -> 2601D047 | C48: =IFERROR(__xludf.DUMMYFUNCTION("""COMPUTED_VALUE"""),"KAI WNA ") -> KAI WNA | D48: =IFERROR(__xludf.DUMMYFUNCTION("""COMPUTED_VALUE"""),"4915736805277") -> 4915736805277 | E48: =IFERROR(__xludf.DUMMYFUNCTION("""COMPUTED_VALUE"""),"Website") -> Website | F48: =IFERROR(__xludf.DUMMYFUNCTION("""COMPUTED_VALUE"""),"Gagal") -> Gagal | G48: =IFERROR(__xludf.DUMMYFUNCTION("""COMPUTED_VALUE"""),"TN ALAS PURWO") -> TN ALAS PURWO | I48: =IFERROR(__xludf.DUMMYFUNCTION("""COMPUTED_VALUE"""),2.0) -> 2 | K48: =IFERROR(__xludf.DUMMYFUNCTION("""COMPUTED_VALUE"""),"tdk ada kelanjutan") -> tdk ada kelanjutan
A49: =IFERROR(__xludf.DUMMYFUNCTION("""COMPUTED_VALUE"""),46027.0) -> 46027 | B49: =IFERROR(__xludf.DUMMYFUNCTION("""COMPUTED_VALUE"""),"2601D048") -> 2601D048 | C49: =IFERROR(__xludf.DUMMYFUNCTION("""COMPUTED_VALUE"""),"Nww") -> Nww | D49: =IFERROR(__xludf.DUMMYFUNCTION("""COMPUTED_VALUE"""),"082232269773") -> 082232269773 | E49: =IFERROR(__xludf.DUMMYFUNCTION("""COMPUTED_VALUE"""),"Website") -> Website | F49: =IFERROR(__xludf.DUMMYFUNCTION("""COMPUTED_VALUE"""),"Gagal") -> Gagal
A50: =IFERROR(__xludf.DUMMYFUNCTION("""COMPUTED_VALUE"""),46027.0) -> 46027 | B50: =IFERROR(__xludf.DUMMYFUNCTION("""COMPUTED_VALUE"""),"2601D049") -> 2601D049 | C50: =IFERROR(__xludf.DUMMYFUNCTION("""COMPUTED_VALUE"""),"Fjr") -> Fjr | D50: =IFERROR(__xludf.DUMMYFUNCTION("""COMPUTED_VALUE"""),"081937743496") -> 081937743496 | E50: =IFERROR(__xludf.DUMMYFUNCTION("""COMPUTED_VALUE"""),"Instagram") -> Instagram | F50: =IFERROR(__xludf.DUMMYFUNCTION("""COMPUTED_VALUE"""),"Gagal") -> Gagal | G50: =IFERROR(__xludf.DUMMYFUNCTION("""COMPUTED_VALUE"""),"trip bedil ") -> trip bedil | K50: =IFERROR(__xludf.DUMMYFUNCTION("""COMPUTED_VALUE"""),"tidak jawab") -> tidak jawab
A51: =IFERROR(__xludf.DUMMYFUNCTION("""COMPUTED_VALUE"""),46027.0) -> 46027 | B51: =IFERROR(__xludf.DUMMYFUNCTION("""COMPUTED_VALUE"""),"2601D050") -> 2601D050 | C51: =IFERROR(__xludf.DUMMYFUNCTION("""COMPUTED_VALUE"""),"Agus Trisunu") -> Agus Trisunu | D51: =IFERROR(__xludf.DUMMYFUNCTION("""COMPUTED_VALUE"""),"082198600529") -> 082198600529 | E51: =IFERROR(__xludf.DUMMYFUNCTION("""COMPUTED_VALUE"""),"Website") -> Website | F51: =IFERROR(__xludf.DUMMYFUNCTION("""COMPUTED_VALUE"""),"Gagal") -> Gagal | G51: =IFERROR(__xludf.DUMMYFUNCTION("""COMPUTED_VALUE"""),"3H2M ") -> 3H2M | H51: =IFERROR(__xludf.DUMMYFUNCTION("""COMPUTED_VALUE"""),46042.0) -> 46042 | I51: =IFERROR(__xludf.DUMMYFUNCTION("""COMPUTED_VALUE"""),2.0) -> 2 | K51: =IFERROR(__xludf.DUMMYFUNCTION("""COMPUTED_VALUE"""),"batal") -> batal
A52: =IFERROR(__xludf.DUMMYFUNCTION("""COMPUTED_VALUE"""),46027.0) -> 46027 | B52: =IFERROR(__xludf.DUMMYFUNCTION("""COMPUTED_VALUE"""),"2601D051") -> 2601D051 | C52: =IFERROR(__xludf.DUMMYFUNCTION("""COMPUTED_VALUE"""),"SriH fai hai") -> SriH fai hai | D52: =IFERROR(__xludf.DUMMYFUNCTION("""COMPUTED_VALUE"""),"081317770228") -> 081317770228 | E52: =IFERROR(__xludf.DUMMYFUNCTION("""COMPUTED_VALUE"""),"Instagram") -> Instagram | F52: =IFERROR(__xludf.DUMMYFUNCTION("""COMPUTED_VALUE"""),"Closing") -> Closing | G52: =IFERROR(__xludf.DUMMYFUNCTION("""COMPUTED_VALUE"""),"3H2M") -> 3H2M | J52: =IFERROR(__xludf.DUMMYFUNCTION("""COMPUTED_VALUE"""),6400000.0) -> 6400000
A53: =IFERROR(__xludf.DUMMYFUNCTION("""COMPUTED_VALUE"""),46027.0) -> 46027 | B53: =IFERROR(__xludf.DUMMYFUNCTION("""COMPUTED_VALUE"""),"2601D052") -> 2601D052 | C53: =IFERROR(__xludf.DUMMYFUNCTION("""COMPUTED_VALUE"""),"Athaya") -> Athaya | D53: =IFERROR(__xludf.DUMMYFUNCTION("""COMPUTED_VALUE"""),"087786696160") -> 087786696160 | E53: =IFERROR(__xludf.DUMMYFUNCTION("""COMPUTED_VALUE"""),"Lainnya") -> Lainnya | F53: =IFERROR(__xludf.DUMMYFUNCTION("""COMPUTED_VALUE"""),"Gagal") -> Gagal | G53: =IFERROR(__xludf.DUMMYFUNCTION("""COMPUTED_VALUE"""),"OT 1 day") -> OT 1 day | H53: =IFERROR(__xludf.DUMMYFUNCTION("""COMPUTED_VALUE"""),46042.0) -> 46042 | I53: =IFERROR(__xludf.DUMMYFUNCTION("""COMPUTED_VALUE"""),1.0) -> 1 | K53: =IFERROR(__xludf.DUMMYFUNCTION("""COMPUTED_VALUE"""),"tidak ada barengan") -> tidak ada barengan
A54: =IFERROR(__xludf.DUMMYFUNCTION("""COMPUTED_VALUE"""),46028.0) -> 46028 | B54: =IFERROR(__xludf.DUMMYFUNCTION("""COMPUTED_VALUE"""),"2601D053") -> 2601D053 | C54: =IFERROR(__xludf.DUMMYFUNCTION("""COMPUTED_VALUE"""),"Beni Kosnadi") -> Beni Kosnadi | D54: =IFERROR(__xludf.DUMMYFUNCTION("""COMPUTED_VALUE"""),"082297981197") -> 082297981197 | E54: =IFERROR(__xludf.DUMMYFUNCTION("""COMPUTED_VALUE"""),"Instagram") -> Instagram | F54: =IFERROR(__xludf.DUMMYFUNCTION("""COMPUTED_VALUE"""),"Gagal") -> Gagal | G54: =IFERROR(__xludf.DUMMYFUNCTION("""COMPUTED_VALUE"""),"OT 1 day Menjangan") -> OT 1 day Menjangan | H54: =IFERROR(__xludf.DUMMYFUNCTION("""COMPUTED_VALUE"""),46039.0) -> 46039 | I54: =IFERROR(__xludf.DUMMYFUNCTION("""COMPUTED_VALUE"""),1.0) -> 1 | K54: =IFERROR(__xludf.DUMMYFUNCTION("""COMPUTED_VALUE"""),"sdh dapat trip") -> sdh dapat trip
A55: =IFERROR(__xludf.DUMMYFUNCTION("""COMPUTED_VALUE"""),46028.0) -> 46028 | B55: =IFERROR(__xludf.DUMMYFUNCTION("""COMPUTED_VALUE"""),"2601D054") -> 2601D054 | C55: =IFERROR(__xludf.DUMMYFUNCTION("""COMPUTED_VALUE"""),"Nsyw") -> Nsyw | D55: =IFERROR(__xludf.DUMMYFUNCTION("""COMPUTED_VALUE"""),"085156302725") -> 085156302725 | E55: =IFERROR(__xludf.DUMMYFUNCTION("""COMPUTED_VALUE"""),"Instagram") -> Instagram | F55: =IFERROR(__xludf.DUMMYFUNCTION("""COMPUTED_VALUE"""),"Gagal") -> Gagal | G55: =IFERROR(__xludf.DUMMYFUNCTION("""COMPUTED_VALUE"""),"OT 3H2M") -> OT 3H2M | K55: =IFERROR(__xludf.DUMMYFUNCTION("""COMPUTED_VALUE"""),"masih liat katalog") -> masih liat katalog
A56: =IFERROR(__xludf.DUMMYFUNCTION("""COMPUTED_VALUE"""),46028.0) -> 46028 | B56: =IFERROR(__xludf.DUMMYFUNCTION("""COMPUTED_VALUE"""),"2601D055") -> 2601D055 | C56: =IFERROR(__xludf.DUMMYFUNCTION("""COMPUTED_VALUE"""),"Hari setiyawati ") -> Hari setiyawati | D56: =IFERROR(__xludf.DUMMYFUNCTION("""COMPUTED_VALUE"""),"085921091374") -> 085921091374 | E56: =IFERROR(__xludf.DUMMYFUNCTION("""COMPUTED_VALUE"""),"Website") -> Website | F56: =IFERROR(__xludf.DUMMYFUNCTION("""COMPUTED_VALUE"""),"Gagal") -> Gagal | G56: =IFERROR(__xludf.DUMMYFUNCTION("""COMPUTED_VALUE"""),"custom 3H2M") -> custom 3H2M | I56: =IFERROR(__xludf.DUMMYFUNCTION("""COMPUTED_VALUE"""),18.0) -> 18 | K56: =IFERROR(__xludf.DUMMYFUNCTION("""COMPUTED_VALUE"""),"tidak jadi budged tidak cukup") -> tidak jadi budged tidak cukup
A57: =IFERROR(__xludf.DUMMYFUNCTION("""COMPUTED_VALUE"""),46028.0) -> 46028 | B57: =IFERROR(__xludf.DUMMYFUNCTION("""COMPUTED_VALUE"""),"2601D056") -> 2601D056 | C57: =IFERROR(__xludf.DUMMYFUNCTION("""COMPUTED_VALUE"""),"Robby rinaldy") -> Robby rinaldy | D57: =IFERROR(__xludf.DUMMYFUNCTION("""COMPUTED_VALUE"""),"082122227424") -> 082122227424 | E57: =IFERROR(__xludf.DUMMYFUNCTION("""COMPUTED_VALUE"""),"Instagram") -> Instagram | F57: =IFERROR(__xludf.DUMMYFUNCTION("""COMPUTED_VALUE"""),"Gagal") -> Gagal | H57: =IFERROR(__xludf.DUMMYFUNCTION("""COMPUTED_VALUE"""),46038.0) -> 46038 | I57: =IFERROR(__xludf.DUMMYFUNCTION("""COMPUTED_VALUE"""),1.0) -> 1 | K57: =IFERROR(__xludf.DUMMYFUNCTION("""COMPUTED_VALUE"""),"CARI TEMEN TRIP, lwt tanggal") -> CARI TEMEN TRIP, lwt tanggal
A58: =IFERROR(__xludf.DUMMYFUNCTION("""COMPUTED_VALUE"""),46028.0) -> 46028 | B58: =IFERROR(__xludf.DUMMYFUNCTION("""COMPUTED_VALUE"""),"2601D057") -> 2601D057 | C58: =IFERROR(__xludf.DUMMYFUNCTION("""COMPUTED_VALUE"""),"Farrel Raynaldi") -> Farrel Raynaldi | D58: =IFERROR(__xludf.DUMMYFUNCTION("""COMPUTED_VALUE"""),"087762831355") -> 087762831355 | E58: =IFERROR(__xludf.DUMMYFUNCTION("""COMPUTED_VALUE"""),"Website") -> Website | F58: =IFERROR(__xludf.DUMMYFUNCTION("""COMPUTED_VALUE"""),"Gagal") -> Gagal | G58: =IFERROR(__xludf.DUMMYFUNCTION("""COMPUTED_VALUE"""),"3H2M") -> 3H2M | I58: =IFERROR(__xludf.DUMMYFUNCTION("""COMPUTED_VALUE"""),30.0) -> 30 | K58: =IFERROR(__xludf.DUMMYFUNCTION("""COMPUTED_VALUE"""),"tidak jawab") -> tidak jawab
A59: =IFERROR(__xludf.DUMMYFUNCTION("""COMPUTED_VALUE"""),46028.0) -> 46028 | B59: =IFERROR(__xludf.DUMMYFUNCTION("""COMPUTED_VALUE"""),"2601D058") -> 2601D058 | C59: =IFERROR(__xludf.DUMMYFUNCTION("""COMPUTED_VALUE"""),"Hajar adiwiyana ") -> Hajar adiwiyana | D59: =IFERROR(__xludf.DUMMYFUNCTION("""COMPUTED_VALUE"""),"085755999900") -> 085755999900 | E59: =IFERROR(__xludf.DUMMYFUNCTION("""COMPUTED_VALUE"""),"Instagram") -> Instagram | F59: =IFERROR(__xludf.DUMMYFUNCTION("""COMPUTED_VALUE"""),"Gagal") -> Gagal | G59: =IFERROR(__xludf.DUMMYFUNCTION("""COMPUTED_VALUE"""),"2H1M") -> 2H1M | I59: =IFERROR(__xludf.DUMMYFUNCTION("""COMPUTED_VALUE"""),2.0) -> 2 | K59: =IFERROR(__xludf.DUMMYFUNCTION("""COMPUTED_VALUE"""),"pending ke bwi") -> pending ke bwi
A60: =IFERROR(__xludf.DUMMYFUNCTION("""COMPUTED_VALUE"""),46028.0) -> 46028 | B60: =IFERROR(__xludf.DUMMYFUNCTION("""COMPUTED_VALUE"""),"2601D059") -> 2601D059 | C60: =IFERROR(__xludf.DUMMYFUNCTION("""COMPUTED_VALUE"""),"Weny") -> Weny | D60: =IFERROR(__xludf.DUMMYFUNCTION("""COMPUTED_VALUE"""),"08125262656") -> 08125262656 | E60: =IFERROR(__xludf.DUMMYFUNCTION("""COMPUTED_VALUE"""),"Website") -> Website | F60: =IFERROR(__xludf.DUMMYFUNCTION("""COMPUTED_VALUE"""),"Gagal") -> Gagal | G60: =IFERROR(__xludf.DUMMYFUNCTION("""COMPUTED_VALUE"""),"2H1M") -> 2H1M | K60: =IFERROR(__xludf.DUMMYFUNCTION("""COMPUTED_VALUE"""),"start sby") -> start sby
A61: =IFERROR(__xludf.DUMMYFUNCTION("""COMPUTED_VALUE"""),46028.0) -> 46028 | B61: =IFERROR(__xludf.DUMMYFUNCTION("""COMPUTED_VALUE"""),"2601D060") -> 2601D060 | C61: =IFERROR(__xludf.DUMMYFUNCTION("""COMPUTED_VALUE"""),"Yande BaliBagus") -> Yande BaliBagus | D61: =IFERROR(__xludf.DUMMYFUNCTION("""COMPUTED_VALUE"""),"081225318054") -> 081225318054 | E61: =IFERROR(__xludf.DUMMYFUNCTION("""COMPUTED_VALUE"""),"Website") -> Website | F61: =IFERROR(__xludf.DUMMYFUNCTION("""COMPUTED_VALUE"""),"Gagal") -> Gagal | G61: =IFERROR(__xludf.DUMMYFUNCTION("""COMPUTED_VALUE"""),"2H1M (trekking ijen)") -> 2H1M (trekking ijen) | I61: =IFERROR(__xludf.DUMMYFUNCTION("""COMPUTED_VALUE"""),4.0) -> 4 | J61: =IFERROR(__xludf.DUMMYFUNCTION("""COMPUTED_VALUE"""),6600000.0) -> 6600000 | K61: =IFERROR(__xludf.DUMMYFUNCTION("""COMPUTED_VALUE"""),"follow up akhir februari") -> follow up akhir februari
A62: =IFERROR(__xludf.DUMMYFUNCTION("""COMPUTED_VALUE"""),46028.0) -> 46028 | B62: =IFERROR(__xludf.DUMMYFUNCTION("""COMPUTED_VALUE"""),"2601D061") -> 2601D061 | C62: =IFERROR(__xludf.DUMMYFUNCTION("""COMPUTED_VALUE"""),"Sinta julianti ") -> Sinta julianti | D62: =IFERROR(__xludf.DUMMYFUNCTION("""COMPUTED_VALUE"""),"085865365502") -> 085865365502 | E62: =IFERROR(__xludf.DUMMYFUNCTION("""COMPUTED_VALUE"""),"Instagram") -> Instagram | F62: =IFERROR(__xludf.DUMMYFUNCTION("""COMPUTED_VALUE"""),"Gagal") -> Gagal | K62: =IFERROR(__xludf.DUMMYFUNCTION("""COMPUTED_VALUE"""),"tidak jawab") -> tidak jawab
A63: =IFERROR(__xludf.DUMMYFUNCTION("""COMPUTED_VALUE"""),46029.0) -> 46029 | B63: =IFERROR(__xludf.DUMMYFUNCTION("""COMPUTED_VALUE"""),"2601D062") -> 2601D062 | C63: =IFERROR(__xludf.DUMMYFUNCTION("""COMPUTED_VALUE"""),"Rachel") -> Rachel | D63: =IFERROR(__xludf.DUMMYFUNCTION("""COMPUTED_VALUE"""),"085775220152") -> 085775220152 | E63: =IFERROR(__xludf.DUMMYFUNCTION("""COMPUTED_VALUE"""),"Instagram") -> Instagram | F63: =IFERROR(__xludf.DUMMYFUNCTION("""COMPUTED_VALUE"""),"Gagal") -> Gagal | H63: =IFERROR(__xludf.DUMMYFUNCTION("""COMPUTED_VALUE"""),46038.0) -> 46038 | K63: =IFERROR(__xludf.DUMMYFUNCTION("""COMPUTED_VALUE"""),"tidak jawab") -> tidak jawab
A64: =IFERROR(__xludf.DUMMYFUNCTION("""COMPUTED_VALUE"""),46029.0) -> 46029 | B64: =IFERROR(__xludf.DUMMYFUNCTION("""COMPUTED_VALUE"""),"2601D063") -> 2601D063 | C64: =IFERROR(__xludf.DUMMYFUNCTION("""COMPUTED_VALUE"""),"Sobar") -> Sobar | D64: =IFERROR(__xludf.DUMMYFUNCTION("""COMPUTED_VALUE"""),"081353674012") -> 081353674012 | E64: =IFERROR(__xludf.DUMMYFUNCTION("""COMPUTED_VALUE"""),"Lainnya") -> Lainnya | F64: =IFERROR(__xludf.DUMMYFUNCTION("""COMPUTED_VALUE"""),"Gagal") -> Gagal | G64: =IFERROR(__xludf.DUMMYFUNCTION("""COMPUTED_VALUE"""),"OT D TI") -> OT D TI | H64: =IFERROR(__xludf.DUMMYFUNCTION("""COMPUTED_VALUE"""),46030.0) -> 46030 | I64: =IFERROR(__xludf.DUMMYFUNCTION("""COMPUTED_VALUE"""),1.0) -> 1 | K64: =IFERROR(__xludf.DUMMYFUNCTION("""COMPUTED_VALUE"""),"tidak ada barengan") -> tidak ada barengan
A65: =IFERROR(__xludf.DUMMYFUNCTION("""COMPUTED_VALUE"""),46030.0) -> 46030 | B65: =IFERROR(__xludf.DUMMYFUNCTION("""COMPUTED_VALUE"""),"2601D064") -> 2601D064 | C65: =IFERROR(__xludf.DUMMYFUNCTION("""COMPUTED_VALUE"""),"Nanik A") -> Nanik A | D65: =IFERROR(__xludf.DUMMYFUNCTION("""COMPUTED_VALUE"""),"082225737622") -> 082225737622 | E65: =IFERROR(__xludf.DUMMYFUNCTION("""COMPUTED_VALUE"""),"Instagram") -> Instagram | F65: =IFERROR(__xludf.DUMMYFUNCTION("""COMPUTED_VALUE"""),"Gagal") -> Gagal | G65: =IFERROR(__xludf.DUMMYFUNCTION("""COMPUTED_VALUE"""),"Trip djawatan baluran") -> Trip djawatan baluran | I65: =IFERROR(__xludf.DUMMYFUNCTION("""COMPUTED_VALUE"""),3.0) -> 3 | K65: =IFERROR(__xludf.DUMMYFUNCTION("""COMPUTED_VALUE"""),"nunggu jadwal cuti") -> nunggu jadwal cuti
A66: =IFERROR(__xludf.DUMMYFUNCTION("""COMPUTED_VALUE"""),46030.0) -> 46030 | B66: =IFERROR(__xludf.DUMMYFUNCTION("""COMPUTED_VALUE"""),"2601D065") -> 2601D065 | C66: =IFERROR(__xludf.DUMMYFUNCTION("""COMPUTED_VALUE"""),"Ganang Age") -> Ganang Age | D66: =IFERROR(__xludf.DUMMYFUNCTION("""COMPUTED_VALUE"""),"0895363160977") -> 0895363160977 | E66: =IFERROR(__xludf.DUMMYFUNCTION("""COMPUTED_VALUE"""),"Lainnya") -> Lainnya | F66: =IFERROR(__xludf.DUMMYFUNCTION("""COMPUTED_VALUE"""),"Gagal") -> Gagal | K66: =IFERROR(__xludf.DUMMYFUNCTION("""COMPUTED_VALUE"""),"tidak jawab") -> tidak jawab
A67: =IFERROR(__xludf.DUMMYFUNCTION("""COMPUTED_VALUE"""),46030.0) -> 46030 | B67: =IFERROR(__xludf.DUMMYFUNCTION("""COMPUTED_VALUE"""),"2601D066") -> 2601D066 | C67: =IFERROR(__xludf.DUMMYFUNCTION("""COMPUTED_VALUE"""),"Adhelia") -> Adhelia | D67: =IFERROR(__xludf.DUMMYFUNCTION("""COMPUTED_VALUE"""),"082335290562") -> 082335290562 | E67: =IFERROR(__xludf.DUMMYFUNCTION("""COMPUTED_VALUE"""),"Lainnya") -> Lainnya | F67: =IFERROR(__xludf.DUMMYFUNCTION("""COMPUTED_VALUE"""),"Gagal") -> Gagal | G67: =IFERROR(__xludf.DUMMYFUNCTION("""COMPUTED_VALUE"""),"Trip baluran ") -> Trip baluran | I67: =IFERROR(__xludf.DUMMYFUNCTION("""COMPUTED_VALUE"""),4.0) -> 4 | K67: =IFERROR(__xludf.DUMMYFUNCTION("""COMPUTED_VALUE"""),"ga jawab") -> ga jawab
A68: =IFERROR(__xludf.DUMMYFUNCTION("""COMPUTED_VALUE"""),46030.0) -> 46030 | B68: =IFERROR(__xludf.DUMMYFUNCTION("""COMPUTED_VALUE"""),"2601D067") -> 2601D067 | C68: =IFERROR(__xludf.DUMMYFUNCTION("""COMPUTED_VALUE"""),"Khoirunnisa' linaas ") -> Khoirunnisa' linaas | D68: =IFERROR(__xludf.DUMMYFUNCTION("""COMPUTED_VALUE"""),"081230352078") -> 081230352078 | E68: =IFERROR(__xludf.DUMMYFUNCTION("""COMPUTED_VALUE"""),"Instagram") -> Instagram | F68: =IFERROR(__xludf.DUMMYFUNCTION("""COMPUTED_VALUE"""),"Gagal") -> Gagal | G68: =IFERROR(__xludf.DUMMYFUNCTION("""COMPUTED_VALUE"""),"tim building KW") -> tim building KW | I68: =IFERROR(__xludf.DUMMYFUNCTION("""COMPUTED_VALUE"""),100.0) -> 100 | J68: =IFERROR(__xludf.DUMMYFUNCTION("""COMPUTED_VALUE"""),1.75E7) -> 17500000 | K68: =IFERROR(__xludf.DUMMYFUNCTION("""COMPUTED_VALUE"""),"tidak ada jawaban") -> tidak ada jawaban
A69: =IFERROR(__xludf.DUMMYFUNCTION("""COMPUTED_VALUE"""),46030.0) -> 46030 | B69: =IFERROR(__xludf.DUMMYFUNCTION("""COMPUTED_VALUE"""),"2601D068") -> 2601D068 | C69: =IFERROR(__xludf.DUMMYFUNCTION("""COMPUTED_VALUE"""),"No name WNA WNI") -> No name WNA WNI | D69: =IFERROR(__xludf.DUMMYFUNCTION("""COMPUTED_VALUE"""),"085784629188") -> 085784629188 | E69: =IFERROR(__xludf.DUMMYFUNCTION("""COMPUTED_VALUE"""),"Lainnya") -> Lainnya | F69: =IFERROR(__xludf.DUMMYFUNCTION("""COMPUTED_VALUE"""),"Gagal") -> Gagal | G69: =IFERROR(__xludf.DUMMYFUNCTION("""COMPUTED_VALUE"""),"custom desinasi") -> custom desinasi | I69: =IFERROR(__xludf.DUMMYFUNCTION("""COMPUTED_VALUE"""),2.0) -> 2 | K69: =IFERROR(__xludf.DUMMYFUNCTION("""COMPUTED_VALUE"""),"buat penawaran, FU pertengahan jan") -> buat penawaran, FU pertengahan jan
A70: =IFERROR(__xludf.DUMMYFUNCTION("""COMPUTED_VALUE"""),46030.0) -> 46030 | B70: =IFERROR(__xludf.DUMMYFUNCTION("""COMPUTED_VALUE"""),"2601D069") -> 2601D069 | C70: =IFERROR(__xludf.DUMMYFUNCTION("""COMPUTED_VALUE"""),"No name Maret") -> No name Maret | D70: =IFERROR(__xludf.DUMMYFUNCTION("""COMPUTED_VALUE"""),"081236371881") -> 081236371881 | E70: =IFERROR(__xludf.DUMMYFUNCTION("""COMPUTED_VALUE"""),"Instagram") -> Instagram | F70: =IFERROR(__xludf.DUMMYFUNCTION("""COMPUTED_VALUE"""),"Gagal") -> Gagal | G70: =IFERROR(__xludf.DUMMYFUNCTION("""COMPUTED_VALUE"""),"OT 3H2M") -> OT 3H2M | J70: =IFERROR(__xludf.DUMMYFUNCTION("""COMPUTED_VALUE"""),6400000.0) -> 6400000 | K70: =IFERROR(__xludf.DUMMYFUNCTION("""COMPUTED_VALUE"""),"tidak ada jawaban, sudah fu 5 kali") -> tidak ada jawaban, sudah fu 5 kali
A71: =IFERROR(__xludf.DUMMYFUNCTION("""COMPUTED_VALUE"""),46030.0) -> 46030 | B71: =IFERROR(__xludf.DUMMYFUNCTION("""COMPUTED_VALUE"""),"2601D070") -> 2601D070 | C71: =IFERROR(__xludf.DUMMYFUNCTION("""COMPUTED_VALUE"""),"Alfian ") -> Alfian | D71: =IFERROR(__xludf.DUMMYFUNCTION("""COMPUTED_VALUE"""),"085729019851") -> 085729019851 | E71: =IFERROR(__xludf.DUMMYFUNCTION("""COMPUTED_VALUE"""),"Lainnya") -> Lainnya | F71: =IFERROR(__xludf.DUMMYFUNCTION("""COMPUTED_VALUE"""),"Gagal") -> Gagal | G71: =IFERROR(__xludf.DUMMYFUNCTION("""COMPUTED_VALUE"""),"private trip") -> private trip | I71: =IFERROR(__xludf.DUMMYFUNCTION("""COMPUTED_VALUE"""),5.0) -> 5 | K71: =IFERROR(__xludf.DUMMYFUNCTION("""COMPUTED_VALUE"""),"tanya tanya, sudah FU tgl 9") -> tanya tanya, sudah FU tgl 9
A72: =IFERROR(__xludf.DUMMYFUNCTION("""COMPUTED_VALUE"""),46030.0) -> 46030 | B72: =IFERROR(__xludf.DUMMYFUNCTION("""COMPUTED_VALUE"""),"2601D071") -> 2601D071 | C72: =IFERROR(__xludf.DUMMYFUNCTION("""COMPUTED_VALUE"""),"Terry sukma ezaria") -> Terry sukma ezaria | D72: =IFERROR(__xludf.DUMMYFUNCTION("""COMPUTED_VALUE"""),"081910004277") -> 081910004277 | E72: =IFERROR(__xludf.DUMMYFUNCTION("""COMPUTED_VALUE"""),"Instagram") -> Instagram | F72: =IFERROR(__xludf.DUMMYFUNCTION("""COMPUTED_VALUE"""),"Prospek") -> Prospek | G72: =IFERROR(__xludf.DUMMYFUNCTION("""COMPUTED_VALUE"""),"paket custom") -> paket custom | J72: =IFERROR(__xludf.DUMMYFUNCTION("""COMPUTED_VALUE"""),1.44E8) -> 144000000 | K72: =IFERROR(__xludf.DUMMYFUNCTION("""COMPUTED_VALUE"""),"buat penawaran, FU 2 Juni ") -> buat penawaran, FU 2 Juni | L72: =IFERROR(__xludf.DUMMYFUNCTION("""COMPUTED_VALUE"""),"https://docs.google.com/document/d/1fMFdvXachGDtyak_UDLjTqjsPv8dJU-8h8riaob89KM/edit?tab=t.0") -> https://docs.google.com/document/d/1fMFdvXachGDtyak_UDLjTqjsPv8dJU-8h8riaob89KM/edit?tab=t.0
A73: =IFERROR(__xludf.DUMMYFUNCTION("""COMPUTED_VALUE"""),46030.0) -> 46030 | B73: =IFERROR(__xludf.DUMMYFUNCTION("""COMPUTED_VALUE"""),"2601D072") -> 2601D072 | C73: =IFERROR(__xludf.DUMMYFUNCTION("""COMPUTED_VALUE"""),"Novia dian ") -> Novia dian | D73: =IFERROR(__xludf.DUMMYFUNCTION("""COMPUTED_VALUE"""),"087748304348") -> 087748304348 | E73: =IFERROR(__xludf.DUMMYFUNCTION("""COMPUTED_VALUE"""),"Instagram") -> Instagram | F73: =IFERROR(__xludf.DUMMYFUNCTION("""COMPUTED_VALUE"""),"Gagal") -> Gagal | G73: =IFERROR(__xludf.DUMMYFUNCTION("""COMPUTED_VALUE"""),"OT 3H2M") -> OT 3H2M | I73: =IFERROR(__xludf.DUMMYFUNCTION("""COMPUTED_VALUE"""),1.0) -> 1 | K73: =IFERROR(__xludf.DUMMYFUNCTION("""COMPUTED_VALUE"""),"tidak ada jawaban dan barengan, lewat tanggal") -> tidak ada jawaban dan barengan, lewat tanggal
A74: =IFERROR(__xludf.DUMMYFUNCTION("""COMPUTED_VALUE"""),46031.0) -> 46031 | B74: =IFERROR(__xludf.DUMMYFUNCTION("""COMPUTED_VALUE"""),"2601D073") -> 2601D073 | C74: =IFERROR(__xludf.DUMMYFUNCTION("""COMPUTED_VALUE"""),"Nusroh Linnas") -> Nusroh Linnas | D74: =IFERROR(__xludf.DUMMYFUNCTION("""COMPUTED_VALUE"""),"08973257454") -> 08973257454 | E74: =IFERROR(__xludf.DUMMYFUNCTION("""COMPUTED_VALUE"""),"Instagram") -> Instagram | F74: =IFERROR(__xludf.DUMMYFUNCTION("""COMPUTED_VALUE"""),"Gagal") -> Gagal | K74: =IFERROR(__xludf.DUMMYFUNCTION("""COMPUTED_VALUE"""),"tanya terkait dokumentasi ") -> tanya terkait dokumentasi
A75: =IFERROR(__xludf.DUMMYFUNCTION("""COMPUTED_VALUE"""),46031.0) -> 46031 | B75: =IFERROR(__xludf.DUMMYFUNCTION("""COMPUTED_VALUE"""),"2601D074") -> 2601D074 | C75: =IFERROR(__xludf.DUMMYFUNCTION("""COMPUTED_VALUE"""),"Khalisa") -> Khalisa | D75: =IFERROR(__xludf.DUMMYFUNCTION("""COMPUTED_VALUE"""),"082159266648") -> 082159266648 | E75: =IFERROR(__xludf.DUMMYFUNCTION("""COMPUTED_VALUE"""),"Instagram") -> Instagram | F75: =IFERROR(__xludf.DUMMYFUNCTION("""COMPUTED_VALUE"""),"Gagal") -> Gagal | G75: =IFERROR(__xludf.DUMMYFUNCTION("""COMPUTED_VALUE"""),"Open trip MT") -> Open trip MT | J75: =IFERROR(__xludf.DUMMYFUNCTION("""COMPUTED_VALUE"""),1475000.0) -> 1475000 | K75: =IFERROR(__xludf.DUMMYFUNCTION("""COMPUTED_VALUE"""),"gajadi liburan tahun inii") -> gajadi liburan tahun inii | L75: =IFERROR(__xludf.DUMMYFUNCTION("""COMPUTED_VALUE"""),"https://docs.google.com/document/d/1vdzggSvQW_6p_JDwwPzKp9o4Qo3PymCg6LpFHcmIR1M/edit?tab=t.0") -> https://docs.google.com/document/d/1vdzggSvQW_6p_JDwwPzKp9o4Qo3PymCg6LpFHcmIR1M/edit?tab=t.0
A76: =IFERROR(__xludf.DUMMYFUNCTION("""COMPUTED_VALUE"""),46031.0) -> 46031 | B76: =IFERROR(__xludf.DUMMYFUNCTION("""COMPUTED_VALUE"""),"2601D075") -> 2601D075 | C76: =IFERROR(__xludf.DUMMYFUNCTION("""COMPUTED_VALUE"""),"Arifah") -> Arifah | D76: =IFERROR(__xludf.DUMMYFUNCTION("""COMPUTED_VALUE"""),"085174307926") -> 085174307926 | E76: =IFERROR(__xludf.DUMMYFUNCTION("""COMPUTED_VALUE"""),"Instagram") -> Instagram | F76: =IFERROR(__xludf.DUMMYFUNCTION("""COMPUTED_VALUE"""),"Review") -> Review | G76: =IFERROR(__xludf.DUMMYFUNCTION("""COMPUTED_VALUE"""),"Trip 4H3M") -> Trip 4H3M | I76: =IFERROR(__xludf.DUMMYFUNCTION("""COMPUTED_VALUE"""),4.0) -> 4 | J76: =IFERROR(__xludf.DUMMYFUNCTION("""COMPUTED_VALUE"""),8460000.0) -> 8460000 | K76: =IFERROR(__xludf.DUMMYFUNCTION("""COMPUTED_VALUE"""),"sdh closing") -> sdh closing
A77: =IFERROR(__xludf.DUMMYFUNCTION("""COMPUTED_VALUE"""),46031.0) -> 46031 | B77: =IFERROR(__xludf.DUMMYFUNCTION("""COMPUTED_VALUE"""),"2601D076") -> 2601D076 | C77: =IFERROR(__xludf.DUMMYFUNCTION("""COMPUTED_VALUE"""),"Livia") -> Livia | D77: =IFERROR(__xludf.DUMMYFUNCTION("""COMPUTED_VALUE"""),"085786328047") -> 085786328047 | E77: =IFERROR(__xludf.DUMMYFUNCTION("""COMPUTED_VALUE"""),"Instagram") -> Instagram | F77: =IFERROR(__xludf.DUMMYFUNCTION("""COMPUTED_VALUE"""),"Gagal") -> Gagal | K77: =IFERROR(__xludf.DUMMYFUNCTION("""COMPUTED_VALUE"""),"di FU tidak balas") -> di FU tidak balas | L77: =IFERROR(__xludf.DUMMYFUNCTION("""COMPUTED_VALUE"""),"https://docs.google.com/document/d/1GT9NMnoa3lcZIxGW9QCfVEc-3eBA1sFnuwQzkzq4o4M/edit?tab=t.0") -> https://docs.google.com/document/d/1GT9NMnoa3lcZIxGW9QCfVEc-3eBA1sFnuwQzkzq4o4M/edit?tab=t.0
A78: =IFERROR(__xludf.DUMMYFUNCTION("""COMPUTED_VALUE"""),46031.0) -> 46031 | B78: =IFERROR(__xludf.DUMMYFUNCTION("""COMPUTED_VALUE"""),"2601D077") -> 2601D077 | C78: =IFERROR(__xludf.DUMMYFUNCTION("""COMPUTED_VALUE"""),"Helsa") -> Helsa | D78: =IFERROR(__xludf.DUMMYFUNCTION("""COMPUTED_VALUE"""),"085721780257") -> 085721780257 | E78: =IFERROR(__xludf.DUMMYFUNCTION("""COMPUTED_VALUE"""),"Instagram") -> Instagram | F78: =IFERROR(__xludf.DUMMYFUNCTION("""COMPUTED_VALUE"""),"Gagal") -> Gagal | I78: =IFERROR(__xludf.DUMMYFUNCTION("""COMPUTED_VALUE"""),2.0) -> 2 | K78: =IFERROR(__xludf.DUMMYFUNCTION("""COMPUTED_VALUE"""),"tanya tanya, FU tgl 11") -> tanya tanya, FU tgl 11
A79: =IFERROR(__xludf.DUMMYFUNCTION("""COMPUTED_VALUE"""),46031.0) -> 46031 | B79: =IFERROR(__xludf.DUMMYFUNCTION("""COMPUTED_VALUE"""),"2601D078") -> 2601D078 | C79: =IFERROR(__xludf.DUMMYFUNCTION("""COMPUTED_VALUE"""),"Muawanah ") -> Muawanah | D79: =IFERROR(__xludf.DUMMYFUNCTION("""COMPUTED_VALUE"""),"08111626220") -> 08111626220 | E79: =IFERROR(__xludf.DUMMYFUNCTION("""COMPUTED_VALUE"""),"Lainnya") -> Lainnya | F79: =IFERROR(__xludf.DUMMYFUNCTION("""COMPUTED_VALUE"""),"Gagal") -> Gagal | G79: =IFERROR(__xludf.DUMMYFUNCTION("""COMPUTED_VALUE"""),"OT 3H2M") -> OT 3H2M | K79: =IFERROR(__xludf.DUMMYFUNCTION("""COMPUTED_VALUE"""),"nunggu info tanggal, FU tgl 11") -> nunggu info tanggal, FU tgl 11
A80: =IFERROR(__xludf.DUMMYFUNCTION("""COMPUTED_VALUE"""),46031.0) -> 46031 | B80: =IFERROR(__xludf.DUMMYFUNCTION("""COMPUTED_VALUE"""),"2601D079") -> 2601D079 | C80: =IFERROR(__xludf.DUMMYFUNCTION("""COMPUTED_VALUE"""),"Anis dadik") -> Anis dadik | D80: =IFERROR(__xludf.DUMMYFUNCTION("""COMPUTED_VALUE"""),"081238722671") -> 081238722671 | E80: =IFERROR(__xludf.DUMMYFUNCTION("""COMPUTED_VALUE"""),"Instagram") -> Instagram | F80: =IFERROR(__xludf.DUMMYFUNCTION("""COMPUTED_VALUE"""),"Gagal") -> Gagal | G80: =IFERROR(__xludf.DUMMYFUNCTION("""COMPUTED_VALUE"""),"Trip 3H2M") -> Trip 3H2M | I80: =IFERROR(__xludf.DUMMYFUNCTION("""COMPUTED_VALUE"""),2.0) -> 2 | K80: =IFERROR(__xludf.DUMMYFUNCTION("""COMPUTED_VALUE"""),"menunggu kabar selanjutnya, FU tgl 11") -> menunggu kabar selanjutnya, FU tgl 11
A81: =IFERROR(__xludf.DUMMYFUNCTION("""COMPUTED_VALUE"""),46031.0) -> 46031 | B81: =IFERROR(__xludf.DUMMYFUNCTION("""COMPUTED_VALUE"""),"2601D080") -> 2601D080 | C81: =IFERROR(__xludf.DUMMYFUNCTION("""COMPUTED_VALUE"""),"Tya mardin F.A") -> Tya mardin F.A | D81: =IFERROR(__xludf.DUMMYFUNCTION("""COMPUTED_VALUE"""),"081297769438") -> 081297769438 | E81: =IFERROR(__xludf.DUMMYFUNCTION("""COMPUTED_VALUE"""),"Lainnya") -> Lainnya | F81: =IFERROR(__xludf.DUMMYFUNCTION("""COMPUTED_VALUE"""),"Gagal") -> Gagal | K81: =IFERROR(__xludf.DUMMYFUNCTION("""COMPUTED_VALUE"""),"tanya mepo ") -> tanya mepo
A82: =IFERROR(__xludf.DUMMYFUNCTION("""COMPUTED_VALUE"""),46032.0) -> 46032 | B82: =IFERROR(__xludf.DUMMYFUNCTION("""COMPUTED_VALUE"""),"2601D081") -> 2601D081 | C82: =IFERROR(__xludf.DUMMYFUNCTION("""COMPUTED_VALUE"""),"Evi yemima ") -> Evi yemima | D82: =IFERROR(__xludf.DUMMYFUNCTION("""COMPUTED_VALUE"""),"08973106657") -> 08973106657 | E82: =IFERROR(__xludf.DUMMYFUNCTION("""COMPUTED_VALUE"""),"Instagram") -> Instagram | F82: =IFERROR(__xludf.DUMMYFUNCTION("""COMPUTED_VALUE"""),"Gagal") -> Gagal | G82: =IFERROR(__xludf.DUMMYFUNCTION("""COMPUTED_VALUE"""),"2H1M opsi C") -> 2H1M opsi C | K82: =IFERROR(__xludf.DUMMYFUNCTION("""COMPUTED_VALUE"""),"tanya tanya") -> tanya tanya
A83: =IFERROR(__xludf.DUMMYFUNCTION("""COMPUTED_VALUE"""),46032.0) -> 46032 | B83: =IFERROR(__xludf.DUMMYFUNCTION("""COMPUTED_VALUE"""),"2601D082") -> 2601D082 | C83: =IFERROR(__xludf.DUMMYFUNCTION("""COMPUTED_VALUE"""),"Yuninda cahyani") -> Yuninda cahyani | D83: =IFERROR(__xludf.DUMMYFUNCTION("""COMPUTED_VALUE"""),"08562899073") -> 08562899073 | E83: =IFERROR(__xludf.DUMMYFUNCTION("""COMPUTED_VALUE"""),"Lainnya") -> Lainnya | F83: =IFERROR(__xludf.DUMMYFUNCTION("""COMPUTED_VALUE"""),"Gagal") -> Gagal | G83: =IFERROR(__xludf.DUMMYFUNCTION("""COMPUTED_VALUE"""),"opsi 3H2M") -> opsi 3H2M | K83: =IFERROR(__xludf.DUMMYFUNCTION("""COMPUTED_VALUE"""),"cuaca tidak bersahabat") -> cuaca tidak bersahabat
A84: =IFERROR(__xludf.DUMMYFUNCTION("""COMPUTED_VALUE"""),46032.0) -> 46032 | B84: =IFERROR(__xludf.DUMMYFUNCTION("""COMPUTED_VALUE"""),"2601D083") -> 2601D083 | C84: =IFERROR(__xludf.DUMMYFUNCTION("""COMPUTED_VALUE"""),"Pel ") -> Pel | D84: =IFERROR(__xludf.DUMMYFUNCTION("""COMPUTED_VALUE"""),"081211252959") -> 081211252959 | E84: =IFERROR(__xludf.DUMMYFUNCTION("""COMPUTED_VALUE"""),"Instagram") -> Instagram | F84: =IFERROR(__xludf.DUMMYFUNCTION("""COMPUTED_VALUE"""),"Review") -> Review | G84: =IFERROR(__xludf.DUMMYFUNCTION("""COMPUTED_VALUE"""),"custom 2H1M ") -> custom 2H1M | I84: =IFERROR(__xludf.DUMMYFUNCTION("""COMPUTED_VALUE"""),4.0) -> 4 | J84: =IFERROR(__xludf.DUMMYFUNCTION("""COMPUTED_VALUE"""),6800000.0) -> 6800000 | K84: =IFERROR(__xludf.DUMMYFUNCTION("""COMPUTED_VALUE"""),"FU AKHIR JANUARI") -> FU AKHIR JANUARI
A85: =IFERROR(__xludf.DUMMYFUNCTION("""COMPUTED_VALUE"""),46032.0) -> 46032 | B85: =IFERROR(__xludf.DUMMYFUNCTION("""COMPUTED_VALUE"""),"2601D084") -> 2601D084 | C85: =IFERROR(__xludf.DUMMYFUNCTION("""COMPUTED_VALUE"""),"Wiwit supranata") -> Wiwit supranata | D85: =IFERROR(__xludf.DUMMYFUNCTION("""COMPUTED_VALUE"""),"085640533187") -> 085640533187 | E85: =IFERROR(__xludf.DUMMYFUNCTION("""COMPUTED_VALUE"""),"Lainnya") -> Lainnya | F85: =IFERROR(__xludf.DUMMYFUNCTION("""COMPUTED_VALUE"""),"Review") -> Review | G85: =IFERROR(__xludf.DUMMYFUNCTION("""COMPUTED_VALUE"""),"Tim building PT SBI") -> Tim building PT SBI | H85: =IFERROR(__xludf.DUMMYFUNCTION("""COMPUTED_VALUE"""),46066.0) -> 46066 | I85: =IFERROR(__xludf.DUMMYFUNCTION("""COMPUTED_VALUE"""),38.0) -> 38 | J85: =IFERROR(__xludf.DUMMYFUNCTION("""COMPUTED_VALUE"""),3.6753E7) -> 36753000 | K85: =IFERROR(__xludf.DUMMYFUNCTION("""COMPUTED_VALUE"""),"penawaran") -> penawaran
A86: =IFERROR(__xludf.DUMMYFUNCTION("""COMPUTED_VALUE"""),46032.0) -> 46032 | B86: =IFERROR(__xludf.DUMMYFUNCTION("""COMPUTED_VALUE"""),"2601D085") -> 2601D085 | C86: =IFERROR(__xludf.DUMMYFUNCTION("""COMPUTED_VALUE"""),"Cindy alicia ") -> Cindy alicia | D86: =IFERROR(__xludf.DUMMYFUNCTION("""COMPUTED_VALUE"""),"085782665535") -> 085782665535 | E86: =IFERROR(__xludf.DUMMYFUNCTION("""COMPUTED_VALUE"""),"Instagram") -> Instagram | F86: =IFERROR(__xludf.DUMMYFUNCTION("""COMPUTED_VALUE"""),"Closing") -> Closing | G86: =IFERROR(__xludf.DUMMYFUNCTION("""COMPUTED_VALUE"""),"OT one day D, B") -> OT one day D, B | H86: =IFERROR(__xludf.DUMMYFUNCTION("""COMPUTED_VALUE"""),46037.0) -> 46037 | I86: =IFERROR(__xludf.DUMMYFUNCTION("""COMPUTED_VALUE"""),3.0) -> 3 | J86: =IFERROR(__xludf.DUMMYFUNCTION("""COMPUTED_VALUE"""),1650000.0) -> 1650000
A87: =IFERROR(__xludf.DUMMYFUNCTION("""COMPUTED_VALUE"""),46032.0) -> 46032 | B87: =IFERROR(__xludf.DUMMYFUNCTION("""COMPUTED_VALUE"""),"2601D086") -> 2601D086 | C87: =IFERROR(__xludf.DUMMYFUNCTION("""COMPUTED_VALUE"""),"Adhiww ") -> Adhiww | D87: =IFERROR(__xludf.DUMMYFUNCTION("""COMPUTED_VALUE"""),"08921872710") -> 08921872710 | E87: =IFERROR(__xludf.DUMMYFUNCTION("""COMPUTED_VALUE"""),"Website") -> Website | F87: =IFERROR(__xludf.DUMMYFUNCTION("""COMPUTED_VALUE"""),"Gagal") -> Gagal | G87: =IFERROR(__xludf.DUMMYFUNCTION("""COMPUTED_VALUE"""),"OP kawah ijen") -> OP kawah ijen | H87: =IFERROR(__xludf.DUMMYFUNCTION("""COMPUTED_VALUE"""),46038.0) -> 46038 | I87: =IFERROR(__xludf.DUMMYFUNCTION("""COMPUTED_VALUE"""),2.0) -> 2 | K87: =IFERROR(__xludf.DUMMYFUNCTION("""COMPUTED_VALUE"""),"tanya tanya, lewat tanggal") -> tanya tanya, lewat tanggal
A88: =IFERROR(__xludf.DUMMYFUNCTION("""COMPUTED_VALUE"""),46033.0) -> 46033 | B88: =IFERROR(__xludf.DUMMYFUNCTION("""COMPUTED_VALUE"""),"2601D087") -> 2601D087 | C88: =IFERROR(__xludf.DUMMYFUNCTION("""COMPUTED_VALUE"""),"Nurhoeda") -> Nurhoeda | D88: =IFERROR(__xludf.DUMMYFUNCTION("""COMPUTED_VALUE"""),"081223809344") -> 081223809344 | E88: =IFERROR(__xludf.DUMMYFUNCTION("""COMPUTED_VALUE"""),"Lainnya") -> Lainnya | F88: =IFERROR(__xludf.DUMMYFUNCTION("""COMPUTED_VALUE"""),"Gagal") -> Gagal | G88: =IFERROR(__xludf.DUMMYFUNCTION("""COMPUTED_VALUE"""),"Trip one day") -> Trip one day | K88: =IFERROR(__xludf.DUMMYFUNCTION("""COMPUTED_VALUE"""),"tanya tanya terkait fotografer") -> tanya tanya terkait fotografer
A89: =IFERROR(__xludf.DUMMYFUNCTION("""COMPUTED_VALUE"""),46033.0) -> 46033 | B89: =IFERROR(__xludf.DUMMYFUNCTION("""COMPUTED_VALUE"""),"2601D088") -> 2601D088 | C89: =IFERROR(__xludf.DUMMYFUNCTION("""COMPUTED_VALUE"""),"Annisa ") -> Annisa | D89: =IFERROR(__xludf.DUMMYFUNCTION("""COMPUTED_VALUE"""),"089646617851") -> 089646617851 | E89: =IFERROR(__xludf.DUMMYFUNCTION("""COMPUTED_VALUE"""),"Website") -> Website | F89: =IFERROR(__xludf.DUMMYFUNCTION("""COMPUTED_VALUE"""),"Gagal") -> Gagal | G89: =IFERROR(__xludf.DUMMYFUNCTION("""COMPUTED_VALUE"""),"OP 3H2M") -> OP 3H2M | I89: =IFERROR(__xludf.DUMMYFUNCTION("""COMPUTED_VALUE"""),2.0) -> 2 | K89: =IFERROR(__xludf.DUMMYFUNCTION("""COMPUTED_VALUE"""),"tanya tanya") -> tanya tanya
A90: =IFERROR(__xludf.DUMMYFUNCTION("""COMPUTED_VALUE"""),46033.0) -> 46033 | B90: =IFERROR(__xludf.DUMMYFUNCTION("""COMPUTED_VALUE"""),"2601D089") -> 2601D089 | C90: =IFERROR(__xludf.DUMMYFUNCTION("""COMPUTED_VALUE"""),"Ny wiwin ysn") -> Ny wiwin ysn | D90: =IFERROR(__xludf.DUMMYFUNCTION("""COMPUTED_VALUE"""),"081339772111") -> 081339772111 | E90: =IFERROR(__xludf.DUMMYFUNCTION("""COMPUTED_VALUE"""),"Lainnya") -> Lainnya | F90: =IFERROR(__xludf.DUMMYFUNCTION("""COMPUTED_VALUE"""),"Gagal") -> Gagal | G90: =IFERROR(__xludf.DUMMYFUNCTION("""COMPUTED_VALUE"""),"custom 2H1M ") -> custom 2H1M | I90: =IFERROR(__xludf.DUMMYFUNCTION("""COMPUTED_VALUE"""),3.0) -> 3 | K90: =IFERROR(__xludf.DUMMYFUNCTION("""COMPUTED_VALUE"""),"ga sesuai dengan budget") -> ga sesuai dengan budget
A91: =IFERROR(__xludf.DUMMYFUNCTION("""COMPUTED_VALUE"""),46033.0) -> 46033 | B91: =IFERROR(__xludf.DUMMYFUNCTION("""COMPUTED_VALUE"""),"2601D090") -> 2601D090 | C91: =IFERROR(__xludf.DUMMYFUNCTION("""COMPUTED_VALUE"""),"Yovita") -> Yovita | D91: =IFERROR(__xludf.DUMMYFUNCTION("""COMPUTED_VALUE"""),"087811723237") -> 087811723237 | E91: =IFERROR(__xludf.DUMMYFUNCTION("""COMPUTED_VALUE"""),"Instagram") -> Instagram | F91: =IFERROR(__xludf.DUMMYFUNCTION("""COMPUTED_VALUE"""),"Gagal") -> Gagal | G91: =IFERROR(__xludf.DUMMYFUNCTION("""COMPUTED_VALUE"""),"family gathering 3H2M") -> family gathering 3H2M | I91: =IFERROR(__xludf.DUMMYFUNCTION("""COMPUTED_VALUE"""),20.0) -> 20 | K91: =IFERROR(__xludf.DUMMYFUNCTION("""COMPUTED_VALUE"""),"nunggu info selanjutnya, sudah FU tgl15") -> nunggu info selanjutnya, sudah FU tgl15
A92: =IFERROR(__xludf.DUMMYFUNCTION("""COMPUTED_VALUE"""),46033.0) -> 46033 | B92: =IFERROR(__xludf.DUMMYFUNCTION("""COMPUTED_VALUE"""),"2601D091") -> 2601D091 | C92: =IFERROR(__xludf.DUMMYFUNCTION("""COMPUTED_VALUE"""),"Herman") -> Herman | D92: =IFERROR(__xludf.DUMMYFUNCTION("""COMPUTED_VALUE"""),"082125479301") -> 082125479301 | E92: =IFERROR(__xludf.DUMMYFUNCTION("""COMPUTED_VALUE"""),"Lainnya") -> Lainnya | F92: =IFERROR(__xludf.DUMMYFUNCTION("""COMPUTED_VALUE"""),"Gagal") -> Gagal | G92: =IFERROR(__xludf.DUMMYFUNCTION("""COMPUTED_VALUE"""),"3H2M") -> 3H2M | K92: =IFERROR(__xludf.DUMMYFUNCTION("""COMPUTED_VALUE"""),"sdh FU 1") -> sdh FU 1
A93: =IFERROR(__xludf.DUMMYFUNCTION("""COMPUTED_VALUE"""),46033.0) -> 46033 | B93: =IFERROR(__xludf.DUMMYFUNCTION("""COMPUTED_VALUE"""),"2601D092") -> 2601D092 | C93: =IFERROR(__xludf.DUMMYFUNCTION("""COMPUTED_VALUE"""),"Nathaniaacr") -> Nathaniaacr | D93: =IFERROR(__xludf.DUMMYFUNCTION("""COMPUTED_VALUE"""),"085175207678") -> 085175207678 | E93: =IFERROR(__xludf.DUMMYFUNCTION("""COMPUTED_VALUE"""),"Instagram") -> Instagram | F93: =IFERROR(__xludf.DUMMYFUNCTION("""COMPUTED_VALUE"""),"Closing") -> Closing | G93: =IFERROR(__xludf.DUMMYFUNCTION("""COMPUTED_VALUE"""),"2H1M opsi B") -> 2H1M opsi B | H93: =IFERROR(__xludf.DUMMYFUNCTION("""COMPUTED_VALUE"""),46048.0) -> 46048 | I93: =IFERROR(__xludf.DUMMYFUNCTION("""COMPUTED_VALUE"""),2.0) -> 2 | J93: =IFERROR(__xludf.DUMMYFUNCTION("""COMPUTED_VALUE"""),3920000.0) -> 3920000
A94: =IFERROR(__xludf.DUMMYFUNCTION("""COMPUTED_VALUE"""),46033.0) -> 46033 | B94: =IFERROR(__xludf.DUMMYFUNCTION("""COMPUTED_VALUE"""),"2601D093") -> 2601D093 | C94: =IFERROR(__xludf.DUMMYFUNCTION("""COMPUTED_VALUE"""),"Mytha ") -> Mytha | D94: =IFERROR(__xludf.DUMMYFUNCTION("""COMPUTED_VALUE"""),"081333603433") -> 081333603433 | E94: =IFERROR(__xludf.DUMMYFUNCTION("""COMPUTED_VALUE"""),"Instagram") -> Instagram | F94: =IFERROR(__xludf.DUMMYFUNCTION("""COMPUTED_VALUE"""),"Gagal") -> Gagal | G94: =IFERROR(__xludf.DUMMYFUNCTION("""COMPUTED_VALUE"""),"Trip 1 day") -> Trip 1 day | K94: =IFERROR(__xludf.DUMMYFUNCTION("""COMPUTED_VALUE"""),"masih chek katalog ") -> masih chek katalog
A95: =IFERROR(__xludf.DUMMYFUNCTION("""COMPUTED_VALUE"""),46033.0) -> 46033 | B95: =IFERROR(__xludf.DUMMYFUNCTION("""COMPUTED_VALUE"""),"2601D094") -> 2601D094 | C95: =IFERROR(__xludf.DUMMYFUNCTION("""COMPUTED_VALUE"""),"Sylvia mariam ") -> Sylvia mariam | D95: =IFERROR(__xludf.DUMMYFUNCTION("""COMPUTED_VALUE"""),"089602611056") -> 089602611056 | E95: =IFERROR(__xludf.DUMMYFUNCTION("""COMPUTED_VALUE"""),"Instagram") -> Instagram | F95: =IFERROR(__xludf.DUMMYFUNCTION("""COMPUTED_VALUE"""),"Gagal") -> Gagal | G95: =IFERROR(__xludf.DUMMYFUNCTION("""COMPUTED_VALUE"""),"Trip menjangan ") -> Trip menjangan | I95: =IFERROR(__xludf.DUMMYFUNCTION("""COMPUTED_VALUE"""),2.0) -> 2 | K95: =IFERROR(__xludf.DUMMYFUNCTION("""COMPUTED_VALUE"""),"nunggu info, FU tgl 14 ") -> nunggu info, FU tgl 14
A96: =IFERROR(__xludf.DUMMYFUNCTION("""COMPUTED_VALUE"""),46033.0) -> 46033 | B96: =IFERROR(__xludf.DUMMYFUNCTION("""COMPUTED_VALUE"""),"2601D095") -> 2601D095 | C96: =IFERROR(__xludf.DUMMYFUNCTION("""COMPUTED_VALUE"""),"Wahid") -> Wahid | D96: =IFERROR(__xludf.DUMMYFUNCTION("""COMPUTED_VALUE"""),"081805902225") -> 081805902225 | E96: =IFERROR(__xludf.DUMMYFUNCTION("""COMPUTED_VALUE"""),"Lainnya") -> Lainnya | F96: =IFERROR(__xludf.DUMMYFUNCTION("""COMPUTED_VALUE"""),"Gagal") -> Gagal | G96: =IFERROR(__xludf.DUMMYFUNCTION("""COMPUTED_VALUE"""),"custom destinasi 2H1M") -> custom destinasi 2H1M | I96: =IFERROR(__xludf.DUMMYFUNCTION("""COMPUTED_VALUE"""),2.0) -> 2 | K96: =IFERROR(__xludf.DUMMYFUNCTION("""COMPUTED_VALUE"""),"masih dikomunikasikan, FU tgl 14") -> masih dikomunikasikan, FU tgl 14
A97: =IFERROR(__xludf.DUMMYFUNCTION("""COMPUTED_VALUE"""),46034.0) -> 46034 | B97: =IFERROR(__xludf.DUMMYFUNCTION("""COMPUTED_VALUE"""),"2601D096") -> 2601D096 | C97: =IFERROR(__xludf.DUMMYFUNCTION("""COMPUTED_VALUE"""),"Fdly") -> Fdly | D97: =IFERROR(__xludf.DUMMYFUNCTION("""COMPUTED_VALUE"""),"085781304728") -> 085781304728 | E97: =IFERROR(__xludf.DUMMYFUNCTION("""COMPUTED_VALUE"""),"Lainnya") -> Lainnya | F97: =IFERROR(__xludf.DUMMYFUNCTION("""COMPUTED_VALUE"""),"Gagal") -> Gagal
A98: =IFERROR(__xludf.DUMMYFUNCTION("""COMPUTED_VALUE"""),46034.0) -> 46034 | B98: =IFERROR(__xludf.DUMMYFUNCTION("""COMPUTED_VALUE"""),"2601D097") -> 2601D097 | C98: =IFERROR(__xludf.DUMMYFUNCTION("""COMPUTED_VALUE"""),"Epi") -> Epi | D98: =IFERROR(__xludf.DUMMYFUNCTION("""COMPUTED_VALUE"""),"081318840028") -> 081318840028 | E98: =IFERROR(__xludf.DUMMYFUNCTION("""COMPUTED_VALUE"""),"Instagram") -> Instagram | F98: =IFERROR(__xludf.DUMMYFUNCTION("""COMPUTED_VALUE"""),"Gagal") -> Gagal | G98: =IFERROR(__xludf.DUMMYFUNCTION("""COMPUTED_VALUE"""),"3H2M opsi A") -> 3H2M opsi A | I98: =IFERROR(__xludf.DUMMYFUNCTION("""COMPUTED_VALUE"""),5.0) -> 5 | K98: =IFERROR(__xludf.DUMMYFUNCTION("""COMPUTED_VALUE"""),"masih liat harga") -> masih liat harga
A99: =IFERROR(__xludf.DUMMYFUNCTION("""COMPUTED_VALUE"""),46034.0) -> 46034 | B99: =IFERROR(__xludf.DUMMYFUNCTION("""COMPUTED_VALUE"""),"2601D098") -> 2601D098 | C99: =IFERROR(__xludf.DUMMYFUNCTION("""COMPUTED_VALUE"""),"Vica") -> Vica | D99: =IFERROR(__xludf.DUMMYFUNCTION("""COMPUTED_VALUE"""),"085716117974") -> 085716117974 | E99: =IFERROR(__xludf.DUMMYFUNCTION("""COMPUTED_VALUE"""),"Instagram") -> Instagram | F99: =IFERROR(__xludf.DUMMYFUNCTION("""COMPUTED_VALUE"""),"Gagal") -> Gagal | G99: =IFERROR(__xludf.DUMMYFUNCTION("""COMPUTED_VALUE"""),"2H1M") -> 2H1M | I99: =IFERROR(__xludf.DUMMYFUNCTION("""COMPUTED_VALUE"""),4.0) -> 4 | K99: =IFERROR(__xludf.DUMMYFUNCTION("""COMPUTED_VALUE"""),"tanya titik penjemputan ") -> tanya titik penjemputan
A100: =IFERROR(__xludf.DUMMYFUNCTION("""COMPUTED_VALUE"""),46034.0) -> 46034 | B100: =IFERROR(__xludf.DUMMYFUNCTION("""COMPUTED_VALUE"""),"2601D099") -> 2601D099 | C100: =IFERROR(__xludf.DUMMYFUNCTION("""COMPUTED_VALUE"""),"N") -> N | D100: =IFERROR(__xludf.DUMMYFUNCTION("""COMPUTED_VALUE"""),"081260909299") -> 081260909299 | E100: =IFERROR(__xludf.DUMMYFUNCTION("""COMPUTED_VALUE"""),"Instagram") -> Instagram | F100: =IFERROR(__xludf.DUMMYFUNCTION("""COMPUTED_VALUE"""),"Gagal") -> Gagal | G100: =IFERROR(__xludf.DUMMYFUNCTION("""COMPUTED_VALUE"""),"OT baluran") -> OT baluran | H100: =IFERROR(__xludf.DUMMYFUNCTION("""COMPUTED_VALUE"""),46039.0) -> 46039 | K100: =IFERROR(__xludf.DUMMYFUNCTION("""COMPUTED_VALUE"""),"lewat tanggal") -> lewat tanggal
...

Sheet Leads_Alvin
A1: =IFERROR(__xludf.DUMMYFUNCTION("QUERY( 'Input Data'!A1:N5505, ""select B, A, C, D, E, G, H, I, J, K, L, N where F = 'Alvin'"", 1 ) "),"TANGGAL") -> TANGGAL | B1: =IFERROR(__xludf.DUMMYFUNCTION("""COMPUTED_VALUE"""),"KODE") -> KODE | C1: =IFERROR(__xludf.DUMMYFUNCTION("""COMPUTED_VALUE"""),"NAMA") -> NAMA | D1: =IFERROR(__xludf.DUMMYFUNCTION("""COMPUTED_VALUE"""),"WHATSAPP") -> WHATSAPP | E1: =IFERROR(__xludf.DUMMYFUNCTION("""COMPUTED_VALUE"""),"SOURCE") -> SOURCE | F1: =IFERROR(__xludf.DUMMYFUNCTION("""COMPUTED_VALUE"""),"STATUS") -> STATUS | G1: =IFERROR(__xludf.DUMMYFUNCTION("""COMPUTED_VALUE"""),"PAKET / DESTINASI") -> PAKET / DESTINASI | H1: =IFERROR(__xludf.DUMMYFUNCTION("""COMPUTED_VALUE"""),"TANGGAL TRIP") -> TANGGAL TRIP | I1: =IFERROR(__xludf.DUMMYFUNCTION("""COMPUTED_VALUE"""),"PAX") -> PAX | J1: =IFERROR(__xludf.DUMMYFUNCTION("""COMPUTED_VALUE"""),"ESTIMASI NILAI ORDER") -> ESTIMASI NILAI ORDER | K1: =IFERROR(__xludf.DUMMYFUNCTION("""COMPUTED_VALUE"""),"KETERANGAN") -> KETERANGAN | L1: =IFERROR(__xludf.DUMMYFUNCTION("""COMPUTED_VALUE"""),"ANALISA AI") -> ANALISA AI
A2: =IFERROR(__xludf.DUMMYFUNCTION("""COMPUTED_VALUE"""),46023.0) -> 46023 | B2: =IFERROR(__xludf.DUMMYFUNCTION("""COMPUTED_VALUE"""),"2601A001") -> 2601A001 | C2: =IFERROR(__xludf.DUMMYFUNCTION("""COMPUTED_VALUE"""),"Cynthia") -> Cynthia | D2: =IFERROR(__xludf.DUMMYFUNCTION("""COMPUTED_VALUE"""),"081249880600") -> 081249880600 | E2: =IFERROR(__xludf.DUMMYFUNCTION("""COMPUTED_VALUE"""),"Website") -> Website | F2: =IFERROR(__xludf.DUMMYFUNCTION("""COMPUTED_VALUE"""),"Closing") -> Closing | G2: =IFERROR(__xludf.DUMMYFUNCTION("""COMPUTED_VALUE"""),"Menjangan Tabuhan") -> Menjangan Tabuhan | H2: =IFERROR(__xludf.DUMMYFUNCTION("""COMPUTED_VALUE"""),46025.0) -> 46025 | J2: =IFERROR(__xludf.DUMMYFUNCTION("""COMPUTED_VALUE"""),7905000.0) -> 7905000 | K2: =IFERROR(__xludf.DUMMYFUNCTION("""COMPUTED_VALUE"""),"tambah foto video") -> tambah foto video
A3: =IFERROR(__xludf.DUMMYFUNCTION("""COMPUTED_VALUE"""),46023.0) -> 46023 | B3: =IFERROR(__xludf.DUMMYFUNCTION("""COMPUTED_VALUE"""),"2601A002") -> 2601A002 | C3: =IFERROR(__xludf.DUMMYFUNCTION("""COMPUTED_VALUE"""),"Dewitri") -> Dewitri | D3: =IFERROR(__xludf.DUMMYFUNCTION("""COMPUTED_VALUE"""),"085776495791") -> 085776495791 | E3: =IFERROR(__xludf.DUMMYFUNCTION("""COMPUTED_VALUE"""),"Website") -> Website | F3: =IFERROR(__xludf.DUMMYFUNCTION("""COMPUTED_VALUE"""),"Gagal") -> Gagal | G3: =IFERROR(__xludf.DUMMYFUNCTION("""COMPUTED_VALUE"""),"Kawah ijen") -> Kawah ijen | H3: =IFERROR(__xludf.DUMMYFUNCTION("""COMPUTED_VALUE"""),46023.0) -> 46023 | I3: =IFERROR(__xludf.DUMMYFUNCTION("""COMPUTED_VALUE"""),3.0) -> 3
A4: =IFERROR(__xludf.DUMMYFUNCTION("""COMPUTED_VALUE"""),46024.0) -> 46024 | B4: =IFERROR(__xludf.DUMMYFUNCTION("""COMPUTED_VALUE"""),"2601A003") -> 2601A003 | C4: =IFERROR(__xludf.DUMMYFUNCTION("""COMPUTED_VALUE"""),"Ulil albab") -> Ulil albab | D4: =IFERROR(__xludf.DUMMYFUNCTION("""COMPUTED_VALUE"""),"08561542812") -> 08561542812 | E4: =IFERROR(__xludf.DUMMYFUNCTION("""COMPUTED_VALUE"""),"Website") -> Website | F4: =IFERROR(__xludf.DUMMYFUNCTION("""COMPUTED_VALUE"""),"Gagal") -> Gagal | G4: =IFERROR(__xludf.DUMMYFUNCTION("""COMPUTED_VALUE"""),"Trip MT") -> Trip MT | H4: =IFERROR(__xludf.DUMMYFUNCTION("""COMPUTED_VALUE"""),46024.0) -> 46024 | I4: =IFERROR(__xludf.DUMMYFUNCTION("""COMPUTED_VALUE"""),4.0) -> 4 | K4: =IFERROR(__xludf.DUMMYFUNCTION("""COMPUTED_VALUE"""),"Over budget") -> Over budget
A5: =IFERROR(__xludf.DUMMYFUNCTION("""COMPUTED_VALUE"""),46024.0) -> 46024 | B5: =IFERROR(__xludf.DUMMYFUNCTION("""COMPUTED_VALUE"""),"2601A004") -> 2601A004 | C5: =IFERROR(__xludf.DUMMYFUNCTION("""COMPUTED_VALUE"""),"Anto") -> Anto | D5: =IFERROR(__xludf.DUMMYFUNCTION("""COMPUTED_VALUE"""),"0818950503") -> 0818950503 | E5: =IFERROR(__xludf.DUMMYFUNCTION("""COMPUTED_VALUE"""),"Website") -> Website | F5: =IFERROR(__xludf.DUMMYFUNCTION("""COMPUTED_VALUE"""),"Gagal") -> Gagal | K5: =IFERROR(__xludf.DUMMYFUNCTION("""COMPUTED_VALUE"""),"jadinya ke malang") -> jadinya ke malang
A6: =IFERROR(__xludf.DUMMYFUNCTION("""COMPUTED_VALUE"""),46026.0) -> 46026 | B6: =IFERROR(__xludf.DUMMYFUNCTION("""COMPUTED_VALUE"""),"2601A005") -> 2601A005 | C6: =IFERROR(__xludf.DUMMYFUNCTION("""COMPUTED_VALUE"""),"Tjen bie") -> Tjen bie | D6: =IFERROR(__xludf.DUMMYFUNCTION("""COMPUTED_VALUE"""),"081330627337") -> 081330627337 | E6: =IFERROR(__xludf.DUMMYFUNCTION("""COMPUTED_VALUE"""),"Website") -> Website | F6: =IFERROR(__xludf.DUMMYFUNCTION("""COMPUTED_VALUE"""),"Gagal") -> Gagal | G6: =IFERROR(__xludf.DUMMYFUNCTION("""COMPUTED_VALUE"""),"3H2M Z") -> 3H2M Z | H6: =IFERROR(__xludf.DUMMYFUNCTION("""COMPUTED_VALUE"""),46027.0) -> 46027 | I6: =IFERROR(__xludf.DUMMYFUNCTION("""COMPUTED_VALUE"""),2.0) -> 2 | K6: =IFERROR(__xludf.DUMMYFUNCTION("""COMPUTED_VALUE"""),"Jadi ke lovina") -> Jadi ke lovina
A7: =IFERROR(__xludf.DUMMYFUNCTION("""COMPUTED_VALUE"""),46027.0) -> 46027 | B7: =IFERROR(__xludf.DUMMYFUNCTION("""COMPUTED_VALUE"""),"2601A006") -> 2601A006 | C7: =IFERROR(__xludf.DUMMYFUNCTION("""COMPUTED_VALUE"""),"Anindita purnamasari") -> Anindita purnamasari | D7: =IFERROR(__xludf.DUMMYFUNCTION("""COMPUTED_VALUE"""),"082233330301") -> 082233330301 | E7: =IFERROR(__xludf.DUMMYFUNCTION("""COMPUTED_VALUE"""),"Website") -> Website | F7: =IFERROR(__xludf.DUMMYFUNCTION("""COMPUTED_VALUE"""),"Gagal") -> Gagal | G7: =IFERROR(__xludf.DUMMYFUNCTION("""COMPUTED_VALUE"""),"2H1M") -> 2H1M | I7: =IFERROR(__xludf.DUMMYFUNCTION("""COMPUTED_VALUE"""),2.0) -> 2 | K7: =IFERROR(__xludf.DUMMYFUNCTION("""COMPUTED_VALUE"""),"dikabari jika jadi ambil paketnya") -> dikabari jika jadi ambil paketnya
A8: =IFERROR(__xludf.DUMMYFUNCTION("""COMPUTED_VALUE"""),46027.0) -> 46027 | B8: =IFERROR(__xludf.DUMMYFUNCTION("""COMPUTED_VALUE"""),"2601A007") -> 2601A007 | C8: =IFERROR(__xludf.DUMMYFUNCTION("""COMPUTED_VALUE"""),"Riska") -> Riska | D8: =IFERROR(__xludf.DUMMYFUNCTION("""COMPUTED_VALUE"""),"08994700800") -> 08994700800 | E8: =IFERROR(__xludf.DUMMYFUNCTION("""COMPUTED_VALUE"""),"Website") -> Website | F8: =IFERROR(__xludf.DUMMYFUNCTION("""COMPUTED_VALUE"""),"Gagal") -> Gagal | G8: =IFERROR(__xludf.DUMMYFUNCTION("""COMPUTED_VALUE"""),"3H2M A") -> 3H2M A | I8: =IFERROR(__xludf.DUMMYFUNCTION("""COMPUTED_VALUE"""),10.0) -> 10 | K8: =IFERROR(__xludf.DUMMYFUNCTION("""COMPUTED_VALUE"""),"tanya tanya, masih blm jawab follow up") -> tanya tanya, masih blm jawab follow up
A9: =IFERROR(__xludf.DUMMYFUNCTION("""COMPUTED_VALUE"""),46029.0) -> 46029 | B9: =IFERROR(__xludf.DUMMYFUNCTION("""COMPUTED_VALUE"""),"2601A008") -> 2601A008 | C9: =IFERROR(__xludf.DUMMYFUNCTION("""COMPUTED_VALUE"""),"Helmi") -> Helmi | D9: =IFERROR(__xludf.DUMMYFUNCTION("""COMPUTED_VALUE"""),"083826179860‬") -> 083826179860‬ | E9: =IFERROR(__xludf.DUMMYFUNCTION("""COMPUTED_VALUE"""),"Website") -> Website | F9: =IFERROR(__xludf.DUMMYFUNCTION("""COMPUTED_VALUE"""),"Gagal") -> Gagal | G9: =IFERROR(__xludf.DUMMYFUNCTION("""COMPUTED_VALUE"""),"1D IB") -> 1D IB | H9: =IFERROR(__xludf.DUMMYFUNCTION("""COMPUTED_VALUE"""),46030.0) -> 46030 | I9: =IFERROR(__xludf.DUMMYFUNCTION("""COMPUTED_VALUE"""),3.0) -> 3 | J9: =IFERROR(__xludf.DUMMYFUNCTION("""COMPUTED_VALUE"""),2076000.0) -> 2076000 | K9: =IFERROR(__xludf.DUMMYFUNCTION("""COMPUTED_VALUE"""),"order") -> order
A10: =IFERROR(__xludf.DUMMYFUNCTION("""COMPUTED_VALUE"""),46030.0) -> 46030 | B10: =IFERROR(__xludf.DUMMYFUNCTION("""COMPUTED_VALUE"""),"2601A009") -> 2601A009 | C10: =IFERROR(__xludf.DUMMYFUNCTION("""COMPUTED_VALUE"""),"Ruly") -> Ruly | D10: =IFERROR(__xludf.DUMMYFUNCTION("""COMPUTED_VALUE"""),"08170934898") -> 08170934898 | E10: =IFERROR(__xludf.DUMMYFUNCTION("""COMPUTED_VALUE"""),"Website") -> Website | F10: =IFERROR(__xludf.DUMMYFUNCTION("""COMPUTED_VALUE"""),"Gagal") -> Gagal | G10: =IFERROR(__xludf.DUMMYFUNCTION("""COMPUTED_VALUE"""),"3H2M A") -> 3H2M A | I10: =IFERROR(__xludf.DUMMYFUNCTION("""COMPUTED_VALUE"""),2.0) -> 2 | K10: =IFERROR(__xludf.DUMMYFUNCTION("""COMPUTED_VALUE"""),"Tidak jawab") -> Tidak jawab
A11: =IFERROR(__xludf.DUMMYFUNCTION("""COMPUTED_VALUE"""),46030.0) -> 46030 | B11: =IFERROR(__xludf.DUMMYFUNCTION("""COMPUTED_VALUE"""),"2601A010") -> 2601A010 | C11: =IFERROR(__xludf.DUMMYFUNCTION("""COMPUTED_VALUE"""),"Stephan") -> Stephan | D11: =IFERROR(__xludf.DUMMYFUNCTION("""COMPUTED_VALUE"""),"085105912829") -> 085105912829 | E11: =IFERROR(__xludf.DUMMYFUNCTION("""COMPUTED_VALUE"""),"Website") -> Website | F11: =IFERROR(__xludf.DUMMYFUNCTION("""COMPUTED_VALUE"""),"Gagal") -> Gagal | G11: =IFERROR(__xludf.DUMMYFUNCTION("""COMPUTED_VALUE"""),"4H3M") -> 4H3M | I11: =IFERROR(__xludf.DUMMYFUNCTION("""COMPUTED_VALUE"""),2.0) -> 2 | K11: =IFERROR(__xludf.DUMMYFUNCTION("""COMPUTED_VALUE"""),"lagi pikir-pikir, FU pertengahan januari") -> lagi pikir-pikir, FU pertengahan januari
A12: =IFERROR(__xludf.DUMMYFUNCTION("""COMPUTED_VALUE"""),46031.0) -> 46031 | B12: =IFERROR(__xludf.DUMMYFUNCTION("""COMPUTED_VALUE"""),"2601A011") -> 2601A011 | C12: =IFERROR(__xludf.DUMMYFUNCTION("""COMPUTED_VALUE"""),"carone") -> carone | D12: =IFERROR(__xludf.DUMMYFUNCTION("""COMPUTED_VALUE"""),"0877933043674") -> 0877933043674 | E12: =IFERROR(__xludf.DUMMYFUNCTION("""COMPUTED_VALUE"""),"Lainnya") -> Lainnya | F12: =IFERROR(__xludf.DUMMYFUNCTION("""COMPUTED_VALUE"""),"Gagal") -> Gagal | G12: =IFERROR(__xludf.DUMMYFUNCTION("""COMPUTED_VALUE"""),"3H2M") -> 3H2M | K12: =IFERROR(__xludf.DUMMYFUNCTION("""COMPUTED_VALUE"""),"Masih tanya tanya") -> Masih tanya tanya
A13: =IFERROR(__xludf.DUMMYFUNCTION("""COMPUTED_VALUE"""),46031.0) -> 46031 | B13: =IFERROR(__xludf.DUMMYFUNCTION("""COMPUTED_VALUE"""),"2601A012") -> 2601A012 | C13: =IFERROR(__xludf.DUMMYFUNCTION("""COMPUTED_VALUE"""),"Giet") -> Giet | D13: =IFERROR(__xludf.DUMMYFUNCTION("""COMPUTED_VALUE"""),"085377504433") -> 085377504433 | E13: =IFERROR(__xludf.DUMMYFUNCTION("""COMPUTED_VALUE"""),"Website") -> Website | F13: =IFERROR(__xludf.DUMMYFUNCTION("""COMPUTED_VALUE"""),"Gagal") -> Gagal | G13: =IFERROR(__xludf.DUMMYFUNCTION("""COMPUTED_VALUE"""),"3H2M") -> 3H2M | K13: =IFERROR(__xludf.DUMMYFUNCTION("""COMPUTED_VALUE"""),"masih tanya tanya") -> masih tanya tanya
A14: =IFERROR(__xludf.DUMMYFUNCTION("""COMPUTED_VALUE"""),46032.0) -> 46032 | B14: =IFERROR(__xludf.DUMMYFUNCTION("""COMPUTED_VALUE"""),"2601A013") -> 2601A013 | C14: =IFERROR(__xludf.DUMMYFUNCTION("""COMPUTED_VALUE"""),"Deni Sultan") -> Deni Sultan | D14: =IFERROR(__xludf.DUMMYFUNCTION("""COMPUTED_VALUE"""),"081912435459‬") -> 081912435459‬ | E14: =IFERROR(__xludf.DUMMYFUNCTION("""COMPUTED_VALUE"""),"Website") -> Website | F14: =IFERROR(__xludf.DUMMYFUNCTION("""COMPUTED_VALUE"""),"Closing") -> Closing | G14: =IFERROR(__xludf.DUMMYFUNCTION("""COMPUTED_VALUE"""),"MT") -> MT | H14: =IFERROR(__xludf.DUMMYFUNCTION("""COMPUTED_VALUE"""),46046.0) -> 46046 | I14: =IFERROR(__xludf.DUMMYFUNCTION("""COMPUTED_VALUE"""),2.0) -> 2 | J14: =IFERROR(__xludf.DUMMYFUNCTION("""COMPUTED_VALUE"""),590000.0) -> 590000 | K14: =IFERROR(__xludf.DUMMYFUNCTION("""COMPUTED_VALUE"""),"order") -> order
A15: =IFERROR(__xludf.DUMMYFUNCTION("""COMPUTED_VALUE"""),46031.0) -> 46031 | B15: =IFERROR(__xludf.DUMMYFUNCTION("""COMPUTED_VALUE"""),"2601A014") -> 2601A014 | C15: =IFERROR(__xludf.DUMMYFUNCTION("""COMPUTED_VALUE"""),"Asep") -> Asep | D15: =IFERROR(__xludf.DUMMYFUNCTION("""COMPUTED_VALUE"""),"085524416539") -> 085524416539 | E15: =IFERROR(__xludf.DUMMYFUNCTION("""COMPUTED_VALUE"""),"Website") -> Website | F15: =IFERROR(__xludf.DUMMYFUNCTION("""COMPUTED_VALUE"""),"Gagal") -> Gagal | G15: =IFERROR(__xludf.DUMMYFUNCTION("""COMPUTED_VALUE"""),"Trip Alas Purwo") -> Trip Alas Purwo | I15: =IFERROR(__xludf.DUMMYFUNCTION("""COMPUTED_VALUE"""),10.0) -> 10 | K15: =IFERROR(__xludf.DUMMYFUNCTION("""COMPUTED_VALUE"""),"tanya tanya") -> tanya tanya
A16: =IFERROR(__xludf.DUMMYFUNCTION("""COMPUTED_VALUE"""),46033.0) -> 46033 | B16: =IFERROR(__xludf.DUMMYFUNCTION("""COMPUTED_VALUE"""),"2601A015") -> 2601A015 | C16: =IFERROR(__xludf.DUMMYFUNCTION("""COMPUTED_VALUE"""),"Istinah") -> Istinah | D16: =IFERROR(__xludf.DUMMYFUNCTION("""COMPUTED_VALUE"""),"081334625968") -> 081334625968 | E16: =IFERROR(__xludf.DUMMYFUNCTION("""COMPUTED_VALUE"""),"Website") -> Website | F16: =IFERROR(__xludf.DUMMYFUNCTION("""COMPUTED_VALUE"""),"Gagal") -> Gagal | G16: =IFERROR(__xludf.DUMMYFUNCTION("""COMPUTED_VALUE"""),"Trip Djawatan Baluran") -> Trip Djawatan Baluran | I16: =IFERROR(__xludf.DUMMYFUNCTION("""COMPUTED_VALUE"""),10.0) -> 10 | K16: =IFERROR(__xludf.DUMMYFUNCTION("""COMPUTED_VALUE"""),"masih cari informasi") -> masih cari informasi
A17: =IFERROR(__xludf.DUMMYFUNCTION("""COMPUTED_VALUE"""),46033.0) -> 46033 | B17: =IFERROR(__xludf.DUMMYFUNCTION("""COMPUTED_VALUE"""),"2601A016") -> 2601A016 | C17: =IFERROR(__xludf.DUMMYFUNCTION("""COMPUTED_VALUE"""),"Edwin") -> Edwin | D17: =IFERROR(__xludf.DUMMYFUNCTION("""COMPUTED_VALUE"""),"085659981058") -> 085659981058 | E17: =IFERROR(__xludf.DUMMYFUNCTION("""COMPUTED_VALUE"""),"Website") -> Website | F17: =IFERROR(__xludf.DUMMYFUNCTION("""COMPUTED_VALUE"""),"Closing") -> Closing | G17: =IFERROR(__xludf.DUMMYFUNCTION("""COMPUTED_VALUE"""),"Private trip 3H2M") -> Private trip 3H2M | I17: =IFERROR(__xludf.DUMMYFUNCTION("""COMPUTED_VALUE"""),2.0) -> 2 | J17: =IFERROR(__xludf.DUMMYFUNCTION("""COMPUTED_VALUE"""),6794000.0) -> 6794000 | K17: =IFERROR(__xludf.DUMMYFUNCTION("""COMPUTED_VALUE"""),"order") -> order
A18: =IFERROR(__xludf.DUMMYFUNCTION("""COMPUTED_VALUE"""),46035.0) -> 46035 | B18: =IFERROR(__xludf.DUMMYFUNCTION("""COMPUTED_VALUE"""),"2601A017") -> 2601A017 | C18: =IFERROR(__xludf.DUMMYFUNCTION("""COMPUTED_VALUE"""),"Jessica") -> Jessica | D18: =IFERROR(__xludf.DUMMYFUNCTION("""COMPUTED_VALUE"""),"08113166995") -> 08113166995 | E18: =IFERROR(__xludf.DUMMYFUNCTION("""COMPUTED_VALUE"""),"Website") -> Website | F18: =IFERROR(__xludf.DUMMYFUNCTION("""COMPUTED_VALUE"""),"Gagal") -> Gagal | G18: =IFERROR(__xludf.DUMMYFUNCTION("""COMPUTED_VALUE"""),"Trip Ijen") -> Trip Ijen | K18: =IFERROR(__xludf.DUMMYFUNCTION("""COMPUTED_VALUE"""),"tidak ada respon") -> tidak ada respon
A19: =IFERROR(__xludf.DUMMYFUNCTION("""COMPUTED_VALUE"""),46036.0) -> 46036 | B19: =IFERROR(__xludf.DUMMYFUNCTION("""COMPUTED_VALUE"""),"2601A018") -> 2601A018 | C19: =IFERROR(__xludf.DUMMYFUNCTION("""COMPUTED_VALUE"""),"Kambali khan") -> Kambali khan | D19: =IFERROR(__xludf.DUMMYFUNCTION("""COMPUTED_VALUE"""),"081133300048") -> 081133300048 | E19: =IFERROR(__xludf.DUMMYFUNCTION("""COMPUTED_VALUE"""),"Website") -> Website | F19: =IFERROR(__xludf.DUMMYFUNCTION("""COMPUTED_VALUE"""),"Gagal") -> Gagal | G19: =IFERROR(__xludf.DUMMYFUNCTION("""COMPUTED_VALUE"""),"rekom 2H1M") -> rekom 2H1M | I19: =IFERROR(__xludf.DUMMYFUNCTION("""COMPUTED_VALUE"""),7.0) -> 7 | K19: =IFERROR(__xludf.DUMMYFUNCTION("""COMPUTED_VALUE"""),"tanya paket open trip ") -> tanya paket open trip
A20: =IFERROR(__xludf.DUMMYFUNCTION("""COMPUTED_VALUE"""),46036.0) -> 46036 | B20: =IFERROR(__xludf.DUMMYFUNCTION("""COMPUTED_VALUE"""),"2601A019") -> 2601A019 | C20: =IFERROR(__xludf.DUMMYFUNCTION("""COMPUTED_VALUE"""),"Harun") -> Harun | D20: =IFERROR(__xludf.DUMMYFUNCTION("""COMPUTED_VALUE"""),"085190940022") -> 085190940022 | E20: =IFERROR(__xludf.DUMMYFUNCTION("""COMPUTED_VALUE"""),"Website") -> Website | F20: =IFERROR(__xludf.DUMMYFUNCTION("""COMPUTED_VALUE"""),"Gagal") -> Gagal | K20: =IFERROR(__xludf.DUMMYFUNCTION("""COMPUTED_VALUE"""),"tidak ada respon") -> tidak ada respon
A21: =IFERROR(__xludf.DUMMYFUNCTION("""COMPUTED_VALUE"""),46037.0) -> 46037 | B21: =IFERROR(__xludf.DUMMYFUNCTION("""COMPUTED_VALUE"""),"2601A020") -> 2601A020 | C21: =IFERROR(__xludf.DUMMYFUNCTION("""COMPUTED_VALUE"""),"Darius") -> Darius | D21: =IFERROR(__xludf.DUMMYFUNCTION("""COMPUTED_VALUE"""),"0811508236") -> 0811508236 | E21: =IFERROR(__xludf.DUMMYFUNCTION("""COMPUTED_VALUE"""),"Website") -> Website | F21: =IFERROR(__xludf.DUMMYFUNCTION("""COMPUTED_VALUE"""),"Gagal") -> Gagal | G21: =IFERROR(__xludf.DUMMYFUNCTION("""COMPUTED_VALUE"""),"4H3M") -> 4H3M | I21: =IFERROR(__xludf.DUMMYFUNCTION("""COMPUTED_VALUE"""),10.0) -> 10 | K21: =IFERROR(__xludf.DUMMYFUNCTION("""COMPUTED_VALUE"""),"jadinya ke bali, temannya Aji") -> jadinya ke bali, temannya Aji
A22: =IFERROR(__xludf.DUMMYFUNCTION("""COMPUTED_VALUE"""),46038.0) -> 46038 | B22: =IFERROR(__xludf.DUMMYFUNCTION("""COMPUTED_VALUE"""),"2601A021") -> 2601A021 | C22: =IFERROR(__xludf.DUMMYFUNCTION("""COMPUTED_VALUE"""),"Novita ") -> Novita | D22: =IFERROR(__xludf.DUMMYFUNCTION("""COMPUTED_VALUE"""),"085600920652") -> 085600920652 | E22: =IFERROR(__xludf.DUMMYFUNCTION("""COMPUTED_VALUE"""),"Website") -> Website | F22: =IFERROR(__xludf.DUMMYFUNCTION("""COMPUTED_VALUE"""),"Gagal") -> Gagal | G22: =IFERROR(__xludf.DUMMYFUNCTION("""COMPUTED_VALUE"""),"Trip D, B") -> Trip D, B | H22: =IFERROR(__xludf.DUMMYFUNCTION("""COMPUTED_VALUE"""),46046.0) -> 46046 | K22: =IFERROR(__xludf.DUMMYFUNCTION("""COMPUTED_VALUE"""),"masih belum minat") -> masih belum minat
A23: =IFERROR(__xludf.DUMMYFUNCTION("""COMPUTED_VALUE"""),46039.0) -> 46039 | B23: =IFERROR(__xludf.DUMMYFUNCTION("""COMPUTED_VALUE"""),"2601A022") -> 2601A022 | C23: =IFERROR(__xludf.DUMMYFUNCTION("""COMPUTED_VALUE"""),"Abi Yuma") -> Abi Yuma | D23: =IFERROR(__xludf.DUMMYFUNCTION("""COMPUTED_VALUE"""),"08119025858") -> 08119025858 | E23: =IFERROR(__xludf.DUMMYFUNCTION("""COMPUTED_VALUE"""),"Website") -> Website | F23: =IFERROR(__xludf.DUMMYFUNCTION("""COMPUTED_VALUE"""),"Gagal") -> Gagal | G23: =IFERROR(__xludf.DUMMYFUNCTION("""COMPUTED_VALUE"""),"2H3M") -> 2H3M | K23: =IFERROR(__xludf.DUMMYFUNCTION("""COMPUTED_VALUE"""),"tidak jawab") -> tidak jawab
A24: =IFERROR(__xludf.DUMMYFUNCTION("""COMPUTED_VALUE"""),46039.0) -> 46039 | B24: =IFERROR(__xludf.DUMMYFUNCTION("""COMPUTED_VALUE"""),"2601A023") -> 2601A023 | C24: =IFERROR(__xludf.DUMMYFUNCTION("""COMPUTED_VALUE"""),"Aji") -> Aji | D24: =IFERROR(__xludf.DUMMYFUNCTION("""COMPUTED_VALUE"""),"082211224004") -> 082211224004 | E24: =IFERROR(__xludf.DUMMYFUNCTION("""COMPUTED_VALUE"""),"Lainnya") -> Lainnya | F24: =IFERROR(__xludf.DUMMYFUNCTION("""COMPUTED_VALUE"""),"Gagal") -> Gagal | G24: =IFERROR(__xludf.DUMMYFUNCTION("""COMPUTED_VALUE"""),"3H4M") -> 3H4M | K24: =IFERROR(__xludf.DUMMYFUNCTION("""COMPUTED_VALUE"""),"jadinya ke bali") -> jadinya ke bali
A25: =IFERROR(__xludf.DUMMYFUNCTION("""COMPUTED_VALUE"""),46041.0) -> 46041 | B25: =IFERROR(__xludf.DUMMYFUNCTION("""COMPUTED_VALUE"""),"2601A024") -> 2601A024 | C25: =IFERROR(__xludf.DUMMYFUNCTION("""COMPUTED_VALUE"""),"Adi Suseno") -> Adi Suseno | D25: =IFERROR(__xludf.DUMMYFUNCTION("""COMPUTED_VALUE"""),"081293287733") -> 081293287733 | E25: =IFERROR(__xludf.DUMMYFUNCTION("""COMPUTED_VALUE"""),"Website") -> Website | F25: =IFERROR(__xludf.DUMMYFUNCTION("""COMPUTED_VALUE"""),"Closing") -> Closing | G25: =IFERROR(__xludf.DUMMYFUNCTION("""COMPUTED_VALUE"""),"Trip ijen baluran dll") -> Trip ijen baluran dll | H25: =IFERROR(__xludf.DUMMYFUNCTION("""COMPUTED_VALUE"""),46042.0) -> 46042 | J25: =IFERROR(__xludf.DUMMYFUNCTION("""COMPUTED_VALUE"""),3820000.0) -> 3820000 | K25: =IFERROR(__xludf.DUMMYFUNCTION("""COMPUTED_VALUE"""),"order") -> order
A26: =IFERROR(__xludf.DUMMYFUNCTION("""COMPUTED_VALUE"""),46041.0) -> 46041 | B26: =IFERROR(__xludf.DUMMYFUNCTION("""COMPUTED_VALUE"""),"2601A025") -> 2601A025 | C26: =IFERROR(__xludf.DUMMYFUNCTION("""COMPUTED_VALUE"""),"Fadilah") -> Fadilah | D26: =IFERROR(__xludf.DUMMYFUNCTION("""COMPUTED_VALUE"""),"087715569423") -> 087715569423 | E26: =IFERROR(__xludf.DUMMYFUNCTION("""COMPUTED_VALUE"""),"Website") -> Website | F26: =IFERROR(__xludf.DUMMYFUNCTION("""COMPUTED_VALUE"""),"Gagal") -> Gagal | G26: =IFERROR(__xludf.DUMMYFUNCTION("""COMPUTED_VALUE"""),"4H3M") -> 4H3M
A27: =IFERROR(__xludf.DUMMYFUNCTION("""COMPUTED_VALUE"""),46041.0) -> 46041 | B27: =IFERROR(__xludf.DUMMYFUNCTION("""COMPUTED_VALUE"""),"2601A026") -> 2601A026 | C27: =IFERROR(__xludf.DUMMYFUNCTION("""COMPUTED_VALUE"""),"Okky") -> Okky | D27: =IFERROR(__xludf.DUMMYFUNCTION("""COMPUTED_VALUE"""),"081319880887") -> 081319880887 | E27: =IFERROR(__xludf.DUMMYFUNCTION("""COMPUTED_VALUE"""),"Website") -> Website | F27: =IFERROR(__xludf.DUMMYFUNCTION("""COMPUTED_VALUE"""),"Gagal") -> Gagal | G27: =IFERROR(__xludf.DUMMYFUNCTION("""COMPUTED_VALUE"""),"3H2M A") -> 3H2M A | I27: =IFERROR(__xludf.DUMMYFUNCTION("""COMPUTED_VALUE"""),4.0) -> 4 | J27: =IFERROR(__xludf.DUMMYFUNCTION("""COMPUTED_VALUE"""),6808000.0) -> 6808000 | K27: =IFERROR(__xludf.DUMMYFUNCTION("""COMPUTED_VALUE"""),"gada balasan") -> gada balasan | L27: =IFERROR(__xludf.DUMMYFUNCTION("""COMPUTED_VALUE"""),"https://docs.google.com/document/d/1tO1LgOdMkFtOXA2Keh2AwL0MUaqLJDAcxzgeBUy-pmY/edit?usp=sharing") -> https://docs.google.com/document/d/1tO1LgOdMkFtOXA2Keh2AwL0MUaqLJDAcxzgeBUy-pmY/edit?usp=sharing
A28: =IFERROR(__xludf.DUMMYFUNCTION("""COMPUTED_VALUE"""),46041.0) -> 46041 | B28: =IFERROR(__xludf.DUMMYFUNCTION("""COMPUTED_VALUE"""),"2601A027") -> 2601A027 | C28: =IFERROR(__xludf.DUMMYFUNCTION("""COMPUTED_VALUE"""),"Tiyan") -> Tiyan | D28: =IFERROR(__xludf.DUMMYFUNCTION("""COMPUTED_VALUE"""),"085159766960") -> 085159766960 | E28: =IFERROR(__xludf.DUMMYFUNCTION("""COMPUTED_VALUE"""),"Website") -> Website | F28: =IFERROR(__xludf.DUMMYFUNCTION("""COMPUTED_VALUE"""),"Gagal") -> Gagal | G28: =IFERROR(__xludf.DUMMYFUNCTION("""COMPUTED_VALUE"""),"3H2M") -> 3H2M | K28: =IFERROR(__xludf.DUMMYFUNCTION("""COMPUTED_VALUE"""),"tidak ada respon") -> tidak ada respon
A29: =IFERROR(__xludf.DUMMYFUNCTION("""COMPUTED_VALUE"""),46041.0) -> 46041 | B29: =IFERROR(__xludf.DUMMYFUNCTION("""COMPUTED_VALUE"""),"2601A028") -> 2601A028 | C29: =IFERROR(__xludf.DUMMYFUNCTION("""COMPUTED_VALUE"""),"Roha") -> Roha | D29: =IFERROR(__xludf.DUMMYFUNCTION("""COMPUTED_VALUE"""),"923344633856") -> 923344633856 | E29: =IFERROR(__xludf.DUMMYFUNCTION("""COMPUTED_VALUE"""),"Website") -> Website | F29: =IFERROR(__xludf.DUMMYFUNCTION("""COMPUTED_VALUE"""),"Gagal") -> Gagal | G29: =IFERROR(__xludf.DUMMYFUNCTION("""COMPUTED_VALUE"""),"trip djawatan baluran") -> trip djawatan baluran | I29: =IFERROR(__xludf.DUMMYFUNCTION("""COMPUTED_VALUE"""),2.0) -> 2 | K29: =IFERROR(__xludf.DUMMYFUNCTION("""COMPUTED_VALUE"""),"tidak tertarik ") -> tidak tertarik
A30: =IFERROR(__xludf.DUMMYFUNCTION("""COMPUTED_VALUE"""),46041.0) -> 46041 | B30: =IFERROR(__xludf.DUMMYFUNCTION("""COMPUTED_VALUE"""),"2601A029") -> 2601A029 | C30: =IFERROR(__xludf.DUMMYFUNCTION("""COMPUTED_VALUE"""),"Tsabitah Nur") -> Tsabitah Nur | D30: =IFERROR(__xludf.DUMMYFUNCTION("""COMPUTED_VALUE"""),"085163058792") -> 085163058792 | E30: =IFERROR(__xludf.DUMMYFUNCTION("""COMPUTED_VALUE"""),"Website") -> Website | F30: =IFERROR(__xludf.DUMMYFUNCTION("""COMPUTED_VALUE"""),"Gagal") -> Gagal | K30: =IFERROR(__xludf.DUMMYFUNCTION("""COMPUTED_VALUE"""),"tidak ada respon") -> tidak ada respon
A31: =IFERROR(__xludf.DUMMYFUNCTION("""COMPUTED_VALUE"""),46042.0) -> 46042 | B31: =IFERROR(__xludf.DUMMYFUNCTION("""COMPUTED_VALUE"""),"2601A030") -> 2601A030 | C31: =IFERROR(__xludf.DUMMYFUNCTION("""COMPUTED_VALUE"""),"Dwi Isti") -> Dwi Isti | D31: =IFERROR(__xludf.DUMMYFUNCTION("""COMPUTED_VALUE"""),"089671917797") -> 089671917797 | E31: =IFERROR(__xludf.DUMMYFUNCTION("""COMPUTED_VALUE"""),"Website") -> Website | F31: =IFERROR(__xludf.DUMMYFUNCTION("""COMPUTED_VALUE"""),"Closing") -> Closing | G31: =IFERROR(__xludf.DUMMYFUNCTION("""COMPUTED_VALUE"""),"3H2M B") -> 3H2M B | J31: =IFERROR(__xludf.DUMMYFUNCTION("""COMPUTED_VALUE"""),8603000.0) -> 8603000 | K31: =IFERROR(__xludf.DUMMYFUNCTION("""COMPUTED_VALUE"""),"ALHAMDULILAH ORDER") -> ALHAMDULILAH ORDER
A32: =IFERROR(__xludf.DUMMYFUNCTION("""COMPUTED_VALUE"""),46042.0) -> 46042 | B32: =IFERROR(__xludf.DUMMYFUNCTION("""COMPUTED_VALUE"""),"2601A031") -> 2601A031 | C32: =IFERROR(__xludf.DUMMYFUNCTION("""COMPUTED_VALUE"""),"Honeymoon") -> Honeymoon | D32: =IFERROR(__xludf.DUMMYFUNCTION("""COMPUTED_VALUE"""),"087879654866") -> 087879654866 | E32: =IFERROR(__xludf.DUMMYFUNCTION("""COMPUTED_VALUE"""),"Website") -> Website | F32: =IFERROR(__xludf.DUMMYFUNCTION("""COMPUTED_VALUE"""),"Gagal") -> Gagal | G32: =IFERROR(__xludf.DUMMYFUNCTION("""COMPUTED_VALUE"""),"3H2M Opsi A") -> 3H2M Opsi A | K32: =IFERROR(__xludf.DUMMYFUNCTION("""COMPUTED_VALUE"""),"tidak ada respon") -> tidak ada respon
A33: =IFERROR(__xludf.DUMMYFUNCTION("""COMPUTED_VALUE"""),46042.0) -> 46042 | B33: =IFERROR(__xludf.DUMMYFUNCTION("""COMPUTED_VALUE"""),"2601A032") -> 2601A032 | C33: =IFERROR(__xludf.DUMMYFUNCTION("""COMPUTED_VALUE"""),"Nurandita") -> Nurandita | D33: =IFERROR(__xludf.DUMMYFUNCTION("""COMPUTED_VALUE"""),"081317308408") -> 081317308408 | E33: =IFERROR(__xludf.DUMMYFUNCTION("""COMPUTED_VALUE"""),"Website") -> Website | F33: =IFERROR(__xludf.DUMMYFUNCTION("""COMPUTED_VALUE"""),"Gagal") -> Gagal | G33: =IFERROR(__xludf.DUMMYFUNCTION("""COMPUTED_VALUE"""),"Private Trip 3H2M Custom") -> Private Trip 3H2M Custom | I33: =IFERROR(__xludf.DUMMYFUNCTION("""COMPUTED_VALUE"""),21.0) -> 21 | J33: =IFERROR(__xludf.DUMMYFUNCTION("""COMPUTED_VALUE"""),5.166E7) -> 51660000 | K33: =IFERROR(__xludf.DUMMYFUNCTION("""COMPUTED_VALUE"""),"gada bbalasan") -> gada bbalasan | L33: =IFERROR(__xludf.DUMMYFUNCTION("""COMPUTED_VALUE"""),"https://docs.google.com/document/d/1hKGuEK3I6GR0h7KG7tijUbTOER93QwazXSeUlH1209s/edit?usp=sharing") -> https://docs.google.com/document/d/1hKGuEK3I6GR0h7KG7tijUbTOER93QwazXSeUlH1209s/edit?usp=sharing
A34: =IFERROR(__xludf.DUMMYFUNCTION("""COMPUTED_VALUE"""),46042.0) -> 46042 | B34: =IFERROR(__xludf.DUMMYFUNCTION("""COMPUTED_VALUE"""),"2601A033") -> 2601A033 | C34: =IFERROR(__xludf.DUMMYFUNCTION("""COMPUTED_VALUE"""),"Thio") -> Thio | D34: =IFERROR(__xludf.DUMMYFUNCTION("""COMPUTED_VALUE"""),"081219155817") -> 081219155817 | E34: =IFERROR(__xludf.DUMMYFUNCTION("""COMPUTED_VALUE"""),"Website") -> Website | F34: =IFERROR(__xludf.DUMMYFUNCTION("""COMPUTED_VALUE"""),"Gagal") -> Gagal | G34: =IFERROR(__xludf.DUMMYFUNCTION("""COMPUTED_VALUE"""),"3H2M") -> 3H2M | I34: =IFERROR(__xludf.DUMMYFUNCTION("""COMPUTED_VALUE"""),7.0) -> 7 | K34: =IFERROR(__xludf.DUMMYFUNCTION("""COMPUTED_VALUE"""),"tanya tanya") -> tanya tanya
A35: =IFERROR(__xludf.DUMMYFUNCTION("""COMPUTED_VALUE"""),46042.0) -> 46042 | B35: =IFERROR(__xludf.DUMMYFUNCTION("""COMPUTED_VALUE"""),"2601A034") -> 2601A034 | C35: =IFERROR(__xludf.DUMMYFUNCTION("""COMPUTED_VALUE"""),"EL") -> EL | D35: =IFERROR(__xludf.DUMMYFUNCTION("""COMPUTED_VALUE"""),"085813040343") -> 085813040343 | E35: =IFERROR(__xludf.DUMMYFUNCTION("""COMPUTED_VALUE"""),"Website") -> Website | F35: =IFERROR(__xludf.DUMMYFUNCTION("""COMPUTED_VALUE"""),"Gagal") -> Gagal | G35: =IFERROR(__xludf.DUMMYFUNCTION("""COMPUTED_VALUE"""),"3H2M") -> 3H2M
A36: =IFERROR(__xludf.DUMMYFUNCTION("""COMPUTED_VALUE"""),46043.0) -> 46043 | B36: =IFERROR(__xludf.DUMMYFUNCTION("""COMPUTED_VALUE"""),"2601A035") -> 2601A035 | C36: =IFERROR(__xludf.DUMMYFUNCTION("""COMPUTED_VALUE"""),"Metryayu") -> Metryayu | D36: =IFERROR(__xludf.DUMMYFUNCTION("""COMPUTED_VALUE"""),"081388272191") -> 081388272191 | E36: =IFERROR(__xludf.DUMMYFUNCTION("""COMPUTED_VALUE"""),"Lainnya") -> Lainnya | F36: =IFERROR(__xludf.DUMMYFUNCTION("""COMPUTED_VALUE"""),"Gagal") -> Gagal | G36: =IFERROR(__xludf.DUMMYFUNCTION("""COMPUTED_VALUE"""),"Trip Djawatan Baluran") -> Trip Djawatan Baluran | I36: =IFERROR(__xludf.DUMMYFUNCTION("""COMPUTED_VALUE"""),5.0) -> 5 | K36: =IFERROR(__xludf.DUMMYFUNCTION("""COMPUTED_VALUE"""),"tidak ada respon") -> tidak ada respon
A37: =IFERROR(__xludf.DUMMYFUNCTION("""COMPUTED_VALUE"""),46043.0) -> 46043 | B37: =IFERROR(__xludf.DUMMYFUNCTION("""COMPUTED_VALUE"""),"2601A036") -> 2601A036 | C37: =IFERROR(__xludf.DUMMYFUNCTION("""COMPUTED_VALUE"""),"Hj.Wiwin") -> Hj.Wiwin | D37: =IFERROR(__xludf.DUMMYFUNCTION("""COMPUTED_VALUE"""),"085213862132") -> 085213862132 | E37: =IFERROR(__xludf.DUMMYFUNCTION("""COMPUTED_VALUE"""),"Website") -> Website | F37: =IFERROR(__xludf.DUMMYFUNCTION("""COMPUTED_VALUE"""),"Gagal") -> Gagal | G37: =IFERROR(__xludf.DUMMYFUNCTION("""COMPUTED_VALUE"""),"3H2M") -> 3H2M | I37: =IFERROR(__xludf.DUMMYFUNCTION("""COMPUTED_VALUE"""),10.0) -> 10 | J37: =IFERROR(__xludf.DUMMYFUNCTION("""COMPUTED_VALUE"""),2.865E7) -> 28650000 | K37: =IFERROR(__xludf.DUMMYFUNCTION("""COMPUTED_VALUE"""),"tidak ada respon") -> tidak ada respon | L37: =IFERROR(__xludf.DUMMYFUNCTION("""COMPUTED_VALUE"""),"https://docs.google.com/document/d/1dIRrs3AubGSROJCp1oEJBYXBkQBoa1UGWgOsiAXf6oo/edit?usp=sharing") -> https://docs.google.com/document/d/1dIRrs3AubGSROJCp1oEJBYXBkQBoa1UGWgOsiAXf6oo/edit?usp=sharing
A38: =IFERROR(__xludf.DUMMYFUNCTION("""COMPUTED_VALUE"""),46043.0) -> 46043 | B38: =IFERROR(__xludf.DUMMYFUNCTION("""COMPUTED_VALUE"""),"2601A037") -> 2601A037 | C38: =IFERROR(__xludf.DUMMYFUNCTION("""COMPUTED_VALUE"""),"82118155984") -> 82118155984 | D38: =IFERROR(__xludf.DUMMYFUNCTION("""COMPUTED_VALUE"""),"082118155984") -> 082118155984 | E38: =IFERROR(__xludf.DUMMYFUNCTION("""COMPUTED_VALUE"""),"Website") -> Website | F38: =IFERROR(__xludf.DUMMYFUNCTION("""COMPUTED_VALUE"""),"Gagal") -> Gagal | G38: =IFERROR(__xludf.DUMMYFUNCTION("""COMPUTED_VALUE"""),"3H2M") -> 3H2M | I38: =IFERROR(__xludf.DUMMYFUNCTION("""COMPUTED_VALUE"""),3.0) -> 3 | J38: =IFERROR(__xludf.DUMMYFUNCTION("""COMPUTED_VALUE"""),9192000.0) -> 9192000 | K38: =IFERROR(__xludf.DUMMYFUNCTION("""COMPUTED_VALUE"""),"belum dapat cuti") -> belum dapat cuti
A39: =IFERROR(__xludf.DUMMYFUNCTION("""COMPUTED_VALUE"""),45996.0) -> 45996 | B39: =IFERROR(__xludf.DUMMYFUNCTION("""COMPUTED_VALUE"""),"2512A001") -> 2512A001 | C39: =IFERROR(__xludf.DUMMYFUNCTION("""COMPUTED_VALUE"""),"Kian Djiang(Agus setia budi)") -> Kian Djiang(Agus setia budi) | D39: =IFERROR(__xludf.DUMMYFUNCTION("""COMPUTED_VALUE"""),"0895603297486") -> 0895603297486 | E39: =IFERROR(__xludf.DUMMYFUNCTION("""COMPUTED_VALUE"""),"Website") -> Website | F39: =IFERROR(__xludf.DUMMYFUNCTION("""COMPUTED_VALUE"""),"Warm Leads") -> Warm Leads | G39: =IFERROR(__xludf.DUMMYFUNCTION("""COMPUTED_VALUE"""),"4H3M") -> 4H3M | I39: =IFERROR(__xludf.DUMMYFUNCTION("""COMPUTED_VALUE"""),50.0) -> 50 | J39: =IFERROR(__xludf.DUMMYFUNCTION("""COMPUTED_VALUE"""),1.257E8) -> 125700000 | K39: =IFERROR(__xludf.DUMMYFUNCTION("""COMPUTED_VALUE"""),"DP bulan Juli (Trip bulan Agustus)") -> DP bulan Juli (Trip bulan Agustus)
A40: =IFERROR(__xludf.DUMMYFUNCTION("""COMPUTED_VALUE"""),46044.0) -> 46044 | B40: =IFERROR(__xludf.DUMMYFUNCTION("""COMPUTED_VALUE"""),"2601A038") -> 2601A038 | C40: =IFERROR(__xludf.DUMMYFUNCTION("""COMPUTED_VALUE"""),"81234323491") -> 81234323491 | D40: =IFERROR(__xludf.DUMMYFUNCTION("""COMPUTED_VALUE"""),"081234323491") -> 081234323491 | E40: =IFERROR(__xludf.DUMMYFUNCTION("""COMPUTED_VALUE"""),"Website") -> Website | F40: =IFERROR(__xludf.DUMMYFUNCTION("""COMPUTED_VALUE"""),"Gagal") -> Gagal | G40: =IFERROR(__xludf.DUMMYFUNCTION("""COMPUTED_VALUE"""),"OT One day Ijen Baluran") -> OT One day Ijen Baluran
A41: =IFERROR(__xludf.DUMMYFUNCTION("""COMPUTED_VALUE"""),46044.0) -> 46044 | B41: =IFERROR(__xludf.DUMMYFUNCTION("""COMPUTED_VALUE"""),"2601A039") -> 2601A039 | C41: =IFERROR(__xludf.DUMMYFUNCTION("""COMPUTED_VALUE"""),"Ikna") -> Ikna | D41: =IFERROR(__xludf.DUMMYFUNCTION("""COMPUTED_VALUE"""),"085780090877") -> 085780090877 | E41: =IFERROR(__xludf.DUMMYFUNCTION("""COMPUTED_VALUE"""),"Website") -> Website | F41: =IFERROR(__xludf.DUMMYFUNCTION("""COMPUTED_VALUE"""),"Gagal") -> Gagal | G41: =IFERROR(__xludf.DUMMYFUNCTION("""COMPUTED_VALUE"""),"2H1M") -> 2H1M
A42: =IFERROR(__xludf.DUMMYFUNCTION("""COMPUTED_VALUE"""),46044.0) -> 46044 | B42: =IFERROR(__xludf.DUMMYFUNCTION("""COMPUTED_VALUE"""),"2601A040") -> 2601A040 | C42: =IFERROR(__xludf.DUMMYFUNCTION("""COMPUTED_VALUE"""),"Fida") -> Fida | D42: =IFERROR(__xludf.DUMMYFUNCTION("""COMPUTED_VALUE"""),"085869776991") -> 085869776991 | E42: =IFERROR(__xludf.DUMMYFUNCTION("""COMPUTED_VALUE"""),"Website") -> Website | F42: =IFERROR(__xludf.DUMMYFUNCTION("""COMPUTED_VALUE"""),"Gagal") -> Gagal | G42: =IFERROR(__xludf.DUMMYFUNCTION("""COMPUTED_VALUE"""),"3H2M") -> 3H2M | K42: =IFERROR(__xludf.DUMMYFUNCTION("""COMPUTED_VALUE"""),"tanya tanya") -> tanya tanya
A43: =IFERROR(__xludf.DUMMYFUNCTION("""COMPUTED_VALUE"""),45969.0) -> 45969 | B43: =IFERROR(__xludf.DUMMYFUNCTION("""COMPUTED_VALUE"""),"2511A001") -> 2511A001 | C43: =IFERROR(__xludf.DUMMYFUNCTION("""COMPUTED_VALUE"""),"Andika") -> Andika | D43: =IFERROR(__xludf.DUMMYFUNCTION("""COMPUTED_VALUE"""),"082226664141") -> 082226664141 | E43: =IFERROR(__xludf.DUMMYFUNCTION("""COMPUTED_VALUE"""),"Website") -> Website | F43: =IFERROR(__xludf.DUMMYFUNCTION("""COMPUTED_VALUE"""),"Closing") -> Closing | G43: =IFERROR(__xludf.DUMMYFUNCTION("""COMPUTED_VALUE"""),"Private Trip 3H2M Opsi A") -> Private Trip 3H2M Opsi A | I43: =IFERROR(__xludf.DUMMYFUNCTION("""COMPUTED_VALUE"""),6.0) -> 6 | J43: =IFERROR(__xludf.DUMMYFUNCTION("""COMPUTED_VALUE"""),1.3638E7) -> 13638000 | K43: =IFERROR(__xludf.DUMMYFUNCTION("""COMPUTED_VALUE"""),"order") -> order
A44: =IFERROR(__xludf.DUMMYFUNCTION("""COMPUTED_VALUE"""),46021.0) -> 46021 | B44: =IFERROR(__xludf.DUMMYFUNCTION("""COMPUTED_VALUE"""),"2512A002") -> 2512A002 | C44: =IFERROR(__xludf.DUMMYFUNCTION("""COMPUTED_VALUE"""),"Kiky Rizkiyah") -> Kiky Rizkiyah | D44: =IFERROR(__xludf.DUMMYFUNCTION("""COMPUTED_VALUE"""),"08123045710") -> 08123045710 | E44: =IFERROR(__xludf.DUMMYFUNCTION("""COMPUTED_VALUE"""),"Website") -> Website | F44: =IFERROR(__xludf.DUMMYFUNCTION("""COMPUTED_VALUE"""),"Closing") -> Closing | G44: =IFERROR(__xludf.DUMMYFUNCTION("""COMPUTED_VALUE"""),"Private Trip 2H1M Custom") -> Private Trip 2H1M Custom | J44: =IFERROR(__xludf.DUMMYFUNCTION("""COMPUTED_VALUE"""),7000000.0) -> 7000000 | K44: =IFERROR(__xludf.DUMMYFUNCTION("""COMPUTED_VALUE"""),"order") -> order
A45: =IFERROR(__xludf.DUMMYFUNCTION("""COMPUTED_VALUE"""),46044.0) -> 46044 | B45: =IFERROR(__xludf.DUMMYFUNCTION("""COMPUTED_VALUE"""),"2601A041") -> 2601A041 | C45: =IFERROR(__xludf.DUMMYFUNCTION("""COMPUTED_VALUE"""),"Pras bayu") -> Pras bayu | D45: =IFERROR(__xludf.DUMMYFUNCTION("""COMPUTED_VALUE"""),"08976412063") -> 08976412063 | E45: =IFERROR(__xludf.DUMMYFUNCTION("""COMPUTED_VALUE"""),"Website") -> Website | F45: =IFERROR(__xludf.DUMMYFUNCTION("""COMPUTED_VALUE"""),"Gagal") -> Gagal | G45: =IFERROR(__xludf.DUMMYFUNCTION("""COMPUTED_VALUE"""),"Tanya tanya") -> Tanya tanya | K45: =IFERROR(__xludf.DUMMYFUNCTION("""COMPUTED_VALUE"""),"mencari driver") -> mencari driver
A46: =IFERROR(__xludf.DUMMYFUNCTION("""COMPUTED_VALUE"""),46044.0) -> 46044 | B46: =IFERROR(__xludf.DUMMYFUNCTION("""COMPUTED_VALUE"""),"2601A042") -> 2601A042 | C46: =IFERROR(__xludf.DUMMYFUNCTION("""COMPUTED_VALUE"""),"85664690787") -> 85664690787 | D46: =IFERROR(__xludf.DUMMYFUNCTION("""COMPUTED_VALUE"""),"085664690787") -> 085664690787 | E46: =IFERROR(__xludf.DUMMYFUNCTION("""COMPUTED_VALUE"""),"Website") -> Website | F46: =IFERROR(__xludf.DUMMYFUNCTION("""COMPUTED_VALUE"""),"Gagal") -> Gagal | K46: =IFERROR(__xludf.DUMMYFUNCTION("""COMPUTED_VALUE"""),"idak ada respon") -> idak ada respon
A47: =IFERROR(__xludf.DUMMYFUNCTION("""COMPUTED_VALUE"""),46045.0) -> 46045 | B47: =IFERROR(__xludf.DUMMYFUNCTION("""COMPUTED_VALUE"""),"2601A043") -> 2601A043 | C47: =IFERROR(__xludf.DUMMYFUNCTION("""COMPUTED_VALUE"""),"Farras") -> Farras | D47: =IFERROR(__xludf.DUMMYFUNCTION("""COMPUTED_VALUE"""),"082326313343") -> 082326313343 | E47: =IFERROR(__xludf.DUMMYFUNCTION("""COMPUTED_VALUE"""),"Website") -> Website | F47: =IFERROR(__xludf.DUMMYFUNCTION("""COMPUTED_VALUE"""),"Gagal") -> Gagal | G47: =IFERROR(__xludf.DUMMYFUNCTION("""COMPUTED_VALUE"""),"4H3M") -> 4H3M | H47: =IFERROR(__xludf.DUMMYFUNCTION("""COMPUTED_VALUE"""),46048.0) -> 46048 | I47: =IFERROR(__xludf.DUMMYFUNCTION("""COMPUTED_VALUE"""),2.0) -> 2 | K47: =IFERROR(__xludf.DUMMYFUNCTION("""COMPUTED_VALUE"""),"belum cocok waktu") -> belum cocok waktu
A48: =IFERROR(__xludf.DUMMYFUNCTION("""COMPUTED_VALUE"""),46045.0) -> 46045 | B48: =IFERROR(__xludf.DUMMYFUNCTION("""COMPUTED_VALUE"""),"2601A044") -> 2601A044 | C48: =IFERROR(__xludf.DUMMYFUNCTION("""COMPUTED_VALUE"""),"Rosta") -> Rosta | D48: =IFERROR(__xludf.DUMMYFUNCTION("""COMPUTED_VALUE"""),"081382731664") -> 081382731664 | E48: =IFERROR(__xludf.DUMMYFUNCTION("""COMPUTED_VALUE"""),"Website") -> Website | F48: =IFERROR(__xludf.DUMMYFUNCTION("""COMPUTED_VALUE"""),"Gagal") -> Gagal | G48: =IFERROR(__xludf.DUMMYFUNCTION("""COMPUTED_VALUE"""),"3H2M Custom") -> 3H2M Custom | I48: =IFERROR(__xludf.DUMMYFUNCTION("""COMPUTED_VALUE"""),60.0) -> 60 | J48: =IFERROR(__xludf.DUMMYFUNCTION("""COMPUTED_VALUE"""),1.5E8) -> 150000000 | K48: =IFERROR(__xludf.DUMMYFUNCTION("""COMPUTED_VALUE"""),"gaada balasan lagi") -> gaada balasan lagi
A49: =IFERROR(__xludf.DUMMYFUNCTION("""COMPUTED_VALUE"""),46045.0) -> 46045 | B49: =IFERROR(__xludf.DUMMYFUNCTION("""COMPUTED_VALUE"""),"2601A045") -> 2601A045 | C49: =IFERROR(__xludf.DUMMYFUNCTION("""COMPUTED_VALUE"""),"Yetty") -> Yetty | D49: =IFERROR(__xludf.DUMMYFUNCTION("""COMPUTED_VALUE"""),"081910011543") -> 081910011543 | E49: =IFERROR(__xludf.DUMMYFUNCTION("""COMPUTED_VALUE"""),"Website") -> Website | F49: =IFERROR(__xludf.DUMMYFUNCTION("""COMPUTED_VALUE"""),"Gagal") -> Gagal | G49: =IFERROR(__xludf.DUMMYFUNCTION("""COMPUTED_VALUE"""),"Trip Ijen") -> Trip Ijen | I49: =IFERROR(__xludf.DUMMYFUNCTION("""COMPUTED_VALUE"""),6.0) -> 6 | K49: =IFERROR(__xludf.DUMMYFUNCTION("""COMPUTED_VALUE"""),"mau di rundingkan dulu") -> mau di rundingkan dulu
A50: =IFERROR(__xludf.DUMMYFUNCTION("""COMPUTED_VALUE"""),46046.0) -> 46046 | B50: =IFERROR(__xludf.DUMMYFUNCTION("""COMPUTED_VALUE"""),"2601A046") -> 2601A046 | C50: =IFERROR(__xludf.DUMMYFUNCTION("""COMPUTED_VALUE"""),"A Sudibyo") -> A Sudibyo | D50: =IFERROR(__xludf.DUMMYFUNCTION("""COMPUTED_VALUE"""),"085102704611") -> 085102704611 | E50: =IFERROR(__xludf.DUMMYFUNCTION("""COMPUTED_VALUE"""),"Website") -> Website | F50: =IFERROR(__xludf.DUMMYFUNCTION("""COMPUTED_VALUE"""),"Gagal") -> Gagal | G50: =IFERROR(__xludf.DUMMYFUNCTION("""COMPUTED_VALUE"""),"OT Djawatan") -> OT Djawatan | I50: =IFERROR(__xludf.DUMMYFUNCTION("""COMPUTED_VALUE"""),2.0) -> 2 | J50: =IFERROR(__xludf.DUMMYFUNCTION("""COMPUTED_VALUE"""),1100000.0) -> 1100000 | K50: =IFERROR(__xludf.DUMMYFUNCTION("""COMPUTED_VALUE"""),"masih ditunda") -> masih ditunda
A51: =IFERROR(__xludf.DUMMYFUNCTION("""COMPUTED_VALUE"""),46046.0) -> 46046 | B51: =IFERROR(__xludf.DUMMYFUNCTION("""COMPUTED_VALUE"""),"2601A047") -> 2601A047 | C51: =IFERROR(__xludf.DUMMYFUNCTION("""COMPUTED_VALUE"""),"Selvy") -> Selvy | D51: =IFERROR(__xludf.DUMMYFUNCTION("""COMPUTED_VALUE"""),"0811595446") -> 0811595446 | E51: =IFERROR(__xludf.DUMMYFUNCTION("""COMPUTED_VALUE"""),"Website") -> Website | F51: =IFERROR(__xludf.DUMMYFUNCTION("""COMPUTED_VALUE"""),"Gagal") -> Gagal | K51: =IFERROR(__xludf.DUMMYFUNCTION("""COMPUTED_VALUE"""),"tidak ada respon") -> tidak ada respon
A52: =IFERROR(__xludf.DUMMYFUNCTION("""COMPUTED_VALUE"""),46046.0) -> 46046 | B52: =IFERROR(__xludf.DUMMYFUNCTION("""COMPUTED_VALUE"""),"2601A048") -> 2601A048 | C52: =IFERROR(__xludf.DUMMYFUNCTION("""COMPUTED_VALUE"""),"Des") -> Des | D52: =IFERROR(__xludf.DUMMYFUNCTION("""COMPUTED_VALUE"""),"085314764695") -> 085314764695 | E52: =IFERROR(__xludf.DUMMYFUNCTION("""COMPUTED_VALUE"""),"Website") -> Website | F52: =IFERROR(__xludf.DUMMYFUNCTION("""COMPUTED_VALUE"""),"Gagal") -> Gagal | G52: =IFERROR(__xludf.DUMMYFUNCTION("""COMPUTED_VALUE"""),"3H2M") -> 3H2M | I52: =IFERROR(__xludf.DUMMYFUNCTION("""COMPUTED_VALUE"""),1.0) -> 1 | K52: =IFERROR(__xludf.DUMMYFUNCTION("""COMPUTED_VALUE"""),"tidak ada respon") -> tidak ada respon
A53: =IFERROR(__xludf.DUMMYFUNCTION("""COMPUTED_VALUE"""),46046.0) -> 46046 | B53: =IFERROR(__xludf.DUMMYFUNCTION("""COMPUTED_VALUE"""),"2601A049") -> 2601A049 | C53: =IFERROR(__xludf.DUMMYFUNCTION("""COMPUTED_VALUE"""),"Debyo") -> Debyo | D53: =IFERROR(__xludf.DUMMYFUNCTION("""COMPUTED_VALUE"""),"085643660340") -> 085643660340 | E53: =IFERROR(__xludf.DUMMYFUNCTION("""COMPUTED_VALUE"""),"Website") -> Website | F53: =IFERROR(__xludf.DUMMYFUNCTION("""COMPUTED_VALUE"""),"Gagal") -> Gagal | G53: =IFERROR(__xludf.DUMMYFUNCTION("""COMPUTED_VALUE"""),"4H3M") -> 4H3M | I53: =IFERROR(__xludf.DUMMYFUNCTION("""COMPUTED_VALUE"""),80.0) -> 80 | J53: =IFERROR(__xludf.DUMMYFUNCTION("""COMPUTED_VALUE"""),2.12E8) -> 212000000 | K53: =IFERROR(__xludf.DUMMYFUNCTION("""COMPUTED_VALUE"""),"tidak balas lagi") -> tidak balas lagi
A54: =IFERROR(__xludf.DUMMYFUNCTION("""COMPUTED_VALUE"""),46047.0) -> 46047 | B54: =IFERROR(__xludf.DUMMYFUNCTION("""COMPUTED_VALUE"""),"2601A050") -> 2601A050 | C54: =IFERROR(__xludf.DUMMYFUNCTION("""COMPUTED_VALUE"""),"Eka") -> Eka | D54: =IFERROR(__xludf.DUMMYFUNCTION("""COMPUTED_VALUE"""),"08112913613") -> 08112913613 | E54: =IFERROR(__xludf.DUMMYFUNCTION("""COMPUTED_VALUE"""),"Website") -> Website | F54: =IFERROR(__xludf.DUMMYFUNCTION("""COMPUTED_VALUE"""),"Gagal") -> Gagal | G54: =IFERROR(__xludf.DUMMYFUNCTION("""COMPUTED_VALUE""")," 3H2M Opsi A") -> 3H2M Opsi A | I54: =IFERROR(__xludf.DUMMYFUNCTION("""COMPUTED_VALUE"""),9.0) -> 9 | J54: =IFERROR(__xludf.DUMMYFUNCTION("""COMPUTED_VALUE"""),1.1043E7) -> 11043000 | K54: =IFERROR(__xludf.DUMMYFUNCTION("""COMPUTED_VALUE"""),"gada balasan") -> gada balasan
A55: =IFERROR(__xludf.DUMMYFUNCTION("""COMPUTED_VALUE"""),46047.0) -> 46047 | B55: =IFERROR(__xludf.DUMMYFUNCTION("""COMPUTED_VALUE"""),"2601A051") -> 2601A051 | C55: =IFERROR(__xludf.DUMMYFUNCTION("""COMPUTED_VALUE"""),"Cynn") -> Cynn | D55: =IFERROR(__xludf.DUMMYFUNCTION("""COMPUTED_VALUE"""),"081227870375") -> 081227870375 | E55: =IFERROR(__xludf.DUMMYFUNCTION("""COMPUTED_VALUE"""),"Website") -> Website | F55: =IFERROR(__xludf.DUMMYFUNCTION("""COMPUTED_VALUE"""),"Gagal") -> Gagal | G55: =IFERROR(__xludf.DUMMYFUNCTION("""COMPUTED_VALUE"""),"OT I, B") -> OT I, B | I55: =IFERROR(__xludf.DUMMYFUNCTION("""COMPUTED_VALUE"""),2.0) -> 2 | K55: =IFERROR(__xludf.DUMMYFUNCTION("""COMPUTED_VALUE"""),"tanya tanya") -> tanya tanya
A56: =IFERROR(__xludf.DUMMYFUNCTION("""COMPUTED_VALUE"""),46048.0) -> 46048 | B56: =IFERROR(__xludf.DUMMYFUNCTION("""COMPUTED_VALUE"""),"2601A052") -> 2601A052 | C56: =IFERROR(__xludf.DUMMYFUNCTION("""COMPUTED_VALUE"""),"Syahnindita") -> Syahnindita | D56: =IFERROR(__xludf.DUMMYFUNCTION("""COMPUTED_VALUE"""),"081938890390") -> 081938890390 | E56: =IFERROR(__xludf.DUMMYFUNCTION("""COMPUTED_VALUE"""),"Website") -> Website | F56: =IFERROR(__xludf.DUMMYFUNCTION("""COMPUTED_VALUE"""),"Gagal") -> Gagal | G56: =IFERROR(__xludf.DUMMYFUNCTION("""COMPUTED_VALUE"""),"3H2M Custom") -> 3H2M Custom | I56: =IFERROR(__xludf.DUMMYFUNCTION("""COMPUTED_VALUE"""),7.0) -> 7 | J56: =IFERROR(__xludf.DUMMYFUNCTION("""COMPUTED_VALUE"""),2.4661E7) -> 24661000 | K56: =IFERROR(__xludf.DUMMYFUNCTION("""COMPUTED_VALUE"""),"gadapat cuti, next mungkin dihubungi lagi") -> gadapat cuti, next mungkin dihubungi lagi
A57: =IFERROR(__xludf.DUMMYFUNCTION("""COMPUTED_VALUE"""),46048.0) -> 46048 | B57: =IFERROR(__xludf.DUMMYFUNCTION("""COMPUTED_VALUE"""),"2601A053") -> 2601A053 | C57: =IFERROR(__xludf.DUMMYFUNCTION("""COMPUTED_VALUE"""),"Rasti") -> Rasti | D57: =IFERROR(__xludf.DUMMYFUNCTION("""COMPUTED_VALUE"""),"085333556995") -> 085333556995 | E57: =IFERROR(__xludf.DUMMYFUNCTION("""COMPUTED_VALUE"""),"Website") -> Website | F57: =IFERROR(__xludf.DUMMYFUNCTION("""COMPUTED_VALUE"""),"Gagal") -> Gagal | K57: =IFERROR(__xludf.DUMMYFUNCTION("""COMPUTED_VALUE"""),"tidak ada respon") -> tidak ada respon
A58: =IFERROR(__xludf.DUMMYFUNCTION("""COMPUTED_VALUE"""),46048.0) -> 46048 | B58: =IFERROR(__xludf.DUMMYFUNCTION("""COMPUTED_VALUE"""),"2601A054") -> 2601A054 | C58: =IFERROR(__xludf.DUMMYFUNCTION("""COMPUTED_VALUE"""),"Sendi") -> Sendi | D58: =IFERROR(__xludf.DUMMYFUNCTION("""COMPUTED_VALUE"""),"082244942939") -> 082244942939 | E58: =IFERROR(__xludf.DUMMYFUNCTION("""COMPUTED_VALUE"""),"Website") -> Website | F58: =IFERROR(__xludf.DUMMYFUNCTION("""COMPUTED_VALUE"""),"Gagal") -> Gagal | G58: =IFERROR(__xludf.DUMMYFUNCTION("""COMPUTED_VALUE"""),"Trip Djawatan Baluran") -> Trip Djawatan Baluran | I58: =IFERROR(__xludf.DUMMYFUNCTION("""COMPUTED_VALUE"""),4.0) -> 4 | K58: =IFERROR(__xludf.DUMMYFUNCTION("""COMPUTED_VALUE"""),"belum tertarik") -> belum tertarik
A59: =IFERROR(__xludf.DUMMYFUNCTION("""COMPUTED_VALUE"""),46048.0) -> 46048 | B59: =IFERROR(__xludf.DUMMYFUNCTION("""COMPUTED_VALUE"""),"2601A055") -> 2601A055 | C59: =IFERROR(__xludf.DUMMYFUNCTION("""COMPUTED_VALUE"""),"Hendro") -> Hendro | D59: =IFERROR(__xludf.DUMMYFUNCTION("""COMPUTED_VALUE"""),"081918004080") -> 081918004080 | E59: =IFERROR(__xludf.DUMMYFUNCTION("""COMPUTED_VALUE"""),"Website") -> Website | F59: =IFERROR(__xludf.DUMMYFUNCTION("""COMPUTED_VALUE"""),"Gagal") -> Gagal | G59: =IFERROR(__xludf.DUMMYFUNCTION("""COMPUTED_VALUE"""),"Trip Djawatan Baluran") -> Trip Djawatan Baluran | I59: =IFERROR(__xludf.DUMMYFUNCTION("""COMPUTED_VALUE"""),2.0) -> 2 | K59: =IFERROR(__xludf.DUMMYFUNCTION("""COMPUTED_VALUE"""),"tidak ada respon") -> tidak ada respon
A60: =IFERROR(__xludf.DUMMYFUNCTION("""COMPUTED_VALUE"""),46049.0) -> 46049 | B60: =IFERROR(__xludf.DUMMYFUNCTION("""COMPUTED_VALUE"""),"2601A056") -> 2601A056 | C60: =IFERROR(__xludf.DUMMYFUNCTION("""COMPUTED_VALUE"""),"Aulia Rizky Amalia") -> Aulia Rizky Amalia | D60: =IFERROR(__xludf.DUMMYFUNCTION("""COMPUTED_VALUE"""),"083189971273") -> 083189971273 | E60: =IFERROR(__xludf.DUMMYFUNCTION("""COMPUTED_VALUE"""),"Website") -> Website | F60: =IFERROR(__xludf.DUMMYFUNCTION("""COMPUTED_VALUE"""),"Gagal") -> Gagal | G60: =IFERROR(__xludf.DUMMYFUNCTION("""COMPUTED_VALUE"""),"custom 2H1M") -> custom 2H1M | I60: =IFERROR(__xludf.DUMMYFUNCTION("""COMPUTED_VALUE"""),5.0) -> 5 | K60: =IFERROR(__xludf.DUMMYFUNCTION("""COMPUTED_VALUE"""),"sudah kirim penawaran, masih diinfokan ke temannya") -> sudah kirim penawaran, masih diinfokan ke temannya
A61: =IFERROR(__xludf.DUMMYFUNCTION("""COMPUTED_VALUE"""),46049.0) -> 46049 | B61: =IFERROR(__xludf.DUMMYFUNCTION("""COMPUTED_VALUE"""),"2601A057") -> 2601A057 | C61: =IFERROR(__xludf.DUMMYFUNCTION("""COMPUTED_VALUE"""),"Ari budiman") -> Ari budiman | D61: =IFERROR(__xludf.DUMMYFUNCTION("""COMPUTED_VALUE"""),"081365613727") -> 081365613727 | E61: =IFERROR(__xludf.DUMMYFUNCTION("""COMPUTED_VALUE"""),"Website") -> Website | F61: =IFERROR(__xludf.DUMMYFUNCTION("""COMPUTED_VALUE"""),"Closing") -> Closing | G61: =IFERROR(__xludf.DUMMYFUNCTION("""COMPUTED_VALUE"""),"Trip Teluk Hijau") -> Trip Teluk Hijau | I61: =IFERROR(__xludf.DUMMYFUNCTION("""COMPUTED_VALUE"""),5.0) -> 5 | J61: =IFERROR(__xludf.DUMMYFUNCTION("""COMPUTED_VALUE"""),2250000.0) -> 2250000 | K61: =IFERROR(__xludf.DUMMYFUNCTION("""COMPUTED_VALUE"""),"order") -> order
A62: =IFERROR(__xludf.DUMMYFUNCTION("""COMPUTED_VALUE"""),46049.0) -> 46049 | B62: =IFERROR(__xludf.DUMMYFUNCTION("""COMPUTED_VALUE"""),"2601A058") -> 2601A058 | C62: =IFERROR(__xludf.DUMMYFUNCTION("""COMPUTED_VALUE"""),"Caca") -> Caca | D62: =IFERROR(__xludf.DUMMYFUNCTION("""COMPUTED_VALUE"""),"081573666815") -> 081573666815 | E62: =IFERROR(__xludf.DUMMYFUNCTION("""COMPUTED_VALUE"""),"Website") -> Website | F62: =IFERROR(__xludf.DUMMYFUNCTION("""COMPUTED_VALUE"""),"Gagal") -> Gagal | G62: =IFERROR(__xludf.DUMMYFUNCTION("""COMPUTED_VALUE"""),"Trip baluran") -> Trip baluran | I62: =IFERROR(__xludf.DUMMYFUNCTION("""COMPUTED_VALUE"""),15.0) -> 15 | J62: =IFERROR(__xludf.DUMMYFUNCTION("""COMPUTED_VALUE"""),3900000.0) -> 3900000 | K62: =IFERROR(__xludf.DUMMYFUNCTION("""COMPUTED_VALUE"""),"tidak ada jawaban") -> tidak ada jawaban | L62: =IFERROR(__xludf.DUMMYFUNCTION("""COMPUTED_VALUE"""),"https://docs.google.com/document/d/1dCS-DTyTB0rcOBWL6xkq6bti9h0yXz0xReLOQwOqm6Q/edit?usp=sharing") -> https://docs.google.com/document/d/1dCS-DTyTB0rcOBWL6xkq6bti9h0yXz0xReLOQwOqm6Q/edit?usp=sharing
A63: =IFERROR(__xludf.DUMMYFUNCTION("""COMPUTED_VALUE"""),46050.0) -> 46050 | B63: =IFERROR(__xludf.DUMMYFUNCTION("""COMPUTED_VALUE"""),"2601A060") -> 2601A060 | C63: =IFERROR(__xludf.DUMMYFUNCTION("""COMPUTED_VALUE"""),"Lanny suyanto") -> Lanny suyanto | D63: =IFERROR(__xludf.DUMMYFUNCTION("""COMPUTED_VALUE"""),"0817220272") -> 0817220272 | E63: =IFERROR(__xludf.DUMMYFUNCTION("""COMPUTED_VALUE"""),"Website") -> Website | F63: =IFERROR(__xludf.DUMMYFUNCTION("""COMPUTED_VALUE"""),"Gagal") -> Gagal | G63: =IFERROR(__xludf.DUMMYFUNCTION("""COMPUTED_VALUE"""),"4H3M") -> 4H3M | I63: =IFERROR(__xludf.DUMMYFUNCTION("""COMPUTED_VALUE"""),30.0) -> 30 | J63: =IFERROR(__xludf.DUMMYFUNCTION("""COMPUTED_VALUE"""),6.36E7) -> 63600000 | K63: =IFERROR(__xludf.DUMMYFUNCTION("""COMPUTED_VALUE"""),"tidak ada jawaban lagi") -> tidak ada jawaban lagi | L63: =IFERROR(__xludf.DUMMYFUNCTION("""COMPUTED_VALUE"""),"https://docs.google.com/document/d/1ByN8KaDbVn05mmAo3BQIhKqfPFfGWSR02o7DAvmWzng/edit?usp=sharing") -> https://docs.google.com/document/d/1ByN8KaDbVn05mmAo3BQIhKqfPFfGWSR02o7DAvmWzng/edit?usp=sharing
A64: =IFERROR(__xludf.DUMMYFUNCTION("""COMPUTED_VALUE"""),46050.0) -> 46050 | B64: =IFERROR(__xludf.DUMMYFUNCTION("""COMPUTED_VALUE"""),"2601A061") -> 2601A061 | C64: =IFERROR(__xludf.DUMMYFUNCTION("""COMPUTED_VALUE"""),"Sendy") -> Sendy | D64: =IFERROR(__xludf.DUMMYFUNCTION("""COMPUTED_VALUE"""),"087776660612") -> 087776660612 | E64: =IFERROR(__xludf.DUMMYFUNCTION("""COMPUTED_VALUE"""),"Website") -> Website | F64: =IFERROR(__xludf.DUMMYFUNCTION("""COMPUTED_VALUE"""),"Gagal") -> Gagal | G64: =IFERROR(__xludf.DUMMYFUNCTION("""COMPUTED_VALUE"""),"OT D, B") -> OT D, B | K64: =IFERROR(__xludf.DUMMYFUNCTION("""COMPUTED_VALUE"""),"sendiri") -> sendiri
A65: =IFERROR(__xludf.DUMMYFUNCTION("""COMPUTED_VALUE"""),46051.0) -> 46051 | B65: =IFERROR(__xludf.DUMMYFUNCTION("""COMPUTED_VALUE"""),"2601A062") -> 2601A062 | C65: =IFERROR(__xludf.DUMMYFUNCTION("""COMPUTED_VALUE"""),"Anugerah Perdana") -> Anugerah Perdana | D65: =IFERROR(__xludf.DUMMYFUNCTION("""COMPUTED_VALUE"""),"081329762124") -> 081329762124 | E65: =IFERROR(__xludf.DUMMYFUNCTION("""COMPUTED_VALUE"""),"Website") -> Website | F65: =IFERROR(__xludf.DUMMYFUNCTION("""COMPUTED_VALUE"""),"Gagal") -> Gagal | G65: =IFERROR(__xludf.DUMMYFUNCTION("""COMPUTED_VALUE"""),"3H2M Opsi A") -> 3H2M Opsi A | I65: =IFERROR(__xludf.DUMMYFUNCTION("""COMPUTED_VALUE"""),2.0) -> 2 | J65: =IFERROR(__xludf.DUMMYFUNCTION("""COMPUTED_VALUE"""),6128000.0) -> 6128000 | K65: =IFERROR(__xludf.DUMMYFUNCTION("""COMPUTED_VALUE"""),"belum balas lagi") -> belum balas lagi | L65: =IFERROR(__xludf.DUMMYFUNCTION("""COMPUTED_VALUE"""),"https://docs.google.com/document/d/13MqIUKaT--IgfEldtUan8PJMYEDPSAHBA90UC72C-nA/edit?usp=sharing") -> https://docs.google.com/document/d/13MqIUKaT--IgfEldtUan8PJMYEDPSAHBA90UC72C-nA/edit?usp=sharing
A66: =IFERROR(__xludf.DUMMYFUNCTION("""COMPUTED_VALUE"""),46049.0) -> 46049 | B66: =IFERROR(__xludf.DUMMYFUNCTION("""COMPUTED_VALUE"""),"2601A059") -> 2601A059 | C66: =IFERROR(__xludf.DUMMYFUNCTION("""COMPUTED_VALUE"""),"DR") -> DR | D66: =IFERROR(__xludf.DUMMYFUNCTION("""COMPUTED_VALUE"""),"085854406666") -> 085854406666 | E66: =IFERROR(__xludf.DUMMYFUNCTION("""COMPUTED_VALUE"""),"Website") -> Website | F66: =IFERROR(__xludf.DUMMYFUNCTION("""COMPUTED_VALUE"""),"Gagal") -> Gagal | G66: =IFERROR(__xludf.DUMMYFUNCTION("""COMPUTED_VALUE"""),"3H2M Opsi B") -> 3H2M Opsi B | I66: =IFERROR(__xludf.DUMMYFUNCTION("""COMPUTED_VALUE"""),5.0) -> 5 | K66: =IFERROR(__xludf.DUMMYFUNCTION("""COMPUTED_VALUE"""),"Gagal karna tidak ada balasan lagi") -> Gagal karna tidak ada balasan lagi
A67: =IFERROR(__xludf.DUMMYFUNCTION("""COMPUTED_VALUE"""),46051.0) -> 46051 | B67: =IFERROR(__xludf.DUMMYFUNCTION("""COMPUTED_VALUE"""),"2601A063") -> 2601A063 | C67: =IFERROR(__xludf.DUMMYFUNCTION("""COMPUTED_VALUE"""),"Nasyajulia") -> Nasyajulia | D67: =IFERROR(__xludf.DUMMYFUNCTION("""COMPUTED_VALUE"""),"0881024866564") -> 0881024866564 | E67: =IFERROR(__xludf.DUMMYFUNCTION("""COMPUTED_VALUE"""),"Website") -> Website | F67: =IFERROR(__xludf.DUMMYFUNCTION("""COMPUTED_VALUE"""),"Gagal") -> Gagal | K67: =IFERROR(__xludf.DUMMYFUNCTION("""COMPUTED_VALUE"""),"belum tertarik") -> belum tertarik
A68: =IFERROR(__xludf.DUMMYFUNCTION("""COMPUTED_VALUE"""),46052.0) -> 46052 | B68: =IFERROR(__xludf.DUMMYFUNCTION("""COMPUTED_VALUE"""),"2601A064") -> 2601A064 | C68: =IFERROR(__xludf.DUMMYFUNCTION("""COMPUTED_VALUE"""),"Hary ") -> Hary | D68: =IFERROR(__xludf.DUMMYFUNCTION("""COMPUTED_VALUE"""),"085257112446") -> 085257112446 | E68: =IFERROR(__xludf.DUMMYFUNCTION("""COMPUTED_VALUE"""),"Website") -> Website | F68: =IFERROR(__xludf.DUMMYFUNCTION("""COMPUTED_VALUE"""),"Gagal") -> Gagal | G68: =IFERROR(__xludf.DUMMYFUNCTION("""COMPUTED_VALUE"""),"2H1M Custom") -> 2H1M Custom | I68: =IFERROR(__xludf.DUMMYFUNCTION("""COMPUTED_VALUE"""),2.0) -> 2 | K68: =IFERROR(__xludf.DUMMYFUNCTION("""COMPUTED_VALUE"""),"kurang minat karna jauh") -> kurang minat karna jauh
A69: =IFERROR(__xludf.DUMMYFUNCTION("""COMPUTED_VALUE"""),46053.0) -> 46053 | B69: =IFERROR(__xludf.DUMMYFUNCTION("""COMPUTED_VALUE"""),"2601A065") -> 2601A065 | C69: =IFERROR(__xludf.DUMMYFUNCTION("""COMPUTED_VALUE"""),"Anna") -> Anna | D69: =IFERROR(__xludf.DUMMYFUNCTION("""COMPUTED_VALUE"""),"085829041849") -> 085829041849 | E69: =IFERROR(__xludf.DUMMYFUNCTION("""COMPUTED_VALUE"""),"Website") -> Website | F69: =IFERROR(__xludf.DUMMYFUNCTION("""COMPUTED_VALUE"""),"Gagal") -> Gagal | G69: =IFERROR(__xludf.DUMMYFUNCTION("""COMPUTED_VALUE"""),"paket trip ijen") -> paket trip ijen | I69: =IFERROR(__xludf.DUMMYFUNCTION("""COMPUTED_VALUE"""),12.0) -> 12 | K69: =IFERROR(__xludf.DUMMYFUNCTION("""COMPUTED_VALUE"""),"Masih ditawarkan ke tamunya") -> Masih ditawarkan ke tamunya
A70: =IFERROR(__xludf.DUMMYFUNCTION("""COMPUTED_VALUE"""),46053.0) -> 46053 | B70: =IFERROR(__xludf.DUMMYFUNCTION("""COMPUTED_VALUE"""),"2601A066") -> 2601A066 | C70: =IFERROR(__xludf.DUMMYFUNCTION("""COMPUTED_VALUE"""),"Rain") -> Rain | D70: =IFERROR(__xludf.DUMMYFUNCTION("""COMPUTED_VALUE"""),"085719601265") -> 085719601265 | E70: =IFERROR(__xludf.DUMMYFUNCTION("""COMPUTED_VALUE"""),"Website") -> Website | F70: =IFERROR(__xludf.DUMMYFUNCTION("""COMPUTED_VALUE"""),"Gagal") -> Gagal | K70: =IFERROR(__xludf.DUMMYFUNCTION("""COMPUTED_VALUE"""),"gagal, tidak ada balasan") -> gagal, tidak ada balasan
A71: =IFERROR(__xludf.DUMMYFUNCTION("""COMPUTED_VALUE"""),46053.0) -> 46053 | B71: =IFERROR(__xludf.DUMMYFUNCTION("""COMPUTED_VALUE"""),"2601A067") -> 2601A067 | C71: =IFERROR(__xludf.DUMMYFUNCTION("""COMPUTED_VALUE"""),"JM Rouf") -> JM Rouf | D71: =IFERROR(__xludf.DUMMYFUNCTION("""COMPUTED_VALUE"""),"33617373308") -> 33617373308 | E71: =IFERROR(__xludf.DUMMYFUNCTION("""COMPUTED_VALUE"""),"Website") -> Website | F71: =IFERROR(__xludf.DUMMYFUNCTION("""COMPUTED_VALUE"""),"Gagal") -> Gagal | G71: =IFERROR(__xludf.DUMMYFUNCTION("""COMPUTED_VALUE"""),"Trip D, PM, TI") -> Trip D, PM, TI | K71: =IFERROR(__xludf.DUMMYFUNCTION("""COMPUTED_VALUE"""),"tidak minat") -> tidak minat
A72: =IFERROR(__xludf.DUMMYFUNCTION("""COMPUTED_VALUE"""),46053.0) -> 46053 | B72: =IFERROR(__xludf.DUMMYFUNCTION("""COMPUTED_VALUE"""),"2601A068") -> 2601A068 | C72: =IFERROR(__xludf.DUMMYFUNCTION("""COMPUTED_VALUE"""),"Mila") -> Mila | D72: =IFERROR(__xludf.DUMMYFUNCTION("""COMPUTED_VALUE"""),"081511307136") -> 081511307136 | E72: =IFERROR(__xludf.DUMMYFUNCTION("""COMPUTED_VALUE"""),"Website") -> Website | F72: =IFERROR(__xludf.DUMMYFUNCTION("""COMPUTED_VALUE"""),"Gagal") -> Gagal | K72: =IFERROR(__xludf.DUMMYFUNCTION("""COMPUTED_VALUE"""),"Gagal Tidak ada respon") -> Gagal Tidak ada respon
A73: =IFERROR(__xludf.DUMMYFUNCTION("""COMPUTED_VALUE"""),46023.0) -> 46023 | B73: =IFERROR(__xludf.DUMMYFUNCTION("""COMPUTED_VALUE"""),"2602A001") -> 2602A001 | C73: =IFERROR(__xludf.DUMMYFUNCTION("""COMPUTED_VALUE"""),"Layla") -> Layla | D73: =IFERROR(__xludf.DUMMYFUNCTION("""COMPUTED_VALUE"""),"085334674721") -> 085334674721 | E73: =IFERROR(__xludf.DUMMYFUNCTION("""COMPUTED_VALUE"""),"Website") -> Website | F73: =IFERROR(__xludf.DUMMYFUNCTION("""COMPUTED_VALUE"""),"Closing") -> Closing | G73: =IFERROR(__xludf.DUMMYFUNCTION("""COMPUTED_VALUE"""),"Trip 1D M , B") -> Trip 1D M , B | H73: =IFERROR(__xludf.DUMMYFUNCTION("""COMPUTED_VALUE"""),46172.0) -> 46172 | I73: =IFERROR(__xludf.DUMMYFUNCTION("""COMPUTED_VALUE"""),4.0) -> 4 | J73: =IFERROR(__xludf.DUMMYFUNCTION("""COMPUTED_VALUE"""),3708000.0) -> 3708000 | K73: =IFERROR(__xludf.DUMMYFUNCTION("""COMPUTED_VALUE"""),"ALHAMDULILLAH ") -> ALHAMDULILLAH | L73: =IFERROR(__xludf.DUMMYFUNCTION("""COMPUTED_VALUE"""),"https://docs.google.com/document/d/11U4STf_PzmsD-tx3NDn4KyQxOXU4Cy7IdOLpO4cHx9Y/edit?usp=sharing") -> https://docs.google.com/document/d/11U4STf_PzmsD-tx3NDn4KyQxOXU4Cy7IdOLpO4cHx9Y/edit?usp=sharing
A74: =IFERROR(__xludf.DUMMYFUNCTION("""COMPUTED_VALUE"""),46055.0) -> 46055 | B74: =IFERROR(__xludf.DUMMYFUNCTION("""COMPUTED_VALUE"""),"2602A002") -> 2602A002 | C74: =IFERROR(__xludf.DUMMYFUNCTION("""COMPUTED_VALUE"""),"Suci") -> Suci | D74: =IFERROR(__xludf.DUMMYFUNCTION("""COMPUTED_VALUE"""),"081233877184") -> 081233877184 | E74: =IFERROR(__xludf.DUMMYFUNCTION("""COMPUTED_VALUE"""),"Website") -> Website | F74: =IFERROR(__xludf.DUMMYFUNCTION("""COMPUTED_VALUE"""),"Gagal") -> Gagal | G74: =IFERROR(__xludf.DUMMYFUNCTION("""COMPUTED_VALUE"""),"3H2M Opsi B") -> 3H2M Opsi B | H74: =IFERROR(__xludf.DUMMYFUNCTION("""COMPUTED_VALUE"""),46117.0) -> 46117 | I74: =IFERROR(__xludf.DUMMYFUNCTION("""COMPUTED_VALUE"""),4.0) -> 4 | K74: =IFERROR(__xludf.DUMMYFUNCTION("""COMPUTED_VALUE"""),"cancellll") -> cancellll
A75: =IFERROR(__xludf.DUMMYFUNCTION("""COMPUTED_VALUE"""),46056.0) -> 46056 | B75: =IFERROR(__xludf.DUMMYFUNCTION("""COMPUTED_VALUE"""),"2602A003") -> 2602A003 | C75: =IFERROR(__xludf.DUMMYFUNCTION("""COMPUTED_VALUE"""),"Steven sieto") -> Steven sieto | D75: =IFERROR(__xludf.DUMMYFUNCTION("""COMPUTED_VALUE"""),"08165444838") -> 08165444838 | E75: =IFERROR(__xludf.DUMMYFUNCTION("""COMPUTED_VALUE"""),"Website") -> Website | F75: =IFERROR(__xludf.DUMMYFUNCTION("""COMPUTED_VALUE"""),"Gagal") -> Gagal | G75: =IFERROR(__xludf.DUMMYFUNCTION("""COMPUTED_VALUE"""),"2H1M Z") -> 2H1M Z | I75: =IFERROR(__xludf.DUMMYFUNCTION("""COMPUTED_VALUE"""),20.0) -> 20 | J75: =IFERROR(__xludf.DUMMYFUNCTION("""COMPUTED_VALUE"""),1.5E7) -> 15000000 | K75: =IFERROR(__xludf.DUMMYFUNCTION("""COMPUTED_VALUE"""),"Blm balas lagi") -> Blm balas lagi
A76: =IFERROR(__xludf.DUMMYFUNCTION("""COMPUTED_VALUE"""),46057.0) -> 46057 | B76: =IFERROR(__xludf.DUMMYFUNCTION("""COMPUTED_VALUE"""),"2602A004") -> 2602A004 | C76: =IFERROR(__xludf.DUMMYFUNCTION("""COMPUTED_VALUE"""),"83173513987") -> 83173513987 | D76: =IFERROR(__xludf.DUMMYFUNCTION("""COMPUTED_VALUE"""),"083173513987") -> 083173513987 | E76: =IFERROR(__xludf.DUMMYFUNCTION("""COMPUTED_VALUE"""),"Website") -> Website | F76: =IFERROR(__xludf.DUMMYFUNCTION("""COMPUTED_VALUE"""),"Gagal") -> Gagal | G76: =IFERROR(__xludf.DUMMYFUNCTION("""COMPUTED_VALUE"""),"one day trip banyuwangi") -> one day trip banyuwangi | I76: =IFERROR(__xludf.DUMMYFUNCTION("""COMPUTED_VALUE"""),1.0) -> 1
A77: =IFERROR(__xludf.DUMMYFUNCTION("""COMPUTED_VALUE"""),46058.0) -> 46058 | B77: =IFERROR(__xludf.DUMMYFUNCTION("""COMPUTED_VALUE"""),"2602A005") -> 2602A005 | C77: =IFERROR(__xludf.DUMMYFUNCTION("""COMPUTED_VALUE"""),"Dr. Leny Erfiana") -> Dr. Leny Erfiana | D77: =IFERROR(__xludf.DUMMYFUNCTION("""COMPUTED_VALUE"""),"085236381772") -> 085236381772 | E77: =IFERROR(__xludf.DUMMYFUNCTION("""COMPUTED_VALUE"""),"Website") -> Website | F77: =IFERROR(__xludf.DUMMYFUNCTION("""COMPUTED_VALUE"""),"Gagal") -> Gagal | G77: =IFERROR(__xludf.DUMMYFUNCTION("""COMPUTED_VALUE"""),"trip 3H2M") -> trip 3H2M | H77: =IFERROR(__xludf.DUMMYFUNCTION("""COMPUTED_VALUE"""),46097.0) -> 46097 | I77: =IFERROR(__xludf.DUMMYFUNCTION("""COMPUTED_VALUE"""),3.0) -> 3 | J77: =IFERROR(__xludf.DUMMYFUNCTION("""COMPUTED_VALUE"""),6402000.0) -> 6402000 | K77: =IFERROR(__xludf.DUMMYFUNCTION("""COMPUTED_VALUE"""),"nanti dikabari lagi") -> nanti dikabari lagi
A78: =IFERROR(__xludf.DUMMYFUNCTION("""COMPUTED_VALUE"""),46058.0) -> 46058 | B78: =IFERROR(__xludf.DUMMYFUNCTION("""COMPUTED_VALUE"""),"2602A006") -> 2602A006 | C78: =IFERROR(__xludf.DUMMYFUNCTION("""COMPUTED_VALUE"""),"Akm") -> Akm | D78: =IFERROR(__xludf.DUMMYFUNCTION("""COMPUTED_VALUE"""),"085200412086") -> 085200412086 | E78: =IFERROR(__xludf.DUMMYFUNCTION("""COMPUTED_VALUE"""),"Lainnya") -> Lainnya | F78: =IFERROR(__xludf.DUMMYFUNCTION("""COMPUTED_VALUE"""),"Gagal") -> Gagal | G78: =IFERROR(__xludf.DUMMYFUNCTION("""COMPUTED_VALUE"""),"Trip Green island") -> Trip Green island | I78: =IFERROR(__xludf.DUMMYFUNCTION("""COMPUTED_VALUE"""),1.0) -> 1 | K78: =IFERROR(__xludf.DUMMYFUNCTION("""COMPUTED_VALUE"""),"sudah di trip lain") -> sudah di trip lain
A79: =IFERROR(__xludf.DUMMYFUNCTION("""COMPUTED_VALUE"""),46058.0) -> 46058 | B79: =IFERROR(__xludf.DUMMYFUNCTION("""COMPUTED_VALUE"""),"2602A007") -> 2602A007 | C79: =IFERROR(__xludf.DUMMYFUNCTION("""COMPUTED_VALUE"""),"Rizka") -> Rizka | D79: =IFERROR(__xludf.DUMMYFUNCTION("""COMPUTED_VALUE"""),"085280537600") -> 085280537600 | E79: =IFERROR(__xludf.DUMMYFUNCTION("""COMPUTED_VALUE"""),"Website") -> Website | F79: =IFERROR(__xludf.DUMMYFUNCTION("""COMPUTED_VALUE"""),"Closing") -> Closing | G79: =IFERROR(__xludf.DUMMYFUNCTION("""COMPUTED_VALUE"""),"2H1M Z (1D PM, 1D KW B)") -> 2H1M Z (1D PM, 1D KW B) | I79: =IFERROR(__xludf.DUMMYFUNCTION("""COMPUTED_VALUE"""),4.0) -> 4 | J79: =IFERROR(__xludf.DUMMYFUNCTION("""COMPUTED_VALUE"""),3840000.0) -> 3840000 | K79: =IFERROR(__xludf.DUMMYFUNCTION("""COMPUTED_VALUE"""),"Sudah DP alhamdulillah") -> Sudah DP alhamdulillah
A80: =IFERROR(__xludf.DUMMYFUNCTION("""COMPUTED_VALUE"""),46059.0) -> 46059 | B80: =IFERROR(__xludf.DUMMYFUNCTION("""COMPUTED_VALUE"""),"2602A008") -> 2602A008 | C80: =IFERROR(__xludf.DUMMYFUNCTION("""COMPUTED_VALUE"""),"Michelle") -> Michelle | D80: =IFERROR(__xludf.DUMMYFUNCTION("""COMPUTED_VALUE"""),"08111807321") -> 08111807321 | E80: =IFERROR(__xludf.DUMMYFUNCTION("""COMPUTED_VALUE"""),"Website") -> Website | F80: =IFERROR(__xludf.DUMMYFUNCTION("""COMPUTED_VALUE"""),"Gagal") -> Gagal | G80: =IFERROR(__xludf.DUMMYFUNCTION("""COMPUTED_VALUE"""),"Trip Teluk Hijau") -> Trip Teluk Hijau | H80: =IFERROR(__xludf.DUMMYFUNCTION("""COMPUTED_VALUE"""),46158.0) -> 46158 | I80: =IFERROR(__xludf.DUMMYFUNCTION("""COMPUTED_VALUE"""),6.0) -> 6 | J80: =IFERROR(__xludf.DUMMYFUNCTION("""COMPUTED_VALUE"""),3090000.0) -> 3090000 | K80: =IFERROR(__xludf.DUMMYFUNCTION("""COMPUTED_VALUE"""),"tidak ada balasan") -> tidak ada balasan | L80: =IFERROR(__xludf.DUMMYFUNCTION("""COMPUTED_VALUE"""),"https://docs.google.com/document/d/1Hq7YCuakPtUJsUYKsWDb8GCrQAL7Sype9pV3jo0_5XI/edit?usp=sharing") -> https://docs.google.com/document/d/1Hq7YCuakPtUJsUYKsWDb8GCrQAL7Sype9pV3jo0_5XI/edit?usp=sharing
A81: =IFERROR(__xludf.DUMMYFUNCTION("""COMPUTED_VALUE"""),46060.0) -> 46060 | B81: =IFERROR(__xludf.DUMMYFUNCTION("""COMPUTED_VALUE"""),"2602A009") -> 2602A009 | C81: =IFERROR(__xludf.DUMMYFUNCTION("""COMPUTED_VALUE"""),"Julinda") -> Julinda | D81: =IFERROR(__xludf.DUMMYFUNCTION("""COMPUTED_VALUE"""),"08990033369") -> 08990033369 | E81: =IFERROR(__xludf.DUMMYFUNCTION("""COMPUTED_VALUE"""),"Website") -> Website | F81: =IFERROR(__xludf.DUMMYFUNCTION("""COMPUTED_VALUE"""),"Gagal") -> Gagal | G81: =IFERROR(__xludf.DUMMYFUNCTION("""COMPUTED_VALUE"""),"OT Alas Purwo, D, PM") -> OT Alas Purwo, D, PM | H81: =IFERROR(__xludf.DUMMYFUNCTION("""COMPUTED_VALUE"""),46061.0) -> 46061 | I81: =IFERROR(__xludf.DUMMYFUNCTION("""COMPUTED_VALUE"""),2.0) -> 2 | K81: =IFERROR(__xludf.DUMMYFUNCTION("""COMPUTED_VALUE"""),"belum balas lagi") -> belum balas lagi
A82: =IFERROR(__xludf.DUMMYFUNCTION("""COMPUTED_VALUE"""),46060.0) -> 46060 | B82: =IFERROR(__xludf.DUMMYFUNCTION("""COMPUTED_VALUE"""),"2602A010") -> 2602A010 | C82: =IFERROR(__xludf.DUMMYFUNCTION("""COMPUTED_VALUE"""),"Lenny") -> Lenny | D82: =IFERROR(__xludf.DUMMYFUNCTION("""COMPUTED_VALUE"""),"081319190031") -> 081319190031 | E82: =IFERROR(__xludf.DUMMYFUNCTION("""COMPUTED_VALUE"""),"Website") -> Website | F82: =IFERROR(__xludf.DUMMYFUNCTION("""COMPUTED_VALUE"""),"Gagal") -> Gagal | G82: =IFERROR(__xludf.DUMMYFUNCTION("""COMPUTED_VALUE"""),"OT 3H2M Everyday") -> OT 3H2M Everyday | I82: =IFERROR(__xludf.DUMMYFUNCTION("""COMPUTED_VALUE"""),2.0) -> 2 | J82: =IFERROR(__xludf.DUMMYFUNCTION("""COMPUTED_VALUE"""),3200000.0) -> 3200000 | K82: =IFERROR(__xludf.DUMMYFUNCTION("""COMPUTED_VALUE"""),"masih tanya tanya") -> masih tanya tanya
A83: =IFERROR(__xludf.DUMMYFUNCTION("""COMPUTED_VALUE"""),46061.0) -> 46061 | B83: =IFERROR(__xludf.DUMMYFUNCTION("""COMPUTED_VALUE"""),"2602A011") -> 2602A011 | C83: =IFERROR(__xludf.DUMMYFUNCTION("""COMPUTED_VALUE"""),"A.M") -> A.M | D83: =IFERROR(__xludf.DUMMYFUNCTION("""COMPUTED_VALUE"""),"085141444406") -> 085141444406 | E83: =IFERROR(__xludf.DUMMYFUNCTION("""COMPUTED_VALUE"""),"Lainnya") -> Lainnya | F83: =IFERROR(__xludf.DUMMYFUNCTION("""COMPUTED_VALUE"""),"Gagal") -> Gagal | G83: =IFERROR(__xludf.DUMMYFUNCTION("""COMPUTED_VALUE"""),"OT D, B") -> OT D, B | H83: =IFERROR(__xludf.DUMMYFUNCTION("""COMPUTED_VALUE"""),46068.0) -> 46068 | I83: =IFERROR(__xludf.DUMMYFUNCTION("""COMPUTED_VALUE"""),2.0) -> 2 | J83: =IFERROR(__xludf.DUMMYFUNCTION("""COMPUTED_VALUE"""),1100000.0) -> 1100000 | K83: =IFERROR(__xludf.DUMMYFUNCTION("""COMPUTED_VALUE"""),"nanti dikabari jika fiks, masih di luar negri, FU 2 maret") -> nanti dikabari jika fiks, masih di luar negri, FU 2 maret
A84: =IFERROR(__xludf.DUMMYFUNCTION("""COMPUTED_VALUE"""),46061.0) -> 46061 | B84: =IFERROR(__xludf.DUMMYFUNCTION("""COMPUTED_VALUE"""),"2602A012") -> 2602A012 | C84: =IFERROR(__xludf.DUMMYFUNCTION("""COMPUTED_VALUE"""),"Marina Woods") -> Marina Woods | D84: =IFERROR(__xludf.DUMMYFUNCTION("""COMPUTED_VALUE"""),"447899367364") -> 447899367364 | E84: =IFERROR(__xludf.DUMMYFUNCTION("""COMPUTED_VALUE"""),"Website") -> Website | F84: =IFERROR(__xludf.DUMMYFUNCTION("""COMPUTED_VALUE"""),"Closing") -> Closing | G84: =IFERROR(__xludf.DUMMYFUNCTION("""COMPUTED_VALUE"""),"Private Trip Ijen") -> Private Trip Ijen | H84: =IFERROR(__xludf.DUMMYFUNCTION("""COMPUTED_VALUE"""),46062.0) -> 46062 | I84: =IFERROR(__xludf.DUMMYFUNCTION("""COMPUTED_VALUE"""),2.0) -> 2 | J84: =IFERROR(__xludf.DUMMYFUNCTION("""COMPUTED_VALUE"""),1600000.0) -> 1600000 | K84: =IFERROR(__xludf.DUMMYFUNCTION("""COMPUTED_VALUE"""),"order, sdh dp") -> order, sdh dp
A85: =IFERROR(__xludf.DUMMYFUNCTION("""COMPUTED_VALUE"""),46062.0) -> 46062 | B85: =IFERROR(__xludf.DUMMYFUNCTION("""COMPUTED_VALUE"""),"2602A013") -> 2602A013 | C85: =IFERROR(__xludf.DUMMYFUNCTION("""COMPUTED_VALUE"""),"Shethe") -> Shethe | D85: =IFERROR(__xludf.DUMMYFUNCTION("""COMPUTED_VALUE"""),"085729951440") -> 085729951440 | E85: =IFERROR(__xludf.DUMMYFUNCTION("""COMPUTED_VALUE"""),"Website") -> Website | F85: =IFERROR(__xludf.DUMMYFUNCTION("""COMPUTED_VALUE"""),"Gagal") -> Gagal | G85: =IFERROR(__xludf.DUMMYFUNCTION("""COMPUTED_VALUE"""),"Trip Ijen") -> Trip Ijen | I85: =IFERROR(__xludf.DUMMYFUNCTION("""COMPUTED_VALUE"""),5.0) -> 5 | K85: =IFERROR(__xludf.DUMMYFUNCTION("""COMPUTED_VALUE"""),"tanya tanya") -> tanya tanya
A86: =IFERROR(__xludf.DUMMYFUNCTION("""COMPUTED_VALUE"""),46062.0) -> 46062 | B86: =IFERROR(__xludf.DUMMYFUNCTION("""COMPUTED_VALUE"""),"2602A014") -> 2602A014 | C86: =IFERROR(__xludf.DUMMYFUNCTION("""COMPUTED_VALUE"""),"Sunardi Edy Sukamto") -> Sunardi Edy Sukamto | D86: =IFERROR(__xludf.DUMMYFUNCTION("""COMPUTED_VALUE"""),"08123282494") -> 08123282494 | E86: =IFERROR(__xludf.DUMMYFUNCTION("""COMPUTED_VALUE"""),"Website") -> Website | F86: =IFERROR(__xludf.DUMMYFUNCTION("""COMPUTED_VALUE"""),"Gagal") -> Gagal | G86: =IFERROR(__xludf.DUMMYFUNCTION("""COMPUTED_VALUE"""),"1 day Trip D,MU,PM") -> 1 day Trip D,MU,PM | H86: =IFERROR(__xludf.DUMMYFUNCTION("""COMPUTED_VALUE"""),46067.0) -> 46067 | I86: =IFERROR(__xludf.DUMMYFUNCTION("""COMPUTED_VALUE"""),32.0) -> 32 | J86: =IFERROR(__xludf.DUMMYFUNCTION("""COMPUTED_VALUE"""),7360000.0) -> 7360000 | K86: =IFERROR(__xludf.DUMMYFUNCTION("""COMPUTED_VALUE"""),"rombongan tidak jadi berangkat") -> rombongan tidak jadi berangkat
A87: =IFERROR(__xludf.DUMMYFUNCTION("""COMPUTED_VALUE"""),46062.0) -> 46062 | B87: =IFERROR(__xludf.DUMMYFUNCTION("""COMPUTED_VALUE"""),"2602A015") -> 2602A015 | C87: =IFERROR(__xludf.DUMMYFUNCTION("""COMPUTED_VALUE"""),"Trisna") -> Trisna | D87: =IFERROR(__xludf.DUMMYFUNCTION("""COMPUTED_VALUE"""),"081332193311") -> 081332193311 | E87: =IFERROR(__xludf.DUMMYFUNCTION("""COMPUTED_VALUE"""),"Website") -> Website | F87: =IFERROR(__xludf.DUMMYFUNCTION("""COMPUTED_VALUE"""),"Gagal") -> Gagal | G87: =IFERROR(__xludf.DUMMYFUNCTION("""COMPUTED_VALUE"""),"Trip GI") -> Trip GI | I87: =IFERROR(__xludf.DUMMYFUNCTION("""COMPUTED_VALUE"""),2.0) -> 2 | K87: =IFERROR(__xludf.DUMMYFUNCTION("""COMPUTED_VALUE"""),"gagal karna tidak tertarik") -> gagal karna tidak tertarik
A88: =IFERROR(__xludf.DUMMYFUNCTION("""COMPUTED_VALUE"""),46062.0) -> 46062 | B88: =IFERROR(__xludf.DUMMYFUNCTION("""COMPUTED_VALUE"""),"2602A016") -> 2602A016 | C88: =IFERROR(__xludf.DUMMYFUNCTION("""COMPUTED_VALUE"""),"Ulul Amri") -> Ulul Amri | D88: =IFERROR(__xludf.DUMMYFUNCTION("""COMPUTED_VALUE"""),"085278155358") -> 085278155358 | E88: =IFERROR(__xludf.DUMMYFUNCTION("""COMPUTED_VALUE"""),"Website") -> Website | F88: =IFERROR(__xludf.DUMMYFUNCTION("""COMPUTED_VALUE"""),"Gagal") -> Gagal | G88: =IFERROR(__xludf.DUMMYFUNCTION("""COMPUTED_VALUE"""),"Trip Ijen") -> Trip Ijen | H88: =IFERROR(__xludf.DUMMYFUNCTION("""COMPUTED_VALUE"""),46067.0) -> 46067 | I88: =IFERROR(__xludf.DUMMYFUNCTION("""COMPUTED_VALUE"""),5.0) -> 5 | K88: =IFERROR(__xludf.DUMMYFUNCTION("""COMPUTED_VALUE"""),"lewat tanggal dan tidak balas lagi") -> lewat tanggal dan tidak balas lagi
A89: =IFERROR(__xludf.DUMMYFUNCTION("""COMPUTED_VALUE"""),46063.0) -> 46063 | B89: =IFERROR(__xludf.DUMMYFUNCTION("""COMPUTED_VALUE"""),"2602A017") -> 2602A017 | C89: =IFERROR(__xludf.DUMMYFUNCTION("""COMPUTED_VALUE"""),"Rosidbagus") -> Rosidbagus | D89: =IFERROR(__xludf.DUMMYFUNCTION("""COMPUTED_VALUE"""),"082123031677") -> 082123031677 | E89: =IFERROR(__xludf.DUMMYFUNCTION("""COMPUTED_VALUE"""),"Website") -> Website | F89: =IFERROR(__xludf.DUMMYFUNCTION("""COMPUTED_VALUE"""),"Gagal") -> Gagal | G89: =IFERROR(__xludf.DUMMYFUNCTION("""COMPUTED_VALUE"""),"Trip D, B") -> Trip D, B | H89: =IFERROR(__xludf.DUMMYFUNCTION("""COMPUTED_VALUE"""),46105.0) -> 46105 | I89: =IFERROR(__xludf.DUMMYFUNCTION("""COMPUTED_VALUE"""),6.0) -> 6 | J89: =IFERROR(__xludf.DUMMYFUNCTION("""COMPUTED_VALUE"""),4290000.0) -> 4290000 | K89: =IFERROR(__xludf.DUMMYFUNCTION("""COMPUTED_VALUE"""),"gada respon") -> gada respon
A90: =IFERROR(__xludf.DUMMYFUNCTION("""COMPUTED_VALUE"""),46063.0) -> 46063 | B90: =IFERROR(__xludf.DUMMYFUNCTION("""COMPUTED_VALUE"""),"2602A018") -> 2602A018 | C90: =IFERROR(__xludf.DUMMYFUNCTION("""COMPUTED_VALUE"""),"Dila ") -> Dila | D90: =IFERROR(__xludf.DUMMYFUNCTION("""COMPUTED_VALUE"""),"081332256246") -> 081332256246 | E90: =IFERROR(__xludf.DUMMYFUNCTION("""COMPUTED_VALUE"""),"Website") -> Website | F90: =IFERROR(__xludf.DUMMYFUNCTION("""COMPUTED_VALUE"""),"Closing") -> Closing | G90: =IFERROR(__xludf.DUMMYFUNCTION("""COMPUTED_VALUE"""),"Open Trip Ijen") -> Open Trip Ijen | H90: =IFERROR(__xludf.DUMMYFUNCTION("""COMPUTED_VALUE"""),46069.0) -> 46069 | I90: =IFERROR(__xludf.DUMMYFUNCTION("""COMPUTED_VALUE"""),4.0) -> 4 | J90: =IFERROR(__xludf.DUMMYFUNCTION("""COMPUTED_VALUE"""),1000000.0) -> 1000000 | K90: =IFERROR(__xludf.DUMMYFUNCTION("""COMPUTED_VALUE"""),"order,") -> order,
A91: =IFERROR(__xludf.DUMMYFUNCTION("""COMPUTED_VALUE"""),46066.0) -> 46066 | B91: =IFERROR(__xludf.DUMMYFUNCTION("""COMPUTED_VALUE"""),"2602A019") -> 2602A019 | C91: =IFERROR(__xludf.DUMMYFUNCTION("""COMPUTED_VALUE"""),"Dev") -> Dev | D91: =IFERROR(__xludf.DUMMYFUNCTION("""COMPUTED_VALUE"""),"0895411763369") -> 0895411763369 | E91: =IFERROR(__xludf.DUMMYFUNCTION("""COMPUTED_VALUE"""),"Website") -> Website | F91: =IFERROR(__xludf.DUMMYFUNCTION("""COMPUTED_VALUE"""),"Gagal") -> Gagal
A92: =IFERROR(__xludf.DUMMYFUNCTION("""COMPUTED_VALUE"""),46066.0) -> 46066 | B92: =IFERROR(__xludf.DUMMYFUNCTION("""COMPUTED_VALUE"""),"2602A020") -> 2602A020 | C92: =IFERROR(__xludf.DUMMYFUNCTION("""COMPUTED_VALUE"""),"Happy Petals") -> Happy Petals | D92: =IFERROR(__xludf.DUMMYFUNCTION("""COMPUTED_VALUE"""),"08315680898") -> 08315680898 | E92: =IFERROR(__xludf.DUMMYFUNCTION("""COMPUTED_VALUE"""),"Website") -> Website | F92: =IFERROR(__xludf.DUMMYFUNCTION("""COMPUTED_VALUE"""),"Gagal") -> Gagal | G92: =IFERROR(__xludf.DUMMYFUNCTION("""COMPUTED_VALUE"""),"Trip Menjangan, Ijen") -> Trip Menjangan, Ijen | I92: =IFERROR(__xludf.DUMMYFUNCTION("""COMPUTED_VALUE"""),3.0) -> 3 | K92: =IFERROR(__xludf.DUMMYFUNCTION("""COMPUTED_VALUE"""),"tanya tanya") -> tanya tanya
A93: =IFERROR(__xludf.DUMMYFUNCTION("""COMPUTED_VALUE"""),46066.0) -> 46066 | B93: =IFERROR(__xludf.DUMMYFUNCTION("""COMPUTED_VALUE"""),"2602A021") -> 2602A021 | C93: =IFERROR(__xludf.DUMMYFUNCTION("""COMPUTED_VALUE"""),"Owen") -> Owen | D93: =IFERROR(__xludf.DUMMYFUNCTION("""COMPUTED_VALUE"""),"085100988588") -> 085100988588 | E93: =IFERROR(__xludf.DUMMYFUNCTION("""COMPUTED_VALUE"""),"Instagram") -> Instagram | F93: =IFERROR(__xludf.DUMMYFUNCTION("""COMPUTED_VALUE"""),"Closing") -> Closing | G93: =IFERROR(__xludf.DUMMYFUNCTION("""COMPUTED_VALUE"""),"private trip M T") -> private trip M T | H93: =IFERROR(__xludf.DUMMYFUNCTION("""COMPUTED_VALUE"""),46074.0) -> 46074 | I93: =IFERROR(__xludf.DUMMYFUNCTION("""COMPUTED_VALUE"""),3.0) -> 3 | J93: =IFERROR(__xludf.DUMMYFUNCTION("""COMPUTED_VALUE"""),1830000.0) -> 1830000 | K93: =IFERROR(__xludf.DUMMYFUNCTION("""COMPUTED_VALUE""")," order") -> order
A94: =IFERROR(__xludf.DUMMYFUNCTION("""COMPUTED_VALUE"""),46067.0) -> 46067 | B94: =IFERROR(__xludf.DUMMYFUNCTION("""COMPUTED_VALUE"""),"2602A022") -> 2602A022 | C94: =IFERROR(__xludf.DUMMYFUNCTION("""COMPUTED_VALUE"""),"Rahayu") -> Rahayu | D94: =IFERROR(__xludf.DUMMYFUNCTION("""COMPUTED_VALUE"""),"08113392183") -> 08113392183 | E94: =IFERROR(__xludf.DUMMYFUNCTION("""COMPUTED_VALUE"""),"Website") -> Website | F94: =IFERROR(__xludf.DUMMYFUNCTION("""COMPUTED_VALUE"""),"Gagal") -> Gagal | G94: =IFERROR(__xludf.DUMMYFUNCTION("""COMPUTED_VALUE"""),"2H1M") -> 2H1M | I94: =IFERROR(__xludf.DUMMYFUNCTION("""COMPUTED_VALUE"""),1.0) -> 1 | J94: =IFERROR(__xludf.DUMMYFUNCTION("""COMPUTED_VALUE"""),4680000.0) -> 4680000 | K94: =IFERROR(__xludf.DUMMYFUNCTION("""COMPUTED_VALUE"""),"belum balas lagi") -> belum balas lagi
A95: =IFERROR(__xludf.DUMMYFUNCTION("""COMPUTED_VALUE"""),46067.0) -> 46067 | B95: =IFERROR(__xludf.DUMMYFUNCTION("""COMPUTED_VALUE"""),"2512A003") -> 2512A003 | C95: =IFERROR(__xludf.DUMMYFUNCTION("""COMPUTED_VALUE"""),"Arif Dalan Wisata") -> Arif Dalan Wisata | D95: =IFERROR(__xludf.DUMMYFUNCTION("""COMPUTED_VALUE"""),"082121616867") -> 082121616867 | E95: =IFERROR(__xludf.DUMMYFUNCTION("""COMPUTED_VALUE"""),"Website") -> Website | F95: =IFERROR(__xludf.DUMMYFUNCTION("""COMPUTED_VALUE"""),"Gagal") -> Gagal | G95: =IFERROR(__xludf.DUMMYFUNCTION("""COMPUTED_VALUE"""),"2H2M Custom") -> 2H2M Custom | I95: =IFERROR(__xludf.DUMMYFUNCTION("""COMPUTED_VALUE"""),35.0) -> 35 | J95: =IFERROR(__xludf.DUMMYFUNCTION("""COMPUTED_VALUE"""),5.25E7) -> 52500000 | K95: =IFERROR(__xludf.DUMMYFUNCTION("""COMPUTED_VALUE"""),"sudah buat penawaran") -> sudah buat penawaran
A96: =IFERROR(__xludf.DUMMYFUNCTION("""COMPUTED_VALUE"""),46067.0) -> 46067 | B96: =IFERROR(__xludf.DUMMYFUNCTION("""COMPUTED_VALUE"""),"2602A023") -> 2602A023 | C96: =IFERROR(__xludf.DUMMYFUNCTION("""COMPUTED_VALUE"""),"Tri Handoko") -> Tri Handoko | D96: =IFERROR(__xludf.DUMMYFUNCTION("""COMPUTED_VALUE"""),"08151629111") -> 08151629111 | E96: =IFERROR(__xludf.DUMMYFUNCTION("""COMPUTED_VALUE"""),"Website") -> Website | F96: =IFERROR(__xludf.DUMMYFUNCTION("""COMPUTED_VALUE"""),"Closing") -> Closing | G96: =IFERROR(__xludf.DUMMYFUNCTION("""COMPUTED_VALUE"""),"Trip Menjangan Tabuhan") -> Trip Menjangan Tabuhan | H96: =IFERROR(__xludf.DUMMYFUNCTION("""COMPUTED_VALUE"""),46069.0) -> 46069 | I96: =IFERROR(__xludf.DUMMYFUNCTION("""COMPUTED_VALUE"""),6.0) -> 6 | J96: =IFERROR(__xludf.DUMMYFUNCTION("""COMPUTED_VALUE"""),2460000.0) -> 2460000 | K96: =IFERROR(__xludf.DUMMYFUNCTION("""COMPUTED_VALUE"""),"order") -> order
A97: =IFERROR(__xludf.DUMMYFUNCTION("""COMPUTED_VALUE"""),46069.0) -> 46069 | B97: =IFERROR(__xludf.DUMMYFUNCTION("""COMPUTED_VALUE"""),"2602A024") -> 2602A024 | C97: =IFERROR(__xludf.DUMMYFUNCTION("""COMPUTED_VALUE"""),"Dirga") -> Dirga | D97: =IFERROR(__xludf.DUMMYFUNCTION("""COMPUTED_VALUE"""),"083819575522‬") -> 083819575522‬ | E97: =IFERROR(__xludf.DUMMYFUNCTION("""COMPUTED_VALUE"""),"Lainnya") -> Lainnya | F97: =IFERROR(__xludf.DUMMYFUNCTION("""COMPUTED_VALUE"""),"Gagal") -> Gagal | G97: =IFERROR(__xludf.DUMMYFUNCTION("""COMPUTED_VALUE"""),"3H2M") -> 3H2M | I97: =IFERROR(__xludf.DUMMYFUNCTION("""COMPUTED_VALUE"""),2.0) -> 2 | K97: =IFERROR(__xludf.DUMMYFUNCTION("""COMPUTED_VALUE"""),"budget masih kurang") -> budget masih kurang
A98: =IFERROR(__xludf.DUMMYFUNCTION("""COMPUTED_VALUE"""),46069.0) -> 46069 | B98: =IFERROR(__xludf.DUMMYFUNCTION("""COMPUTED_VALUE"""),"2602A025") -> 2602A025 | C98: =IFERROR(__xludf.DUMMYFUNCTION("""COMPUTED_VALUE"""),"083134610505‬") -> 083134610505‬ | D98: =IFERROR(__xludf.DUMMYFUNCTION("""COMPUTED_VALUE"""),"083134610505‬") -> 083134610505‬ | E98: =IFERROR(__xludf.DUMMYFUNCTION("""COMPUTED_VALUE"""),"Website") -> Website | F98: =IFERROR(__xludf.DUMMYFUNCTION("""COMPUTED_VALUE"""),"Gagal") -> Gagal | G98: =IFERROR(__xludf.DUMMYFUNCTION("""COMPUTED_VALUE"""),"3H2M") -> 3H2M | I98: =IFERROR(__xludf.DUMMYFUNCTION("""COMPUTED_VALUE"""),2.0) -> 2 | K98: =IFERROR(__xludf.DUMMYFUNCTION("""COMPUTED_VALUE"""),"tidak ada jawaban") -> tidak ada jawaban
A99: =IFERROR(__xludf.DUMMYFUNCTION("""COMPUTED_VALUE"""),46069.0) -> 46069 | B99: =IFERROR(__xludf.DUMMYFUNCTION("""COMPUTED_VALUE"""),"2602A026") -> 2602A026 | C99: =IFERROR(__xludf.DUMMYFUNCTION("""COMPUTED_VALUE"""),"Ira") -> Ira | D99: =IFERROR(__xludf.DUMMYFUNCTION("""COMPUTED_VALUE"""),"083820481784‬") -> 083820481784‬ | E99: =IFERROR(__xludf.DUMMYFUNCTION("""COMPUTED_VALUE"""),"Lainnya") -> Lainnya | F99: =IFERROR(__xludf.DUMMYFUNCTION("""COMPUTED_VALUE"""),"Gagal") -> Gagal | G99: =IFERROR(__xludf.DUMMYFUNCTION("""COMPUTED_VALUE"""),"3H2M") -> 3H2M | I99: =IFERROR(__xludf.DUMMYFUNCTION("""COMPUTED_VALUE"""),2.0) -> 2 | K99: =IFERROR(__xludf.DUMMYFUNCTION("""COMPUTED_VALUE"""),"gada balasan") -> gada balasan | L99: =IFERROR(__xludf.DUMMYFUNCTION("""COMPUTED_VALUE"""),"https://docs.google.com/document/d/11YdmRlFi-WWKqHGELpCpy0x-_2wwvx5U7V_2f2bLfHI/edit?usp=sharing") -> https://docs.google.com/document/d/11YdmRlFi-WWKqHGELpCpy0x-_2wwvx5U7V_2f2bLfHI/edit?usp=sharing
A100: =IFERROR(__xludf.DUMMYFUNCTION("""COMPUTED_VALUE"""),46070.0) -> 46070 | B100: =IFERROR(__xludf.DUMMYFUNCTION("""COMPUTED_VALUE"""),"2602A027") -> 2602A027 | C100: =IFERROR(__xludf.DUMMYFUNCTION("""COMPUTED_VALUE"""),"Elita") -> Elita | D100: =IFERROR(__xludf.DUMMYFUNCTION("""COMPUTED_VALUE"""),"0818669148‬") -> 0818669148‬ | E100: =IFERROR(__xludf.DUMMYFUNCTION("""COMPUTED_VALUE"""),"Website") -> Website | F100: =IFERROR(__xludf.DUMMYFUNCTION("""COMPUTED_VALUE"""),"Gagal") -> Gagal | G100: =IFERROR(__xludf.DUMMYFUNCTION("""COMPUTED_VALUE"""),"2H1M") -> 2H1M | K100: =IFERROR(__xludf.DUMMYFUNCTION("""COMPUTED_VALUE"""),"tidak ada jawaban") -> tidak ada jawaban
...

Sheet Leads_Holiday
A1: =IFERROR(__xludf.DUMMYFUNCTION("QUERY( 'Input Data'!A1:N5505, ""select B, A, C, D, E, G, H, I, J, K, L, N where F = 'Holiday'"", 1 ) "),"TANGGAL") -> TANGGAL | B1: =IFERROR(__xludf.DUMMYFUNCTION("""COMPUTED_VALUE"""),"KODE") -> KODE | C1: =IFERROR(__xludf.DUMMYFUNCTION("""COMPUTED_VALUE"""),"NAMA") -> NAMA | D1: =IFERROR(__xludf.DUMMYFUNCTION("""COMPUTED_VALUE"""),"WHATSAPP") -> WHATSAPP | E1: =IFERROR(__xludf.DUMMYFUNCTION("""COMPUTED_VALUE"""),"SOURCE") -> SOURCE | F1: =IFERROR(__xludf.DUMMYFUNCTION("""COMPUTED_VALUE"""),"STATUS") -> STATUS | G1: =IFERROR(__xludf.DUMMYFUNCTION("""COMPUTED_VALUE"""),"PAKET / DESTINASI") -> PAKET / DESTINASI | H1: =IFERROR(__xludf.DUMMYFUNCTION("""COMPUTED_VALUE"""),"TANGGAL TRIP") -> TANGGAL TRIP | I1: =IFERROR(__xludf.DUMMYFUNCTION("""COMPUTED_VALUE"""),"PAX") -> PAX | J1: =IFERROR(__xludf.DUMMYFUNCTION("""COMPUTED_VALUE"""),"ESTIMASI NILAI ORDER") -> ESTIMASI NILAI ORDER | K1: =IFERROR(__xludf.DUMMYFUNCTION("""COMPUTED_VALUE"""),"KETERANGAN") -> KETERANGAN | L1: =IFERROR(__xludf.DUMMYFUNCTION("""COMPUTED_VALUE"""),"ANALISA AI") -> ANALISA AI
A2: =IFERROR(__xludf.DUMMYFUNCTION("""COMPUTED_VALUE"""),46023.0) -> 46023 | B2: =IFERROR(__xludf.DUMMYFUNCTION("""COMPUTED_VALUE"""),"2601H001") -> 2601H001 | C2: =IFERROR(__xludf.DUMMYFUNCTION("""COMPUTED_VALUE"""),"Imam Syaroni") -> Imam Syaroni | D2: =IFERROR(__xludf.DUMMYFUNCTION("""COMPUTED_VALUE"""),"0811311157") -> 0811311157 | E2: =IFERROR(__xludf.DUMMYFUNCTION("""COMPUTED_VALUE"""),"Website") -> Website | F2: =IFERROR(__xludf.DUMMYFUNCTION("""COMPUTED_VALUE"""),"Closing") -> Closing | G2: =IFERROR(__xludf.DUMMYFUNCTION("""COMPUTED_VALUE"""),"One day Baluran") -> One day Baluran | H2: =IFERROR(__xludf.DUMMYFUNCTION("""COMPUTED_VALUE"""),46023.0) -> 46023 | I2: =IFERROR(__xludf.DUMMYFUNCTION("""COMPUTED_VALUE"""),3.0) -> 3 | K2: =IFERROR(__xludf.DUMMYFUNCTION("""COMPUTED_VALUE"""),"Alhamdulillah closing") -> Alhamdulillah closing
A3: =IFERROR(__xludf.DUMMYFUNCTION("""COMPUTED_VALUE"""),46022.0) -> 46022 | B3: =IFERROR(__xludf.DUMMYFUNCTION("""COMPUTED_VALUE"""),"2601H002") -> 2601H002 | C3: =IFERROR(__xludf.DUMMYFUNCTION("""COMPUTED_VALUE"""),"Puspita Anggasari") -> Puspita Anggasari | D3: =IFERROR(__xludf.DUMMYFUNCTION("""COMPUTED_VALUE"""),"081317773235") -> 081317773235 | E3: =IFERROR(__xludf.DUMMYFUNCTION("""COMPUTED_VALUE"""),"Website") -> Website | F3: =IFERROR(__xludf.DUMMYFUNCTION("""COMPUTED_VALUE"""),"Closing") -> Closing | H3: =IFERROR(__xludf.DUMMYFUNCTION("""COMPUTED_VALUE"""),46025.0) -> 46025 | I3: =IFERROR(__xludf.DUMMYFUNCTION("""COMPUTED_VALUE"""),5.0) -> 5
A4: =IFERROR(__xludf.DUMMYFUNCTION("""COMPUTED_VALUE"""),46003.0) -> 46003 | B4: =IFERROR(__xludf.DUMMYFUNCTION("""COMPUTED_VALUE"""),"2601H003") -> 2601H003 | C4: =IFERROR(__xludf.DUMMYFUNCTION("""COMPUTED_VALUE"""),"Sri") -> Sri | D4: =IFERROR(__xludf.DUMMYFUNCTION("""COMPUTED_VALUE"""),"0816691965") -> 0816691965 | E4: =IFERROR(__xludf.DUMMYFUNCTION("""COMPUTED_VALUE"""),"Website") -> Website | F4: =IFERROR(__xludf.DUMMYFUNCTION("""COMPUTED_VALUE"""),"Closing") -> Closing | I4: =IFERROR(__xludf.DUMMYFUNCTION("""COMPUTED_VALUE"""),10.0) -> 10 | J4: =IFERROR(__xludf.DUMMYFUNCTION("""COMPUTED_VALUE"""),6870000.0) -> 6870000
A5: =IFERROR(__xludf.DUMMYFUNCTION("""COMPUTED_VALUE"""),46034.0) -> 46034 | B5: =IFERROR(__xludf.DUMMYFUNCTION("""COMPUTED_VALUE"""),"2601H004") -> 2601H004 | C5: =IFERROR(__xludf.DUMMYFUNCTION("""COMPUTED_VALUE"""),"Arum Radiasti") -> Arum Radiasti | D5: =IFERROR(__xludf.DUMMYFUNCTION("""COMPUTED_VALUE"""),"08164844630") -> 08164844630 | E5: =IFERROR(__xludf.DUMMYFUNCTION("""COMPUTED_VALUE"""),"Website") -> Website | F5: =IFERROR(__xludf.DUMMYFUNCTION("""COMPUTED_VALUE"""),"Closing") -> Closing | I5: =IFERROR(__xludf.DUMMYFUNCTION("""COMPUTED_VALUE"""),5.0) -> 5 | J5: =IFERROR(__xludf.DUMMYFUNCTION("""COMPUTED_VALUE"""),6650000.0) -> 6650000
A6: =IFERROR(__xludf.DUMMYFUNCTION("""COMPUTED_VALUE"""),46027.0) -> 46027 | B6: =IFERROR(__xludf.DUMMYFUNCTION("""COMPUTED_VALUE"""),"2601H005") -> 2601H005 | C6: =IFERROR(__xludf.DUMMYFUNCTION("""COMPUTED_VALUE"""),"Gugun Gunawan") -> Gugun Gunawan | D6: =IFERROR(__xludf.DUMMYFUNCTION("""COMPUTED_VALUE"""),"08128010671") -> 08128010671 | E6: =IFERROR(__xludf.DUMMYFUNCTION("""COMPUTED_VALUE"""),"Website") -> Website | F6: =IFERROR(__xludf.DUMMYFUNCTION("""COMPUTED_VALUE"""),"Closing") -> Closing | H6: =IFERROR(__xludf.DUMMYFUNCTION("""COMPUTED_VALUE"""),46039.0) -> 46039 | I6: =IFERROR(__xludf.DUMMYFUNCTION("""COMPUTED_VALUE"""),4.0) -> 4 | J6: =IFERROR(__xludf.DUMMYFUNCTION("""COMPUTED_VALUE"""),3872000.0) -> 3872000
A7: =IFERROR(__xludf.DUMMYFUNCTION("""COMPUTED_VALUE"""),46033.0) -> 46033 | B7: =IFERROR(__xludf.DUMMYFUNCTION("""COMPUTED_VALUE"""),"2601H006") -> 2601H006 | C7: =IFERROR(__xludf.DUMMYFUNCTION("""COMPUTED_VALUE"""),"Dzulfikri") -> Dzulfikri | D7: =IFERROR(__xludf.DUMMYFUNCTION("""COMPUTED_VALUE"""),"081385881976") -> 081385881976 | E7: =IFERROR(__xludf.DUMMYFUNCTION("""COMPUTED_VALUE"""),"Website") -> Website | F7: =IFERROR(__xludf.DUMMYFUNCTION("""COMPUTED_VALUE"""),"Closing") -> Closing | I7: =IFERROR(__xludf.DUMMYFUNCTION("""COMPUTED_VALUE"""),5.0) -> 5 | J7: =IFERROR(__xludf.DUMMYFUNCTION("""COMPUTED_VALUE"""),8465000.0) -> 8465000
A8: =IFERROR(__xludf.DUMMYFUNCTION("""COMPUTED_VALUE"""),46041.0) -> 46041 | B8: =IFERROR(__xludf.DUMMYFUNCTION("""COMPUTED_VALUE"""),"2601H007") -> 2601H007 | C8: =IFERROR(__xludf.DUMMYFUNCTION("""COMPUTED_VALUE"""),"Yudha KAI") -> Yudha KAI | D8: =IFERROR(__xludf.DUMMYFUNCTION("""COMPUTED_VALUE"""),"081299954736") -> 081299954736 | E8: =IFERROR(__xludf.DUMMYFUNCTION("""COMPUTED_VALUE"""),"Website") -> Website | F8: =IFERROR(__xludf.DUMMYFUNCTION("""COMPUTED_VALUE"""),"Closing") -> Closing | I8: =IFERROR(__xludf.DUMMYFUNCTION("""COMPUTED_VALUE"""),15.0) -> 15 | J8: =IFERROR(__xludf.DUMMYFUNCTION("""COMPUTED_VALUE"""),7275000.0) -> 7275000
A9: =IFERROR(__xludf.DUMMYFUNCTION("""COMPUTED_VALUE"""),46036.0) -> 46036 | B9: =IFERROR(__xludf.DUMMYFUNCTION("""COMPUTED_VALUE"""),"2601H008") -> 2601H008 | C9: =IFERROR(__xludf.DUMMYFUNCTION("""COMPUTED_VALUE"""),"Ricca") -> Ricca | D9: =IFERROR(__xludf.DUMMYFUNCTION("""COMPUTED_VALUE"""),"08998279499") -> 08998279499 | E9: =IFERROR(__xludf.DUMMYFUNCTION("""COMPUTED_VALUE"""),"Website") -> Website | F9: =IFERROR(__xludf.DUMMYFUNCTION("""COMPUTED_VALUE"""),"Gagal") -> Gagal | K9: =IFERROR(__xludf.DUMMYFUNCTION("""COMPUTED_VALUE"""),"tanya-tanya") -> tanya-tanya
A10: =IFERROR(__xludf.DUMMYFUNCTION("""COMPUTED_VALUE"""),46036.0) -> 46036 | B10: =IFERROR(__xludf.DUMMYFUNCTION("""COMPUTED_VALUE"""),"2601H009") -> 2601H009 | C10: =IFERROR(__xludf.DUMMYFUNCTION("""COMPUTED_VALUE"""),"Malazza") -> Malazza | D10: =IFERROR(__xludf.DUMMYFUNCTION("""COMPUTED_VALUE"""),"081311114375") -> 081311114375 | E10: =IFERROR(__xludf.DUMMYFUNCTION("""COMPUTED_VALUE"""),"Website") -> Website | F10: =IFERROR(__xludf.DUMMYFUNCTION("""COMPUTED_VALUE"""),"Gagal") -> Gagal | I10: =IFERROR(__xludf.DUMMYFUNCTION("""COMPUTED_VALUE"""),15.0) -> 15 | J10: =IFERROR(__xludf.DUMMYFUNCTION("""COMPUTED_VALUE"""),3750000.0) -> 3750000 | K10: =IFERROR(__xludf.DUMMYFUNCTION("""COMPUTED_VALUE"""),"sdh lebih fu 5x, tidak ada jawaban lebih lanjut") -> sdh lebih fu 5x, tidak ada jawaban lebih lanjut
A11: =IFERROR(__xludf.DUMMYFUNCTION("""COMPUTED_VALUE"""),46036.0) -> 46036 | B11: =IFERROR(__xludf.DUMMYFUNCTION("""COMPUTED_VALUE"""),"2601H010") -> 2601H010 | C11: =IFERROR(__xludf.DUMMYFUNCTION("""COMPUTED_VALUE"""),"Vica") -> Vica | D11: =IFERROR(__xludf.DUMMYFUNCTION("""COMPUTED_VALUE"""),"085716117974") -> 085716117974 | E11: =IFERROR(__xludf.DUMMYFUNCTION("""COMPUTED_VALUE"""),"Website") -> Website | F11: =IFERROR(__xludf.DUMMYFUNCTION("""COMPUTED_VALUE"""),"Gagal") -> Gagal | K11: =IFERROR(__xludf.DUMMYFUNCTION("""COMPUTED_VALUE"""),"next time") -> next time
A12: =IFERROR(__xludf.DUMMYFUNCTION("""COMPUTED_VALUE"""),46034.0) -> 46034 | B12: =IFERROR(__xludf.DUMMYFUNCTION("""COMPUTED_VALUE"""),"2601H011") -> 2601H011 | C12: =IFERROR(__xludf.DUMMYFUNCTION("""COMPUTED_VALUE"""),"Lily suharyani") -> Lily suharyani | D12: =IFERROR(__xludf.DUMMYFUNCTION("""COMPUTED_VALUE"""),"08159288885") -> 08159288885 | E12: =IFERROR(__xludf.DUMMYFUNCTION("""COMPUTED_VALUE"""),"Website") -> Website | F12: =IFERROR(__xludf.DUMMYFUNCTION("""COMPUTED_VALUE"""),"Gagal") -> Gagal | K12: =IFERROR(__xludf.DUMMYFUNCTION("""COMPUTED_VALUE"""),"tunggu cuaca mendukung, sudah FU ") -> tunggu cuaca mendukung, sudah FU
A13: =IFERROR(__xludf.DUMMYFUNCTION("""COMPUTED_VALUE"""),46036.0) -> 46036 | B13: =IFERROR(__xludf.DUMMYFUNCTION("""COMPUTED_VALUE"""),"2601H012") -> 2601H012 | C13: =IFERROR(__xludf.DUMMYFUNCTION("""COMPUTED_VALUE"""),"Ronny Quarto") -> Ronny Quarto | D13: =IFERROR(__xludf.DUMMYFUNCTION("""COMPUTED_VALUE"""),"08111441733") -> 08111441733 | E13: =IFERROR(__xludf.DUMMYFUNCTION("""COMPUTED_VALUE"""),"Website") -> Website | F13: =IFERROR(__xludf.DUMMYFUNCTION("""COMPUTED_VALUE"""),"Gagal") -> Gagal | K13: =IFERROR(__xludf.DUMMYFUNCTION("""COMPUTED_VALUE"""),"tanya-tanya") -> tanya-tanya
A14: =IFERROR(__xludf.DUMMYFUNCTION("""COMPUTED_VALUE"""),46035.0) -> 46035 | B14: =IFERROR(__xludf.DUMMYFUNCTION("""COMPUTED_VALUE"""),"2601H013") -> 2601H013 | C14: =IFERROR(__xludf.DUMMYFUNCTION("""COMPUTED_VALUE"""),"Fitri") -> Fitri | D14: =IFERROR(__xludf.DUMMYFUNCTION("""COMPUTED_VALUE"""),"082125355099") -> 082125355099 | E14: =IFERROR(__xludf.DUMMYFUNCTION("""COMPUTED_VALUE"""),"Website") -> Website | F14: =IFERROR(__xludf.DUMMYFUNCTION("""COMPUTED_VALUE"""),"Gagal") -> Gagal | G14: =IFERROR(__xludf.DUMMYFUNCTION("""COMPUTED_VALUE"""),"Kawah Ijen Only") -> Kawah Ijen Only | I14: =IFERROR(__xludf.DUMMYFUNCTION("""COMPUTED_VALUE"""),2.0) -> 2 | K14: =IFERROR(__xludf.DUMMYFUNCTION("""COMPUTED_VALUE"""),"next time") -> next time
A15: =IFERROR(__xludf.DUMMYFUNCTION("""COMPUTED_VALUE"""),46038.0) -> 46038 | B15: =IFERROR(__xludf.DUMMYFUNCTION("""COMPUTED_VALUE"""),"2601H014") -> 2601H014 | C15: =IFERROR(__xludf.DUMMYFUNCTION("""COMPUTED_VALUE"""),"Ilham") -> Ilham | D15: =IFERROR(__xludf.DUMMYFUNCTION("""COMPUTED_VALUE"""),"089696367463") -> 089696367463 | E15: =IFERROR(__xludf.DUMMYFUNCTION("""COMPUTED_VALUE"""),"Website") -> Website | F15: =IFERROR(__xludf.DUMMYFUNCTION("""COMPUTED_VALUE"""),"Gagal") -> Gagal | K15: =IFERROR(__xludf.DUMMYFUNCTION("""COMPUTED_VALUE"""),"tanya trip start jakarta, sudah FU 13 feb") -> tanya trip start jakarta, sudah FU 13 feb
A16: =IFERROR(__xludf.DUMMYFUNCTION("""COMPUTED_VALUE"""),46038.0) -> 46038 | B16: =IFERROR(__xludf.DUMMYFUNCTION("""COMPUTED_VALUE"""),"2601H015") -> 2601H015 | C16: =IFERROR(__xludf.DUMMYFUNCTION("""COMPUTED_VALUE"""),"Neneng Juraidah") -> Neneng Juraidah | D16: =IFERROR(__xludf.DUMMYFUNCTION("""COMPUTED_VALUE"""),"08111339362") -> 08111339362 | E16: =IFERROR(__xludf.DUMMYFUNCTION("""COMPUTED_VALUE"""),"Website") -> Website | F16: =IFERROR(__xludf.DUMMYFUNCTION("""COMPUTED_VALUE"""),"Qualified") -> Qualified | G16: =IFERROR(__xludf.DUMMYFUNCTION("""COMPUTED_VALUE"""),"3H2M Custom") -> 3H2M Custom | I16: =IFERROR(__xludf.DUMMYFUNCTION("""COMPUTED_VALUE"""),7.0) -> 7 | J16: =IFERROR(__xludf.DUMMYFUNCTION("""COMPUTED_VALUE"""),1.7108888E7) -> 17108888 | K16: =IFERROR(__xludf.DUMMYFUNCTION("""COMPUTED_VALUE"""),"FU lagi setelah lebaran, fu 1 juli") -> FU lagi setelah lebaran, fu 1 juli | L16: =IFERROR(__xludf.DUMMYFUNCTION("""COMPUTED_VALUE"""),"https://docs.google.com/document/d/12c3T3MfymkdkNi76muU-IvFXF9oY3jOtG4N7_5v9-OI/edit?usp=drivesdk") -> https://docs.google.com/document/d/12c3T3MfymkdkNi76muU-IvFXF9oY3jOtG4N7_5v9-OI/edit?usp=drivesdk
A17: =IFERROR(__xludf.DUMMYFUNCTION("""COMPUTED_VALUE"""),46038.0) -> 46038 | B17: =IFERROR(__xludf.DUMMYFUNCTION("""COMPUTED_VALUE"""),"2601H016") -> 2601H016 | C17: =IFERROR(__xludf.DUMMYFUNCTION("""COMPUTED_VALUE"""),"Nujiya") -> Nujiya | D17: =IFERROR(__xludf.DUMMYFUNCTION("""COMPUTED_VALUE"""),"085716716929") -> 085716716929 | E17: =IFERROR(__xludf.DUMMYFUNCTION("""COMPUTED_VALUE"""),"Website") -> Website | F17: =IFERROR(__xludf.DUMMYFUNCTION("""COMPUTED_VALUE"""),"Gagal") -> Gagal | G17: =IFERROR(__xludf.DUMMYFUNCTION("""COMPUTED_VALUE"""),"OT 3H2M") -> OT 3H2M | K17: =IFERROR(__xludf.DUMMYFUNCTION("""COMPUTED_VALUE"""),"tanya-tanya OT, FU tgl 6 feb") -> tanya-tanya OT, FU tgl 6 feb
A18: =IFERROR(__xludf.DUMMYFUNCTION("""COMPUTED_VALUE"""),46039.0) -> 46039 | B18: =IFERROR(__xludf.DUMMYFUNCTION("""COMPUTED_VALUE"""),"2601H017") -> 2601H017 | C18: =IFERROR(__xludf.DUMMYFUNCTION("""COMPUTED_VALUE"""),"Tanpa Nama") -> Tanpa Nama | D18: =IFERROR(__xludf.DUMMYFUNCTION("""COMPUTED_VALUE"""),"087773897140") -> 087773897140 | E18: =IFERROR(__xludf.DUMMYFUNCTION("""COMPUTED_VALUE"""),"Website") -> Website | F18: =IFERROR(__xludf.DUMMYFUNCTION("""COMPUTED_VALUE"""),"Gagal") -> Gagal | G18: =IFERROR(__xludf.DUMMYFUNCTION("""COMPUTED_VALUE"""),"Full Day Trip I, KW, B") -> Full Day Trip I, KW, B | I18: =IFERROR(__xludf.DUMMYFUNCTION("""COMPUTED_VALUE"""),1.0) -> 1 | K18: =IFERROR(__xludf.DUMMYFUNCTION("""COMPUTED_VALUE"""),"Masih dipertimbangkan karena cuman sendiri") -> Masih dipertimbangkan karena cuman sendiri
A19: =IFERROR(__xludf.DUMMYFUNCTION("""COMPUTED_VALUE"""),46041.0) -> 46041 | B19: =IFERROR(__xludf.DUMMYFUNCTION("""COMPUTED_VALUE"""),"2601H018") -> 2601H018 | C19: =IFERROR(__xludf.DUMMYFUNCTION("""COMPUTED_VALUE"""),"Tanpa Nama 2") -> Tanpa Nama 2 | D19: =IFERROR(__xludf.DUMMYFUNCTION("""COMPUTED_VALUE"""),"0817190695") -> 0817190695 | E19: =IFERROR(__xludf.DUMMYFUNCTION("""COMPUTED_VALUE"""),"Lainnya") -> Lainnya | F19: =IFERROR(__xludf.DUMMYFUNCTION("""COMPUTED_VALUE"""),"Gagal") -> Gagal | K19: =IFERROR(__xludf.DUMMYFUNCTION("""COMPUTED_VALUE"""),"menarik pesan") -> menarik pesan
A20: =IFERROR(__xludf.DUMMYFUNCTION("""COMPUTED_VALUE"""),46041.0) -> 46041 | B20: =IFERROR(__xludf.DUMMYFUNCTION("""COMPUTED_VALUE"""),"2601H019") -> 2601H019 | C20: =IFERROR(__xludf.DUMMYFUNCTION("""COMPUTED_VALUE"""),"Joehernie") -> Joehernie | D20: =IFERROR(__xludf.DUMMYFUNCTION("""COMPUTED_VALUE"""),"085947419056") -> 085947419056 | E20: =IFERROR(__xludf.DUMMYFUNCTION("""COMPUTED_VALUE"""),"Website") -> Website | F20: =IFERROR(__xludf.DUMMYFUNCTION("""COMPUTED_VALUE"""),"Gagal") -> Gagal | K20: =IFERROR(__xludf.DUMMYFUNCTION("""COMPUTED_VALUE"""),"tanya-tanya, FU belum ada respond") -> tanya-tanya, FU belum ada respond
A21: =IFERROR(__xludf.DUMMYFUNCTION("""COMPUTED_VALUE"""),46041.0) -> 46041 | B21: =IFERROR(__xludf.DUMMYFUNCTION("""COMPUTED_VALUE"""),"2601H020") -> 2601H020 | C21: =IFERROR(__xludf.DUMMYFUNCTION("""COMPUTED_VALUE"""),"Nawaf") -> Nawaf | D21: =IFERROR(__xludf.DUMMYFUNCTION("""COMPUTED_VALUE"""),"087787049591") -> 087787049591 | E21: =IFERROR(__xludf.DUMMYFUNCTION("""COMPUTED_VALUE"""),"Website") -> Website | F21: =IFERROR(__xludf.DUMMYFUNCTION("""COMPUTED_VALUE"""),"Gagal") -> Gagal | G21: =IFERROR(__xludf.DUMMYFUNCTION("""COMPUTED_VALUE"""),"Half Day Trip Ijen") -> Half Day Trip Ijen | I21: =IFERROR(__xludf.DUMMYFUNCTION("""COMPUTED_VALUE"""),20.0) -> 20 | K21: =IFERROR(__xludf.DUMMYFUNCTION("""COMPUTED_VALUE"""),"lain kali ke banyuwangi") -> lain kali ke banyuwangi
A22: =IFERROR(__xludf.DUMMYFUNCTION("""COMPUTED_VALUE"""),46036.0) -> 46036 | B22: =IFERROR(__xludf.DUMMYFUNCTION("""COMPUTED_VALUE"""),"2601H021") -> 2601H021 | C22: =IFERROR(__xludf.DUMMYFUNCTION("""COMPUTED_VALUE"""),"Firyaal Nadhira") -> Firyaal Nadhira | D22: =IFERROR(__xludf.DUMMYFUNCTION("""COMPUTED_VALUE"""),"08978426315") -> 08978426315 | E22: =IFERROR(__xludf.DUMMYFUNCTION("""COMPUTED_VALUE"""),"Website") -> Website | F22: =IFERROR(__xludf.DUMMYFUNCTION("""COMPUTED_VALUE"""),"Gagal") -> Gagal | G22: =IFERROR(__xludf.DUMMYFUNCTION("""COMPUTED_VALUE"""),"3H2M Custom") -> 3H2M Custom | I22: =IFERROR(__xludf.DUMMYFUNCTION("""COMPUTED_VALUE"""),9.0) -> 9 | J22: =IFERROR(__xludf.DUMMYFUNCTION("""COMPUTED_VALUE"""),1.2204E7) -> 12204000 | K22: =IFERROR(__xludf.DUMMYFUNCTION("""COMPUTED_VALUE"""),"masih belum ada jawaban") -> masih belum ada jawaban
A23: =IFERROR(__xludf.DUMMYFUNCTION("""COMPUTED_VALUE"""),46036.0) -> 46036 | B23: =IFERROR(__xludf.DUMMYFUNCTION("""COMPUTED_VALUE"""),"2601H022") -> 2601H022 | C23: =IFERROR(__xludf.DUMMYFUNCTION("""COMPUTED_VALUE"""),"JH") -> JH | D23: =IFERROR(__xludf.DUMMYFUNCTION("""COMPUTED_VALUE"""),"081310300909") -> 081310300909 | E23: =IFERROR(__xludf.DUMMYFUNCTION("""COMPUTED_VALUE"""),"Website") -> Website | F23: =IFERROR(__xludf.DUMMYFUNCTION("""COMPUTED_VALUE"""),"Gagal") -> Gagal | K23: =IFERROR(__xludf.DUMMYFUNCTION("""COMPUTED_VALUE"""),"tanya-tanya OT I, next time ke Bwi") -> tanya-tanya OT I, next time ke Bwi
A24: =IFERROR(__xludf.DUMMYFUNCTION("""COMPUTED_VALUE"""),46043.0) -> 46043 | B24: =IFERROR(__xludf.DUMMYFUNCTION("""COMPUTED_VALUE"""),"2601H023") -> 2601H023 | C24: =IFERROR(__xludf.DUMMYFUNCTION("""COMPUTED_VALUE"""),"Jameelali") -> Jameelali | D24: =IFERROR(__xludf.DUMMYFUNCTION("""COMPUTED_VALUE"""),"08888540196") -> 08888540196 | E24: =IFERROR(__xludf.DUMMYFUNCTION("""COMPUTED_VALUE"""),"Website") -> Website | F24: =IFERROR(__xludf.DUMMYFUNCTION("""COMPUTED_VALUE"""),"Gagal") -> Gagal | G24: =IFERROR(__xludf.DUMMYFUNCTION("""COMPUTED_VALUE"""),"Fullday Trip D, GI, PM") -> Fullday Trip D, GI, PM | I24: =IFERROR(__xludf.DUMMYFUNCTION("""COMPUTED_VALUE"""),2.0) -> 2 | J24: =IFERROR(__xludf.DUMMYFUNCTION("""COMPUTED_VALUE"""),1512000.0) -> 1512000 | K24: =IFERROR(__xludf.DUMMYFUNCTION("""COMPUTED_VALUE"""),"tanggal sudah lewat, tidak balas waktu FU") -> tanggal sudah lewat, tidak balas waktu FU
A25: =IFERROR(__xludf.DUMMYFUNCTION("""COMPUTED_VALUE"""),46043.0) -> 46043 | B25: =IFERROR(__xludf.DUMMYFUNCTION("""COMPUTED_VALUE"""),"2601H024") -> 2601H024 | C25: =IFERROR(__xludf.DUMMYFUNCTION("""COMPUTED_VALUE"""),"Hany Sintya") -> Hany Sintya | D25: =IFERROR(__xludf.DUMMYFUNCTION("""COMPUTED_VALUE"""),"085211221371") -> 085211221371 | E25: =IFERROR(__xludf.DUMMYFUNCTION("""COMPUTED_VALUE"""),"Website") -> Website | F25: =IFERROR(__xludf.DUMMYFUNCTION("""COMPUTED_VALUE"""),"Gagal") -> Gagal | K25: =IFERROR(__xludf.DUMMYFUNCTION("""COMPUTED_VALUE""")," ")
A26: =IFERROR(__xludf.DUMMYFUNCTION("""COMPUTED_VALUE"""),46043.0) -> 46043 | B26: =IFERROR(__xludf.DUMMYFUNCTION("""COMPUTED_VALUE"""),"2601H025") -> 2601H025 | C26: =IFERROR(__xludf.DUMMYFUNCTION("""COMPUTED_VALUE"""),"Hilman Febriana") -> Hilman Febriana | D26: =IFERROR(__xludf.DUMMYFUNCTION("""COMPUTED_VALUE"""),"085161498070") -> 085161498070 | E26: =IFERROR(__xludf.DUMMYFUNCTION("""COMPUTED_VALUE"""),"Website") -> Website | F26: =IFERROR(__xludf.DUMMYFUNCTION("""COMPUTED_VALUE"""),"Gagal") -> Gagal | G26: =IFERROR(__xludf.DUMMYFUNCTION("""COMPUTED_VALUE"""),"3H2M Opsi B") -> 3H2M Opsi B | I26: =IFERROR(__xludf.DUMMYFUNCTION("""COMPUTED_VALUE"""),5.0) -> 5 | J26: =IFERROR(__xludf.DUMMYFUNCTION("""COMPUTED_VALUE"""),1.0825E7) -> 10825000 | K26: =IFERROR(__xludf.DUMMYFUNCTION("""COMPUTED_VALUE"""),"tidak ada balasan, sudah fu") -> tidak ada balasan, sudah fu | L26: =IFERROR(__xludf.DUMMYFUNCTION("""COMPUTED_VALUE"""),"https://docs.google.com/document/d/1MD4vKt2ZQWqX7YfPlQojeuYcf_boCFIM6q-CP2rB4XM/edit?usp=drivesdk") -> https://docs.google.com/document/d/1MD4vKt2ZQWqX7YfPlQojeuYcf_boCFIM6q-CP2rB4XM/edit?usp=drivesdk
A27: =IFERROR(__xludf.DUMMYFUNCTION("""COMPUTED_VALUE"""),46039.0) -> 46039 | B27: =IFERROR(__xludf.DUMMYFUNCTION("""COMPUTED_VALUE"""),"2601H026") -> 2601H026 | C27: =IFERROR(__xludf.DUMMYFUNCTION("""COMPUTED_VALUE"""),"Kirina") -> Kirina | D27: =IFERROR(__xludf.DUMMYFUNCTION("""COMPUTED_VALUE"""),"0811822173") -> 0811822173 | E27: =IFERROR(__xludf.DUMMYFUNCTION("""COMPUTED_VALUE"""),"Website") -> Website | F27: =IFERROR(__xludf.DUMMYFUNCTION("""COMPUTED_VALUE"""),"Gagal") -> Gagal | G27: =IFERROR(__xludf.DUMMYFUNCTION("""COMPUTED_VALUE"""),"3H2M Custom") -> 3H2M Custom | I27: =IFERROR(__xludf.DUMMYFUNCTION("""COMPUTED_VALUE"""),17.0) -> 17 | J27: =IFERROR(__xludf.DUMMYFUNCTION("""COMPUTED_VALUE"""),2.295E7) -> 22950000 | K27: =IFERROR(__xludf.DUMMYFUNCTION("""COMPUTED_VALUE"""),"ganti destinasi ke malaysia") -> ganti destinasi ke malaysia | L27: =IFERROR(__xludf.DUMMYFUNCTION("""COMPUTED_VALUE"""),"https://docs.google.com/document/d/1Cg-pxi4TaA4xqPYFa-eNTbbuCPVGyyJvF8dGS01Kl1M/edit?usp=drivesdk") -> https://docs.google.com/document/d/1Cg-pxi4TaA4xqPYFa-eNTbbuCPVGyyJvF8dGS01Kl1M/edit?usp=drivesdk
A28: =IFERROR(__xludf.DUMMYFUNCTION("""COMPUTED_VALUE"""),46046.0) -> 46046 | B28: =IFERROR(__xludf.DUMMYFUNCTION("""COMPUTED_VALUE"""),"2601H027") -> 2601H027 | C28: =IFERROR(__xludf.DUMMYFUNCTION("""COMPUTED_VALUE"""),"Titin Karyati") -> Titin Karyati | D28: =IFERROR(__xludf.DUMMYFUNCTION("""COMPUTED_VALUE"""),"085285949394") -> 085285949394 | E28: =IFERROR(__xludf.DUMMYFUNCTION("""COMPUTED_VALUE"""),"Lainnya") -> Lainnya | F28: =IFERROR(__xludf.DUMMYFUNCTION("""COMPUTED_VALUE"""),"Qualified") -> Qualified | G28: =IFERROR(__xludf.DUMMYFUNCTION("""COMPUTED_VALUE"""),"2D1N Custom") -> 2D1N Custom | I28: =IFERROR(__xludf.DUMMYFUNCTION("""COMPUTED_VALUE"""),25.0) -> 25 | J28: =IFERROR(__xludf.DUMMYFUNCTION("""COMPUTED_VALUE"""),3.175E7) -> 31750000 | K28: =IFERROR(__xludf.DUMMYFUNCTION("""COMPUTED_VALUE"""),"FU lagi mendekati FU 20 Agustus ") -> FU lagi mendekati FU 20 Agustus
A29: =IFERROR(__xludf.DUMMYFUNCTION("""COMPUTED_VALUE"""),46045.0) -> 46045 | B29: =IFERROR(__xludf.DUMMYFUNCTION("""COMPUTED_VALUE"""),"2601H028") -> 2601H028 | C29: =IFERROR(__xludf.DUMMYFUNCTION("""COMPUTED_VALUE"""),"Jennifer Jones") -> Jennifer Jones | D29: =IFERROR(__xludf.DUMMYFUNCTION("""COMPUTED_VALUE"""),"087887878902") -> 087887878902 | E29: =IFERROR(__xludf.DUMMYFUNCTION("""COMPUTED_VALUE"""),"Website") -> Website | F29: =IFERROR(__xludf.DUMMYFUNCTION("""COMPUTED_VALUE"""),"Closing") -> Closing | G29: =IFERROR(__xludf.DUMMYFUNCTION("""COMPUTED_VALUE"""),"OT I") -> OT I | H29: =IFERROR(__xludf.DUMMYFUNCTION("""COMPUTED_VALUE"""),46048.0) -> 46048 | I29: =IFERROR(__xludf.DUMMYFUNCTION("""COMPUTED_VALUE"""),1.0) -> 1 | J29: =IFERROR(__xludf.DUMMYFUNCTION("""COMPUTED_VALUE"""),325000.0) -> 325000 | K29: =IFERROR(__xludf.DUMMYFUNCTION("""COMPUTED_VALUE"""),"order") -> order
